Workbook

Sheet Income Statement
A1: Income Statement | B1: TTM | C1: 12/31/2024 | D1: 12/31/2023 | E1: 12/31/2022 | F1: 12/31/2021
A2: Total Revenue | B2: 691330000 | C2: 637959000 | D2: 574785000 | E2: 513983000 | F2: 469822000
A3: Operating Revenue | B3: 691330000 | C3: 637959000 | D3: 574785000 | E3: 513983000 | F3: 469822000
A4: Cost of Revenue | B4: 345348000 | C4: 326288000 | D4: 304739000 | E4: 288831000 | F4: 272344000
A5: Gross Profit | B5: 345982000 | C5: 311671000 | D5: 270046000 | E5: 225152000 | F5: 197478000
A6: Operating Expense | B6: 269781000 | C6: 243078000 | D6: 233194000 | E6: 212904000 | F6: 172599000
A7: Selling General and Administrative | B7: 57320000 | C7: 55266000 | D7: 56186000 | E7: 54129000 | F7: 41374000
A8: General & Administrative Expense | B8: 11331000 | C8: 11359000 | D8: 11816000 | E8: 11891000 | F8: 8823000
A9: Other G and A | B9: 11331000 | C9: 11359000 | D9: 11816000 | E9: 11891000 | F9: 8823000
A10: Selling & Marketing Expense | B10: 45989000 | C10: 43907000 | D10: 44370000 | E10: 42238000 | F10: 32551000
A11: Other Operating Expenses | B11: 212461000 | C11: 187812000 | D11: 177008000 | E11: 158775000 | F11: 131225000
A12: Operating Income | B12: 76201000 | C12: 68593000 | D12: 36852000 | E12: 12248000 | F12: 24879000
A13: Net Non Operating Interest Income Expense | B13: 2334000 | C13: 2271000 | D13: -233000 | E13: -1378000 | F13: -1361000
... A47: Tax Effect of Unusual Items | B47: 2596728.3 | C47: -246971.24 | D47: 211380.04 | E47: -3415860 | F47: 1839997.2

Sheet Balance Sheet
A1: Balance Sheet | B1: 12/31/2024 | C1: 12/31/2023 | D1: 12/31/2022 | E1: 12/31/2021
A2: Total Assets | B2: 624894000 | C2: 527854000 | D2: 462675000 | E2: 420549000
A3: Current Assets | B3: 190867000 | C3: 172351000 | D3: 146791000 | E3: 161580000
A4: Cash, Cash Equivalents & Short Term Investments | B4: 101202000 | C4: 86780000 | D4: 70026000 | E4: 96049000
A5: Cash And Cash Equivalents | B5: 78779000 | C5: 73387000 | D5: 53888000 | E5: 36220000
A6: Other Short Term Investments | B6: 22423000 | C6: 13393000 | D6: 16138000 | E6: 59829000
A7: Receivables | B7: 55451000 | C7: 52253000 | D7: 42360000 | E7: 32891000
A8: Accounts receivable | B8: 55451000 | C8: 52253000 | D8: 42360000 | E8: 32891000
A9: Gross Accounts Receivable | B9: 57451000 | C9: 53953000 | D9: 43760000 | E9: 33991000
A10: Allowance For Doubtful Accounts Receivable | B10: -2000000 | C10: -1700000 | D10: -1400000 | E10: -1100000
A11: Inventory | B11: 34214000 | C11: 33318000 | D11: 34405000 | E11: 32640000
A12: Finished Goods | E12: 32640000
A13: Other Inventories | B13: 37214000 | C13: 36318000 | D13: 37205000 | E13: 35240000
A14: Inventories Adjustments Allowances | B14: -3000000 | C14: -3000000 | D14: -2800000 | E14: -2600000
A15: Total non-current assets | B15: 434027000 | C15: 355503000 | D15: 315884000 | E15: 258969000
A16: Net PPE | B16: 328806000 | C16: 276690000 | D16: 252838000 | E16: 216363000
A17: Gross PPE | B17: 470196000 | C17: 396801000 | D17: 349853000 | E17: 294882000
A18: Properties | B18: 123039000 | C18: 105293000 | D18: 91650000 | E18: 81104000
A19: Land And Improvements | C19: 105293000 | D19: 91650000 | E19: 81104000
A20: Machinery Furniture Equipment | E20: 128683000
A21: Other Properties | B21: 300521000 | C21: 262668000 | D21: 228183000 | E21: 188883000
A22: Construction in Progress | B22: 46636000 | C22: 28840000 | D22: 30020000 | E22: 24895000
A23: Accumulated Depreciation | B23: -141390000 | C23: -120111000 | D23: -97015000 | E23: -78519000
A24: Goodwill And Other Intangible Assets | B24: 31676000 | C24: 30476000 | D24: 26385000 | E24: 20478000
A25: Goodwill | B25: 23074000 | C25: 22789000 | D25: 20288000 | E25: 15371000
A26: Other Intangible Assets | B26: 8602000 | C26: 7687000 | D26: 6097000 | E26: 5107000
A27: Other Non Current Assets | B27: 73545000 | C27: 48337000 | D27: 36661000 | E27: 22128000
A28: Total Liabilities Net Minority Interest | B28: 338924000 | C28: 325979000 | D28: 316632000 | E28: 282304000
A29: Current Liabilities | B29: 179431000 | C29: 164917000 | D29: 155393000 | E29: 142266000
A30: Payables And Accrued Expenses | B30: 161328000 | C30: 149690000 | D30: 142166000 | E30: 130439000
A31: Payables | B31: 94363000 | C31: 84981000 | D31: 79600000 | E31: 78664000
A32: Accounts Payable | B32: 94363000 | C32: 84981000 | D32: 79600000 | E32: 78664000
... A58: Total Debt | B58: 130900000 | C58: 135611000 | D58: 140118000 | E58: 116395000
A59: Net Debt | D59: 13262000 | E59: 12524000
A60: Share Issued | B60: 11108000 | C60: 10898000 | D60: 10757000 | E60: 10640000
A61: Ordinary Shares Number | B61: 10593000 | C61: 10383000 | D61: 10242000 | E61: 10180000
A62: Treasury Shares Number | B62: 515000 | C62: 515000 | D62: 515000 | E62: 460000

Sheet Cash Flow Statement
A1: Cash Flow Statement | B1: 12/31/2024 | C1: 12/31/2023 | D1: 12/31/2022 | E1: 12/31/2021 | F1: 12/31/2020
A2: Operating Cash Flow | B2: 130691000 | C2: 115877000 | D2: 84946000 | E2: 46752000 | F2: 46327000
A3: Cash Flow from Continuing Operating Activities | B3: 130691000 | C3: 115877000 | D3: 84946000 | E3: 46752000 | F3: 46327000
A4: Net Income from Continuing Operations | B4: 76482000 | C4: 59248000 | D4: 30425000 | E4: -2722000 | F4: 33364000
A5: Depreciation Amortization Depletion | B5: 61916000 | C5: 52795000 | D5: 48663000 | E5: 41921000 | F5: 34433000
A6: Depreciation & amortization | B6: 61916000 | C6: 52795000 | D6: 48663000 | E6: 41921000 | F6: 34433000
A7: Deferred Tax | B7: 9040000 | C7: -4648000 | D7: -5876000 | E7: -8148000 | F7: -310000
A8: Deferred Income Tax | B8: 9040000 | C8: -4648000 | D8: -5876000 | E8: -8148000 | F8: -310000
A9: Stock based compensation | B9: 20065000 | C9: 22011000 | D9: 24023000 | E9: 19621000 | F9: 12757000
A10: Other non-cash items | B10: -14673000 | C10: 2012000 | D10: -748000 | E10: 16966000 | F10: -14306000
A11: Change in working capital | B11: -22139000 | C11: -15541000 | D11: -11541000 | E11: -20886000 | F11: -19611000
A12: Change in Receivables | B12: -5878000 | C12: -3249000 | D12: -8348000 | E12: -8622000 | F12: -9145000
A13: Changes in Account Receivables | B13: -5878000 | C13: -3249000 | D13: -8348000 | E13: -8622000 | F13: -9145000
... A39: Short Term Debt Payments | B39: -7907000 | C39: -5060000 | D39: -25677000 | E39: -37554000 | F39: -7753000
A40: Net Common Stock Issuance | C40: 0 | D40: 0 | E40: -6000000 | F40: 0
A41: Common Stock Payments | C41: 0 | D41: 0 | E41: -6000000 | F41: 0
A42: Net Other Financing Charges | D42: -271000 | E42: -248000 | F42: -162000
A43: End Cash Position | B43: 70687000 | C43: 82312000 | D43: 73890000 | E43: 54253000 | F43: 36477000
A44: Changes in Cash | B44: -7990000 | C44: 9723000 | D44: 19234000 | E44: 18869000 | F44: -5536000
A45: Effect of Exchange Rate Changes | B45: -223000 | C45: -1301000 | D45: 403000 | E45: -1093000 | F45: -364000
A46: Beginning Cash Position | B46: 78677000 | C46: 73890000 | D46: 54253000 | E46: 36477000 | F46: 42377000
A47: Income Tax Paid Supplemental Data | B47: 10920000 | C47: 12308000 | D47: 11179000 | E47: 6035000 | F47: 3688000
A48: Interest Paid Supplemental Data | B48: 2157000 | C48: 2364000 | D48: 3112000 | E48: 2142000 | F48: 1772000
A49: Capital Expenditure | B49: -120131000 | C49: -82999000 | D49: -52729000 | E49: -63645000 | F49: -61053000
A50: Issuance of Debt | B50: 10431000 | C50: 5142000 | D50: 18129000 | E50: 62719000 | F50: 26959000
A51: Repayment of Debt | B51: -16340000 | C51: -16954000 | D51: -34008000 | E51: -47001000 | F51: -20668000
A52: Repurchase of Capital Stock | C52: 0 | D52: 0 | E52: -6000000 | F52: 0
A53: Free Cash Flow | B53: 10560000 | C53: 32878000 | D53: 32217000 | E53: -16893000 | F53: -14726000

Sheet Ratios
A1: Ratio Category | B1: Ratio Name | C1: Formula | D1: 2022 | E1: 2023 | F1: 2024
A2: Profitability | B2: Gross Profit Margin | C2: Gross Profit / Revenue | D2: ='Income Statement'!E5/Table1[[#This Row],[12/31/2022]] -> 0.4380534 | E2: ='Income Statement'!D5/Table1[[#This Row],[12/31/2023]] -> 0.46982089 | F2: ='Income Statement'!C5/Table1[[#This Row],[12/31/2024]] -> 0.48854393
B3: Operating Margin | C3: Operating Income / Revenue | D3: ='Income Statement'!E12/'Income Statement'!E2 -> 0.023829582 | E3: ='Income Statement'!D12/'Income Statement'!D2 -> 0.064114408 | F3: ='Income Statement'!C12/'Income Statement'!C2 -> 0.10751945
B4: Net Profit Margin | C4: Net Income / Revenue | D4: ='Income Statement'!E23/'Income Statement'!E2 -> -0.005295895 | E4: ='Income Statement'!D23/'Income Statement'!D2 -> 0.052932836 | F4: ='Income Statement'!C23/'Income Statement'!C2 -> 0.092871172
B5: ROE | C5: Net Income / Total Equity | D5: ='Income Statement'!E23/'Balance Sheet'!D42 -> -0.018638346 | E5: ='Income Statement'!D23/'Balance Sheet'!C41 -> 0.15071207 | F5: ='Income Statement'!C23/'Balance Sheet'!B41 -> 0.20718257
B6: ROA | C6: Net Income / Total Assets | D6: ='Income Statement'!E23/'Balance Sheet'!D2 -> -0.0058831793 | E6: ='Income Statement'!D23/'Balance Sheet'!C2 -> 0.057639044 | F6: ='Income Statement'!C23/'Balance Sheet'!B2 -> 0.09481288
A7: Liquidity | B7: Current Ratio | C7: Current Assets / Current Liabilities | D7: ='Balance Sheet'!D3/'Balance Sheet'!D29 -> 0.94464358 | E7: ='Balance Sheet'!C3/'Balance Sheet'!C29 -> 1.0450772 | F7: ='Balance Sheet'!B3/'Balance Sheet'!B29 -> 1.0637348
B8: Quick Ratio | C8: (Current Assets - Inventory) / Current Liabilities | D8: =('Balance Sheet'!D3-'Balance Sheet'!D11)/'Balance Sheet'!D29 -> 0.72323721 | E8: =('Balance Sheet'!C3-'Balance Sheet'!C11)/'Balance Sheet'!C29 -> 0.84304832 | F8: =('Balance Sheet'!B3-'Balance Sheet'!B11)/'Balance Sheet'!B29 -> 0.87305427
A9: Leverage | B9: Debt Ratio | C9: Total Liabilities / Total Assets | D9: ='Balance Sheet'!D28/'Balance Sheet'!D2 -> 0.68435079 | E9: ='Balance Sheet'!C28/'Balance Sheet'!C2 -> 0.61755523 | F9: ='Balance Sheet'!B28/'Balance Sheet'!B2 -> 0.54237039
B10: Debt-to-Equity | C10: Total Liabilities / Total Equity | D10: ='Balance Sheet'!D28/'Balance Sheet'!D41 -> 2.1680738 | E10: ='Balance Sheet'!C28/'Balance Sheet'!C41 -> 1.6147567 | F10: ='Balance Sheet'!B28/'Balance Sheet'!B41 -> 1.1851733
B11: EPS | C11: TTM Net Income/TTM Basic Average Shares | F11: ='Income Statement'!B23/'Income Statement'!B29 -> 7.2042388

Sheet Dashboards
A16: Revenue vs Net Income Line Chart | B16: Column1 | C16: Column2 | E16: ROE & Profit Margins Trend | F16: Column1 | G16: Column2 | H16: Column3 | J16: Debt-to-Equity Ratio Trend | K16: Column1 | M16: Cash Flow Trend | N16: Column1 | O16: Column2 | P16: Column3
A17: Year | B17: Revenue | C17: Net Income | E17: Year | F17: ROE | G17: Operating Margin | H17: Net Profit Margin | J17: Year | K17: Debt-to-Equity Ratio | M17: Year | N17: Operating Cash Flow | O17: Investing Cash Flow | P17: Financing Cash Flow
A18: 2021 | B18: 469822000 | C18: 33364000 | E18: 2022 | F18: -0.018638346 | G18: 0.023829582 | H18: -0.005295895 | J18: 2022 | K18: 2.1680738 | M18: 2020 | N18: 46327000 | O18: -58154000 | P18: 6291000
A19: 2022 | B19: 513983000 | C19: -2722000 | E19: 2023 | F19: 0.15071207 | G19: 0.064114408 | H19: 0.052932836 | J19: 2023 | K19: 1.6147567 | M19: 2021 | N19: 46752000 | O19: -37601000 | P19: 9718000
A20: 2023 | B20: 574785000 | C20: 30425000 | E20: 2024 | F20: 0.20718257 | G20: 0.10751945 | H20: 0.092871172 | J20: 2024 | K20: 1.1851733 | M20: 2022 | N20: 84946000 | O20: -49833000 | P20: -15879000
A21: 2024 | B21: 637959000 | C21: 59248000 | M21: 2023 | N21: 115877000 | O21: -94342000 | P21: -11812000
M22: 2024 | N22: 130691000 | O22: -132743000 | P22: -5938000

Sheet Conclusion
