Workbook

Sheet Summary
A1: MASTERCARD FINANCIAL MODEL – EXECUTIVE SUMMARY
A2: (All figures in USD Millions unless stated otherwise)
A3: Company Overview:
A4: Company Name | B4: Mastercard Inc
A5: Industry | B5: Payment Technology
A6: Forecast Period | B6: 2025-2029
A7: Valuation Methods | B7: DCF,FCFF,DDM,Relative Valuation
A8: Shares Outstanding | B8: ='Profit Loss'!F24 -> 927
A9: Current Share Price | B9: =B52 -> 450
A10: Market Capitalization | B10: =B8*B9 -> 417150
A12: Valuation Multiples | B12: 2024
A13: Enterprise Value | B13: =B22 -> 417150
A14: P/E Ratio | B14: =B9/B32 -> 32.397408
A15: EV/EBITDA | B15: =B13/'Profit Loss'!F25 -> 25.314036
A16: Price / Book | B16: =B9/B17 -> 64.029163
A17: Book Value Per Share | B17: =Balance_Sheet!F41/'Profit Loss'!F24 -> 7.0280475
A19: Key Valuation Summary
A20: Metric | B20: Value
A21: Market Cap | B21: =B10 -> 417150
A22: Enterprise Value | B22: =B10 -> 417150
A23: P/E | B23: =B14 -> 32.397408
A24: EV/EBITDA | B24: =B15 -> 25.314036
A25: Target Price | B25: =B53 -> 378.19635
A26: Upside / Downside | B26: =B54 -> -0.15956367
A28: Financial Highlights
A29: Metric | B29: 2024 | C29: 2025E | D29: 2026E | E29: 2027E | F29: 2028E | G29: 2029E
A30: Revenue | B30: ='Profit Loss'!F4 -> 28167 | C30: ='Profit Loss'!G4 -> 31265.37 | D30: ='Profit Loss'!H4 -> 34391.907 | E30: ='Profit Loss'!I4 -> 37487.179 | F30: ='Profit Loss'!J4 -> 40486.153 | G30: ='Profit Loss'!K4 -> 43320.184
A31: Net Profit | B31: ='Profit Loss'!F20 -> 12874 | C31: ='Profit Loss'!G20 -> 14041.325 | D31: ='Profit Loss'!H20 -> 15786.104 | E31: ='Profit Loss'!I20 -> 17411.45 | F31: ='Profit Loss'!J20 -> 19017.164 | G31: ='Profit Loss'!K20 -> 20568.896
A32: EPS | B32: ='Profit Loss'!F23 -> 13.89 | C32: ='Profit Loss'!G23 -> 15.456184 | D32: ='Profit Loss'!H23 -> 17.731402 | E32: ='Profit Loss'!I23 -> 19.95616 | F32: ='Profit Loss'!J23 -> 22.241379 | G32: ='Profit Loss'!K23 -> 24.547138
A33: Operating Margin | B33: ='Profit Loss'!F26 -> 0.55320055 | C33: ='Profit Loss'!G26 -> 0.55 | D33: ='Profit Loss'!H26 -> 0.56 | E33: ='Profit Loss'!I26 -> 0.565 | F33: ='Profit Loss'!J26 -> 0.57 | G33: ='Profit Loss'!K26 -> 0.575
A35: Growth & Profitability
A36: Key Insights
A37: Revenue CAGR | B37: ='CAGR Projections'!G4 -> 0.16481028
A38: EPS CAGR | B38: ='CAGR Projections'!G7 -> 0.21419038
A39: Average ROE | B39: =AVERAGE(Ratios!C13:G13) -> 1.4616261
A40: Average Operating Margin | B40: =AVERAGE(Ratios!C41:G41) -> 0.54497449
A42: Final Investment Recommendation
A43: Method | B43: Target Price | C43: Weight | D43: Weighted Value
A44: FCFE | B44: ='DDM FCFF Relative Valuation'!B106 -> 338.00514 | C44: 0.25 | D44: =B44*C44 -> 84.501285
A45: DDM | B45: ='DDM FCFF Relative Valuation'!B15 -> 66.395914 | C45: 0.05 | D45: =B45*C45 -> 3.3197957
A46: Relative Valuation | B46: ='DDM FCFF Relative Valuation'!E39 -> 358.78184 | C46: 0.4 | D46: =B46*C46 -> 143.51274
A47: DCF | B47: ='DCF Valuation'!B36 -> 367.15633 | C47: 0.4 | D47: =B47*C47 -> 146.86253
A48: Final Target Price | D48: =SUM(D44:D47) -> 378.19635
A49: Recommendation | D49: =IF(B54>=0.15,"BUY",IF(B54<=-0.1,"SELL","HOLD")) -> SELL
A51: Investment Decision
A52: Current Market Price | B52: 450
A53: Target Price | B53: =D48 -> 378.19635
A54: Upside/Downside | B54: =(B53-B52)/B52 -> -0.15956367
A55: Recommendation | B55: =D49 -> SELL
A57: Model Sheet Linkage
A58: 1.Data Income | B58: Click the Titles
A59: 2.Data Balance | B59: Click the Titles
A60: 3.Income Statement Projections | B60: Click the Titles
A61: 4.Balance Sheet Projections | B61: Click the Titles
A62: 5.Cash Flow Projections | B62: Click the Titles
A63: 6.Common Size | B63: Click the Titles
A64: 7.Data Industry | B64: Click the Titles
A65: 9.Industry Income Statement | B65: Click the Titles
A66: 10.Industry Balance Sheet | B66: Click the Titles
A67: 11.Industry Cash Flow | B67: Click the Titles
A68: 12.Beta Calculation | B68: Click the Titles
A69: 13.Regression | B69: Click the Titles
... A77: 21.Project Report | B77: Click the Titles

Sheet Assumptions
A1: Income Statement | D1: Key Forecast Assumptions – Mastercard Financial Model
A2: Assumption | B2: Value | D2: Assumption | E2: Value | F2: Basis
A3: Cash % of Revenue | B3: 0.15 | D3: Revenue Growth | E3: 0.1 | F3: Historical Trend
A4: Accounts Receivable % of Revenue | B4: 0.0117 | D4: Tax Rate | E4: 0.16 | F4: Effective Tax Rate
A5: Settlement Assets % of Revenue | B5: 0.134 | D5: Opex | E5: 0.45 | F5: 3-Year Average
A6: Prepaid Assets % of Revenue | B6: 0.106
A7: PPE Growth Rate | B7: 0.04 | E7: Capital Allocation Assumptions | F7: Value
A8: Intangibles Growth Rate | B8: 0.03 | E8: Dividend Payout Ratio | F8: 0.3
A9: Accrued Exp % of Revenue | B9: 0.369 | E9: Share Buyback % | F9: 0.02
D11: Opex Expansion Model | E11: Operating expenses decline due to operating leverage and automation efficiency.
A12: Balance Sheet | D12: Year | E12: Opex %
A13: Assumption | B13: Value | D13: 2025 | E13: 0.45
A14: Revenue Growth 2025E | B14: 0.11 | D14: 2026 | E14: 0.44
A15: Revenue Growth 2026E | B15: 0.1 | D15: 2027 | E15: 0.435
A16: Revenue Growth 2027E | B16: 0.09 | D16: 2028 | E16: 0.43
A17: Revenue Growth 2028E | B17: 0.08 | D17: 2029 | E17: 0.425
A18: Revenue Growth 2029E | B18: 0.07
A19: Total Opex % of Revenue | B19: 0.45
A20: Other Income % | B20: -0.01
A21: Tax Rate | B21: 0.16
A22: Cost of Debt | B22: 0.045
A24: Assumption | B24: Value
A25: Revenue CAGR | B25: 0.15
A26: G&A Growth | B26: 0.35
A27: Marketing % of Revenue | B27: 0.03
A28: Depreciation Growth | B28: 0.03
A29: Litigation Growth | B29: 0.05
A30: Investment Income Growth | B30: 0.04
A31: Interest Expense Growth | B31: 0.03
A32: Tax Rate | B32: 0.16
A33: Share Buyback | B33: 0.04
A35: Working Capital Assumption | B35: Value
A36: Accounts Receivable Growth | B36: 0.0117
A37: Settlement Assets Growth | B37: 0.134
A38: Prepaid Assets Growth | B38: 0.08
A39: Accounts Payable Growth | B39: 0.033
A40: Accrued Expenses Growth | B40: 0.369
A41: Other Assets Growth | B41: 0.3535

Sheet WACC
A1: WACC Calculation | B1: Column1
A2: A | B2: B
A3: Cost of Equity (CAPM)
A4: Risk Free Rate | B4: =Table43[[#This Row],[Column1]] -> 0.045
A5: Market Return | B5: =Table43[[#This Row],[Column1]] -> 0.1
A6: Beta | B6: {=Table23[Value]} -> 1.0378473
A7: Cost of Equity | B7: =B4+B6*(B5-B4) -> 0.1020816
A8: Cost of Debt
A9: A | B9: B
A10: Cost of Debt
A11: Interest Expense | B11: 820.17
A12: Total Debt | B12: =Balance_Sheet!G28+Balance_Sheet!G25 -> 18226
A13: Cost of Debt | B13: =B11/B12 -> 0.045
A14: A | B14: B
A15: Capital Structure
A16: Market Price | B16: 450
A17: Shares Outstanding | B17: ='Profit Loss'!K24 -> 837.93458
A18: Market Cap | B18: =B16*B17 -> 377070.56
A19: Total Debt | B19: =B12 -> 18226
A20: Enterprise Value | B20: =B18+B19 -> 395296.56
A21: Capital Weights
A22: A | B22: B
A23: Equity Weight | B23: =B18/B20 -> 0.95389284
A24: Debt Weight | B24: =B19/B20 -> 0.046107156
A25: WACC
A26: A | B26: B
A27: Tax Rate | B27: ='DCF Valuation'!B7 -> 0.16
A28: WACC | B28: =(B23*B7)+(B24*B13*(1-B27)) -> 0.09911776
A30: Sources
A31: Input | B31: Value | C31: Source
A32: Risk Free Rate | B32: 0.042 | C32: US 10Y Treasury
A33: Market Return | B33: 0.1 | C33: Long-term S&P500
A34: Beta | B34: 1.03 | C34: Yahoo Finance

Sheet CAGR Projections
A1: CAGR Projections
A2: Income Statement CAGR Projection
A3: Item | B3: 2020 | C3: 2021 | D3: 2022 | E3: 2023 | F3: 2024 | G3: CAGR | H3: 2025 | I3: 2026 | J3: 2027 | K3: 2028 | L3: 2029
A4: Revenue | B4: =Table1[[#This Row],[2020]] -> 15301 | C4: =Table1[[#This Row],[2021]] -> 18884 | D4: =Table1[[#This Row],[2022]] -> 22237 | E4: =Table1[[#This Row],[2023]] -> 25098 | F4: =Table1[[#This Row],[2024]] -> 28167 | G4: =(Table51[[#This Row],[2024]] / Table51[[#This Row],[2020]])^(1/4)-1 -> 0.16481028 | H4: =F4*(1+$G4) -> 32809.211 | I4: =Table51[[#This Row],[2025]]*(1+Table51[[#This Row],[CAGR]]) -> 38216.506 | J4: =Table51[[#This Row],[2026]]*(1+Table51[[#This Row],[CAGR]]) -> 44514.98 | K4: =Table51[[#This Row],[2027]]*(1+Table51[[#This Row],[CAGR]]) -> 51851.506 | L4: =Table51[[#This Row],[2028]]*(1+Table51[[#This Row],[CAGR]]) -> 60397.167
A5: Operating Income | B5: ='Profit Loss'!B11 -> 8081 | C5: ='Profit Loss'!C11 -> 10082 | D5: ='Profit Loss'!D11 -> 12264 | E5: ='Profit Loss'!E11 -> 14008 | F5: ='Profit Loss'!F11 -> 15582 | G5: =(Table51[[#This Row],[2024]] / Table51[[#This Row],[2020]])^(1/4)-1 -> 0.17839129 | H5: =F5*(1+$G5) -> 18361.693 | I5: =Table51[[#This Row],[2025]]*(1+Table51[[#This Row],[CAGR]]) -> 21637.259 | J5: =Table51[[#This Row],[2026]]*(1+Table51[[#This Row],[CAGR]]) -> 25497.158 | K5: =Table51[[#This Row],[2027]]*(1+Table51[[#This Row],[CAGR]]) -> 30045.629 | L5: =Table51[[#This Row],[2028]]*(1+Table51[[#This Row],[CAGR]]) -> 35405.507
A6: Net Income | B6: ='Profit Loss'!B20 -> 6411 | C6: ='Profit Loss'!C20 -> 8687 | D6: ='Profit Loss'!D20 -> 9930 | E6: ='Profit Loss'!E20 -> 11195 | F6: ='Profit Loss'!F20 -> 12874 | G6: =(Table51[[#This Row],[2024]] / Table51[[#This Row],[2020]])^(1/4)-1 -> 0.190411 | H6: =F6*(1+$G6) -> 15325.351 | I6: =Table51[[#This Row],[2025]]*(1+Table51[[#This Row],[CAGR]]) -> 18243.467 | J6: =Table51[[#This Row],[2026]]*(1+Table51[[#This Row],[CAGR]]) -> 21717.223 | K6: =Table51[[#This Row],[2027]]*(1+Table51[[#This Row],[CAGR]]) -> 25852.422 | L6: =Table51[[#This Row],[2028]]*(1+Table51[[#This Row],[CAGR]]) -> 30775.007
A7: EPS | B7: ='Profit Loss'!B21 -> 6.4 | C7: ='Profit Loss'!C21 -> 8.79 | D7: ='Profit Loss'!D21 -> 10.26 | E7: ='Profit Loss'!E21 -> 11.86 | F7: ='Profit Loss'!F21 -> 13.91 | G7: =(Table51[[#This Row],[2024]] / Table51[[#This Row],[2020]])^(1/4)-1 -> 0.21419038 | H7: =F7*(1+$G7) -> 16.889388 | I7: =Table51[[#This Row],[2025]]*(1+Table51[[#This Row],[CAGR]]) -> 20.506933 | J7: =Table51[[#This Row],[2026]]*(1+Table51[[#This Row],[CAGR]]) -> 24.899321 | K7: =Table51[[#This Row],[2027]]*(1+Table51[[#This Row],[CAGR]]) -> 30.232516 | L7: =Table51[[#This Row],[2028]]*(1+Table51[[#This Row],[CAGR]]) -> 36.70803
A9: Balance Sheet CAGR Projection
A10: Item | B10: 2020 | C10: 2021 | D10: 2022 | E10: 2023 | F10: 2024 | G10: CAGR | H10: 2025 | I10: 2026 | J10: 2027 | K10: 2028 | L10: 2029
A11: Total Assets | B11: =Balance_Sheet!B18 -> 33584 | C11: =Balance_Sheet!C18 -> 37669 | D11: =Balance_Sheet!D18 -> 38724 | E11: =Balance_Sheet!E18 -> 42448 | F11: =Balance_Sheet!F18 -> 48081 | G11: =(Table52[[#This Row],[2024]] / Table52[[#This Row],[2020]])^(1/4)-1 -> 0.093856288 | H11: =F11*(1+$G11) -> 52593.704 | I11: =Table52[[#This Row],[2025]]*(1+Table52[[#This Row],[CAGR]]) -> 57529.954 | J11: =Table52[[#This Row],[2026]]*(1+Table52[[#This Row],[CAGR]]) -> 62929.502 | K11: =Table52[[#This Row],[2027]]*(1+Table52[[#This Row],[CAGR]]) -> 68835.831 | L11: =Table52[[#This Row],[2028]]*(1+Table52[[#This Row],[CAGR]]) -> 75296.507
A12: Total Liabilities | B12: =Balance_Sheet!B31 -> 27067 | C12: =Balance_Sheet!C31 -> 30257 | D12: =Balance_Sheet!D31 -> 32347 | E12: =Balance_Sheet!E31 -> 35451 | F12: =Balance_Sheet!F31 -> 41566 | G12: =(Table52[[#This Row],[2024]] / Table52[[#This Row],[2020]])^(1/4)-1 -> 0.11320341 | H12: =F12*(1+$G12) -> 46271.413 | I12: =Table52[[#This Row],[2025]]*(1+Table52[[#This Row],[CAGR]]) -> 51509.495 | J12: =Table52[[#This Row],[2026]]*(1+Table52[[#This Row],[CAGR]]) -> 57340.545 | K12: =Table52[[#This Row],[2027]]*(1+Table52[[#This Row],[CAGR]]) -> 63831.69 | L12: =Table52[[#This Row],[2028]]*(1+Table52[[#This Row],[CAGR]]) -> 71057.655
A13: Shareholders Equity | B13: =Balance_Sheet!B41 -> 6488 | C13: =Balance_Sheet!C41 -> 7383 | D13: =Balance_Sheet!D41 -> 6356 | E13: =Balance_Sheet!E41 -> 6975 | F13: =Balance_Sheet!F41 -> 6515 | G13: =(Table52[[#This Row],[2024]] / Table52[[#This Row],[2020]])^(1/4)-1 -> 0.0010387626 | H13: =F13*(1+$G13) -> 6521.7675 | I13: =Table52[[#This Row],[2025]]*(1+Table52[[#This Row],[CAGR]]) -> 6528.5421 | J13: =Table52[[#This Row],[2026]]*(1+Table52[[#This Row],[CAGR]]) -> 6535.3237 | K13: =Table52[[#This Row],[2027]]*(1+Table52[[#This Row],[CAGR]]) -> 6542.1124 | L13: =Table52[[#This Row],[2028]]*(1+Table52[[#This Row],[CAGR]]) -> 6548.9081
A14: Cash & Cash Equivalents | B14: =Balance_Sheet!B4 -> 10113 | C14: =Balance_Sheet!C4 -> 7421 | D14: =Balance_Sheet!D4 -> 7008 | E14: =Balance_Sheet!E4 -> 8588 | F14: =Balance_Sheet!F4 -> 8442 | G14: =(Table52[[#This Row],[2024]] / Table52[[#This Row],[2020]])^(1/4)-1 -> -0.044146499 | H14: =F14*(1+$G14) -> 8069.3153 | I14: =Table52[[#This Row],[2025]]*(1+Table52[[#This Row],[CAGR]]) -> 7713.0832 | J14: =Table52[[#This Row],[2026]]*(1+Table52[[#This Row],[CAGR]]) -> 7372.5776 | K14: =Table52[[#This Row],[2027]]*(1+Table52[[#This Row],[CAGR]]) -> 7047.1041 | L14: =Table52[[#This Row],[2028]]*(1+Table52[[#This Row],[CAGR]]) -> 6735.9991
A16: Cash Flow Statement CAGR Projection
A17: Item | B17: 2020 | C17: 2021 | D17: 2022 | E17: 2023 | F17: 2024 | G17: CAGR | H17: 2025 | I17: 2026 | J17: 2027 | K17: 2028 | L17: 2029
A18: Operating Cash Flow | B18: ='Cash Flow'!B24 -> 7224 | C18: ='Cash Flow'!C24 -> 9463 | D18: ='Cash Flow'!D24 -> 11195 | E18: ='Cash Flow'!E24 -> 11980 | F18: ='Cash Flow'!F24 -> 14780 | G18: =(Table53[[#This Row],[2024]] / Table53[[#This Row],[2020]])^(1/4)-1 -> 0.19598071 | H18: =F18*(1+$G18) -> 17676.595 | I18: =Table53[[#This Row],[2025]]*(1+Table53[[#This Row],[CAGR]]) -> 21140.866 | J18: =Table53[[#This Row],[2026]]*(1+Table53[[#This Row],[CAGR]]) -> 25284.068 | K18: =Table53[[#This Row],[2027]]*(1+Table53[[#This Row],[CAGR]]) -> 30239.258 | L18: =Table53[[#This Row],[2028]]*(1+Table53[[#This Row],[CAGR]]) -> 36165.569
A19: Investing Cash Flow | B19: ='Cash Flow'!B38 -> -1879 | C19: ='Cash Flow'!C38 -> -5272 | D19: ='Cash Flow'!D38 -> -1470 | E19: ='Cash Flow'!E38 -> -1351 | F19: ='Cash Flow'!F38 -> -3402 | G19: =(Table53[[#This Row],[2024]] / Table53[[#This Row],[2020]])^(1/4)-1 -> 0.15998369 | H19: =AVERAGE(Table53[[#This Row],[2020]:[2024]]) -> -2674.8 | I19: =AVERAGE(Table53[[#This Row],[2020]:[2024]]) -> -2674.8 | J19: =AVERAGE(Table53[[#This Row],[2020]:[2024]]) -> -2674.8 | K19: =AVERAGE(Table53[[#This Row],[2020]:[2024]]) -> -2674.8 | L19: =AVERAGE(Table53[[#This Row],[2020]:[2024]]) -> -2674.8
A20: Financing Cash Flow | B20: ='Cash Flow'!B50 -> -2152 | C20: ='Cash Flow'!C50 -> -6555 | D20: ='Cash Flow'!D50 -> -10328 | E20: ='Cash Flow'!E50 -> -9488 | F20: ='Cash Flow'!F50 -> -10836 | G20: =(Table53[[#This Row],[2024]] / Table53[[#This Row],[2020]])^(1/4)-1 -> 0.4979823 | H20: =AVERAGE(Table53[[#This Row],[2020]:[2024]]) -> -7871.8 | I20: =AVERAGE(Table53[[#This Row],[2020]:[2024]]) -> -7871.8 | J20: =AVERAGE(Table53[[#This Row],[2020]:[2024]]) -> -7871.8 | K20: =AVERAGE(Table53[[#This Row],[2020]:[2024]]) -> -7871.8 | L20: =AVERAGE(Table53[[#This Row],[2020]:[2024]]) -> -7871.8
A21: Free Cash Flow | B21: ='Cash Flow'!B55 -> 7563 | C21: ='Cash Flow'!C55 -> 9870 | D21: ='Cash Flow'!D55 -> 11637 | E21: ='Cash Flow'!E55 -> 12351 | F21: ='Cash Flow'!F55 -> 15254 | G21: =(Table53[[#This Row],[2024]] / Table53[[#This Row],[2020]])^(1/4)-1 -> 0.19171501 | H21: =F21*(1+$G21) -> 18178.421 | I21: =Table53[[#This Row],[2025]]*(1+Table53[[#This Row],[CAGR]]) -> 21663.497 | J21: =Table53[[#This Row],[2026]]*(1+Table53[[#This Row],[CAGR]]) -> 25816.715 | K21: =Table53[[#This Row],[2027]]*(1+Table53[[#This Row],[CAGR]]) -> 30766.166 | L21: =Table53[[#This Row],[2028]]*(1+Table53[[#This Row],[CAGR]]) -> 36664.502

Sheet Profit Loss
A1: Consolidated Statement of Operations - USD ($) shares in Millions, $ in Millions | B1: 2020 | C1: 2021 | D1: 2022 | E1: 2023 | F1: 2024 | G1: 2025E | H1: 2026E | I1: 2027E | J1: 2028E | K1: 2029E
A2: Mastercard Inc | M2: 2020-2024 | N2: Historicals
A3: Income Statement [Abstract] | M3: 2025-2029 | N3: Projections
A4: Net revenue | B4: 15301 | C4: 18884 | D4: 22237 | E4: 25098 | F4: 28167 | G4: =Table1[[#This Row],[2024]]*(1+Assumptions!B14) -> 31265.37 | H4: =Table1[[#This Row],[2025E]]*(1+Assumptions!B15) -> 34391.907 | I4: =Table1[[#This Row],[2026E]]*(1+Assumptions!B16) -> 37487.179 | J4: =Table1[[#This Row],[2027E]]*(1+Assumptions!B17) -> 40486.153 | K4: =Table1[[#This Row],[2028E]]*(1+Assumptions!B18) -> 43320.184
A5: Operating Expenses
A6: General and administrative | B6: 5910 | C6: 7087 | D6: 8078 | E6: 8927 | F6: 10193 | G6: =Table1[[#This Row],[2024]]*1.08 -> 11008.44 | H6: =Table1[[#This Row],[2025E]]*1.08 -> 11889.115 | I6: =Table1[[#This Row],[2026E]]*1.08 -> 12840.244 | J6: =Table1[[#This Row],[2027E]]*1.08 -> 13867.464 | K6: =Table1[[#This Row],[2028E]]*1.08 -> 14976.861
A7: Advertising and marketing | B7: 657 | C7: 895 | D7: 789 | E7: 825 | F7: 815 | G7: =G4*3% -> 937.9611 | H7: =H4*3% -> 1031.7572 | I7: =I4*3% -> 1124.6154 | J7: =J4*3% -> 1214.5846 | K7: =K4*3% -> 1299.6055
A8: Depreciation and amortization | B8: 580 | C8: 726 | D8: 750 | E8: 799 | F8: 897 | G8: =Table1[[#This Row],[2024]]*1.08 -> 968.76 | H8: =Table1[[#This Row],[2025E]]*1.08 -> 1046.2608 | I8: =Table1[[#This Row],[2026E]]*1.08 -> 1129.9617 | J8: =Table1[[#This Row],[2027E]]*1.08 -> 1220.3586 | K8: =Table1[[#This Row],[2028E]]*1.08 -> 1317.9873
A9: Provision for litigation | B9: 73 | C9: 94 | D9: 356 | E9: 539 | F9: 680 | G9: =Table1[[#This Row],[2024]]*1.05 -> 714 | H9: =Table1[[#This Row],[2025E]]*1.05 -> 749.7 | I9: =Table1[[#This Row],[2026E]]*1.05 -> 787.185 | J9: =Table1[[#This Row],[2027E]]*1.05 -> 826.54425 | K9: =Table1[[#This Row],[2028E]]*1.05 -> 867.87146
A10: Total operating expenses | B10: 7220 | C10: 8802 | D10: 9973 | E10: 11090 | F10: 12585 | G10: =G4*Assumptions!E13 -> 14069.417 | H10: =H4*Assumptions!E14 -> 15132.439 | I10: =I4*Assumptions!E15 -> 16306.923 | J10: =J4*Assumptions!E16 -> 17409.046 | K10: =K4*Assumptions!E17 -> 18411.078
A11: Operating income | B11: 8081 | C11: 10082 | D11: 12264 | E11: 14008 | F11: 15582 | G11: =(G4-G10) -> 17195.954 | H11: =(H4-H10) -> 19259.468 | I11: =(I4-I10) -> 21180.256 | J11: =(J4-J10) -> 23077.107 | K11: =(K4-K10) -> 24909.106
A12: Other Income (Expense)
A13: Investment income | B13: 24 | C13: 11 | D13: 61 | E13: 274 | F13: 327 | G13: =Table1[[#This Row],[2024]]*(1+Assumptions!B30) -> 340.08 | H13: =Table1[[#This Row],[2025E]]*(1+Assumptions!B30) -> 353.6832 | I13: =Table1[[#This Row],[2026E]]*(1+Assumptions!B30) -> 367.83053 | J13: =Table1[[#This Row],[2027E]]*(1+Assumptions!B30) -> 382.54375 | K13: =Table1[[#This Row],[2028E]]*(1+Assumptions!B30) -> 397.8455
A14: Gains (losses) on equity investments, net | B14: 30 | C14: 645 | D14: -145 | E14: -61 | F14: -29 | G14: 0 | H14: 0 | I14: 0 | J14: 0 | K14: 0
A15: Interest expense | B15: -380 | C15: -431 | D15: -471 | E15: -575 | F15: -646 | G15: =-'Common Size'!G43*Assumptions!B22 -> -820.17 | H15: =-'Common Size'!H43*Assumptions!B22 -> -820.17 | I15: =-'Common Size'!I43*Assumptions!B22 -> -820.17 | J15: =-'Common Size'!J43*Assumptions!B22 -> -820.17 | K15: =-'Common Size'!K43*Assumptions!B22 -> -820.17
A16: Other income (expense), net | B16: 5 | C16: 0 | D16: 23 | E16: -7 | F16: 20 | G16: 0 | H16: =Table1[[#This Row],[2025E]]*(1+Assumptions!B31) -> 0 | I16: =Table1[[#This Row],[2026E]]*(1+Assumptions!B31) -> 0 | J16: =Table1[[#This Row],[2027E]]*(1+Assumptions!B31) -> 0 | K16: =Table1[[#This Row],[2028E]]*(1+Assumptions!B31) -> 0
A17: Total other income (expense) | B17: -321 | C17: 225 | D17: -532 | E17: -369 | F17: -328 | G17: =G13+G14+G15+G16 -> -480.09 | H17: =SUM(H13:H16) -> -466.4868 | I17: =SUM(I13:I16) -> -452.33947 | J17: =SUM(J13:J16) -> -437.62625 | K17: =SUM(K13:K16) -> -422.3245
A18: Income before income taxes | B18: 7760 | C18: 10307 | D18: 11732 | E18: 13639 | F18: 15254 | G18: =G11+G17 -> 16715.864 | H18: =H11+H17 -> 18792.981 | I18: =I11+I17 -> 20727.916 | J18: =J11+J17 -> 22639.481 | K18: =K11+K17 -> 24486.781
A19: Income tax expense | B19: 1349 | C19: 1620 | D19: 1802 | E19: 2444 | F19: 2380 | G19: =G18*16% -> 2674.5382 | H19: =H18*16% -> 3006.877 | I19: =I18*16% -> 3316.4666 | J19: =J18*16% -> 3622.3169 | K19: =K18*16% -> 3917.885
A20: Net Income | B20: 6411 | C20: 8687 | D20: 9930 | E20: 11195 | F20: 12874 | G20: =G18-G19 -> 14041.325 | H20: =H18-H19 -> 15786.104 | I20: =I18-I19 -> 17411.45 | J20: =J18-J19 -> 19017.164 | K20: =K18-K19 -> 20568.896
A21: Basic Earnings per Share | B21: 6.4 | C21: 8.79 | D21: 10.26 | E21: 11.86 | F21: 13.91 | G21: =G20/G22 -> 15.489603 | H21: =H20/H22 -> 17.76974 | I21: =I20/I22 -> 19.999308 | J21: =J20/J22 -> 22.289469 | K21: =K20/K22 -> 24.600213
A22: Basic weighted-average shares outstanding | B22: 1002 | C22: 988 | D22: 968 | E22: 944 | F22: 925 | G22: =Table1[[#This Row],[2024]]*(1-2%) -> 906.5 | H22: =Table1[[#This Row],[2025E]]*(1-Assumptions!F9) -> 888.37 | I22: =Table1[[#This Row],[2026E]]*(1-Assumptions!F9) -> 870.6026 | J22: =Table1[[#This Row],[2027E]]*(1-Assumptions!F9) -> 853.19055 | K22: =Table1[[#This Row],[2028E]]*(1-Assumptions!F9) -> 836.12674
A23: Diluted Earnings per Share | B23: 6.37 | C23: 8.76 | D23: 10.22 | E23: 11.83 | F23: 13.89 | G23: =G20/G24 -> 15.456184 | H23: =H20/H24 -> 17.731402 | I23: =I20/I24 -> 19.95616 | J23: =J20/J24 -> 22.241379 | K23: =K20/K24 -> 24.547138
A24: Diluted weighted-average shares outstanding | B24: 1006 | C24: 992 | D24: 971 | E24: 946 | F24: 927 | G24: =Table1[[#This Row],[2024]]*(1-Assumptions!F9) -> 908.46 | H24: =Table1[[#This Row],[2025E]]*(1-Assumptions!F9) -> 890.2908 | I24: =Table1[[#This Row],[2026E]]*(1-Assumptions!F9) -> 872.48498 | J24: =Table1[[#This Row],[2027E]]*(1-Assumptions!F9) -> 855.03528 | K24: =Table1[[#This Row],[2028E]]*(1-Assumptions!F9) -> 837.93458
A25: EBITDA | B25: =B11+B8 -> 8661 | C25: =C11+C8 -> 10808 | D25: =D11+D8 -> 13014 | E25: =E11+E8 -> 14807 | F25: =F11+F8 -> 16479 | G25: =G11+G8 -> 18164.714 | H25: =H11+H8 -> 20305.729 | I25: =I11+I8 -> 22310.218 | ... K25: =K11+K8 -> 26227.093
A26: Operating Margin | B26: =B11/B4 -> 0.52813542 | C26: =C11/C4 -> 0.53389112 | D26: =D11/D4 -> 0.55151324 | E26: =E11/E4 -> 0.55813212 | F26: =F11/F4 -> 0.55320055 | G26: =G11/G4 -> 0.55 | H26: =H11/H4 -> 0.56 | I26: =I11/I4 -> 0.565 | ... K26: =K11/K4 -> 0.575
A27: Net Margin | B27: =B20/B4 -> 0.41899222 | C27: =C20/C4 -> 0.46001906 | D27: =D20/D4 -> 0.44655304 | E27: =E20/E4 -> 0.44605148 | F27: =F20/F4 -> 0.45705968 | G27: =G20/G4 -> 0.44910152 | H27: =H20/H4 -> 0.45900636 | I27: =I20/I4 -> 0.46446413 | ... K27: =K20/K4 -> 0.47481092

Sheet Balance_Sheet
A1: Consolidated Balance Sheet - USD ($) $ in Millions | B1: 2020 | C1: 2021 | D1: 2022 | E1: 2023 | F1: 2024 | G1: 2025E | H1: 2026E | I1: 2027E | J1: 2028E | K1: 2029E
A2: Mastercard Inc | M2: 2020-2024 | N2: Historicals
A3: Assets | M3: 2025-2029 | N3: Projections
A4: Cash and cash equivalents | B4: 10113 | C4: 7421 | D4: 7008 | E4: 8588 | F4: 8442 | G4: ='Cash Flow'!G54 -> 13504.262 | H4: ='Cash Flow'!H54 -> 18359.463 | I4: ='Cash Flow'!I54 -> 23602.217 | J4: ='Cash Flow'!J54 -> 29153.571 | K4: ='Cash Flow'!K54 -> 34906.025
A5: Restricted cash for litigation settlement | B5: 586 | C5: 586 | D5: 589 | E5: 32 | F5: 492 | G5: 492 | H5: 492 | I5: 492 | J5: 492 | K5: 492
A6: Investments | B6: 483 | C6: 473 | D6: 400 | E6: 1845 | F6: 1874 | G6: 1874 | H6: 1874 | I6: 1874 | J6: 1874 | K6: 1874
A7: Accounts receivable | B7: 2646 | C7: 3006 | D7: 3425 | E7: 592 | F7: 330 | G7: ='Profit Loss'!G4*Assumptions!B36 -> 365.80483 | H7: ='Profit Loss'!H4*Assumptions!B36 -> 402.38531 | I7: ='Profit Loss'!I4*Assumptions!B36 -> 438.59999 | J7: ='Profit Loss'!J4*Assumptions!B36 -> 473.68799 | K7: ='Profit Loss'!K4*Assumptions!B36 -> 506.84615
A8: Settlement assets | B8: 1706 | C8: 1319 | D8: 1270 | E8: 4060 | F8: 3773 | G8: ='Profit Loss'!G4*Assumptions!B37 -> 4189.5596 | H8: ='Profit Loss'!H4*Assumptions!B37 -> 4608.5155 | I8: ='Profit Loss'!I4*Assumptions!B37 -> 5023.2819 | J8: ='Profit Loss'!J4*Assumptions!B37 -> 5425.1445 | K8: ='Profit Loss'!K4*Assumptions!B37 -> 5804.9046
A9: Restricted security deposits held for customers | B9: 1696 | C9: 1873 | D9: 1568 | E9: 1233 | F9: 1821 | G9: 1821 | H9: 1821 | I9: 1821 | J9: 1821 | K9: 1821
A10: Prepaid expenses and other current assets | B10: 1883 | C10: 2271 | D10: 2346 | E10: 2611 | F10: 2992 | G10: ='Profit Loss'!G4*Assumptions!B38 -> 2501.2296 | H10: ='Profit Loss'!H4*Assumptions!B38 -> 2751.3526 | I10: ='Profit Loss'!I4*Assumptions!B38 -> 2998.9743 | J10: ='Profit Loss'!J4*Assumptions!B38 -> 3238.8922 | K10: ='Profit Loss'!K4*Assumptions!B38 -> 3465.6147
A11: Total current assets | B11: =SUM(B4:B10) -> 19113 | C11: =SUM(C4:C10) -> 16949 | D11: =SUM(D4:D10) -> 16606 | E11: =SUM(E4:E10) -> 18961 | F11: =SUM(F4:F10) -> 19724 | G11: =SUM(G4:G10) -> 24747.856 | H11: =SUM(H4:H10) -> 30308.716 | I11: =SUM(I4:I10) -> 36250.074 | ... K11: =SUM(K4:K10) -> 48870.39
A12: Property, equipment and right-of-use assets, net | B12: 1902 | C12: 1907 | D12: 2006 | E12: 2061 | F12: 2138 | G12: =Table2[[#This Row],[2024]]*(1+Assumptions!B7) -> 2223.52 | H12: =Table2[[#This Row],[2025E]]*(1+Assumptions!B7) -> 2312.4608 | I12: =Table2[[#This Row],[2026E]]*(1+Assumptions!B7) -> 2404.9592 | J12: =Table2[[#This Row],[2027E]]*(1+Assumptions!B7) -> 2501.1576 | K12: =Table2[[#This Row],[2028E]]*(1+Assumptions!B7) -> 2601.2039
A13: Deferred income taxes | B13: 491 | C13: 486 | D13: 1151 | E13: 1355 | F13: 1614 | G13: 1614 | H13: 1614 | I13: 1614 | J13: 1614 | K13: 1614
A14: Goodwill | B14: 4960 | C14: 7662 | D14: 7522 | E14: 7660 | F14: 9193 | G14: 9193 | H14: 9193 | I14: 9193 | J14: 9193 | K14: 9193
A15: Other intangible assets, net | B15: 1753 | C15: 3671 | D15: 3859 | E15: 4086 | F15: 5453 | G15: =Table2[[#This Row],[2024]]*(1+Assumptions!B8) -> 5616.59 | H15: =Table2[[#This Row],[2025E]]*(1+Assumptions!B8) -> 5785.0877 | I15: =Table2[[#This Row],[2026E]]*(1+Assumptions!B8) -> 5958.6403 | J15: =Table2[[#This Row],[2027E]]*(1+Assumptions!B8) -> 6137.3995 | K15: =Table2[[#This Row],[2028E]]*(1+Assumptions!B8) -> 6321.5215
A16: Total Cash | B16: =B4+B5 -> 10699 | C16: =C4+C5 -> 8007 | D16: =D4+D5 -> 7597 | E16: =E4+E5 -> 8620 | F16: =F4+F5 -> 8934 | G16: =G4+G5 -> 13996.262 | H16: =H4+H5 -> 18851.463 | I16: =I4+I5 -> 24094.217 | ... K16: =K4+K5 -> 35398.025
A17: Other assets | B17: 5365 | C17: 6994 | D17: 7580 | E17: 8325 | F17: 9959 | G17: ='Profit Loss'!G4*Assumptions!B41 -> 11052.308 | H17: ='Profit Loss'!H4*Assumptions!B41 -> 12157.539 | I17: ='Profit Loss'!I4*Assumptions!B41 -> 13251.718 | J17: ='Profit Loss'!J4*Assumptions!B41 -> 14311.855 | K17: ='Profit Loss'!K4*Assumptions!B41 -> 15313.685
A18: Total Assets | B18: 33584 | C18: 37669 | D18: 38724 | E18: 42448 | F18: 48081 | G18: =G31+G41 -> 58699.683 | H18: =H31+H41 -> 70535.502 | I18: =I31+I41 -> 83458.48 | J18: =J31+J41 -> 97406.625 | K18: =K31+K41 -> 112292.29
A19: Liabilities, Redeemable Non-controlling Interests and Equity
A20: Accounts payable | B20: 527 | C20: 738 | D20: 926 | E20: 834 | F20: 929 | G20: ='Profit Loss'!G4*3.3% -> 1031.7572 | H20: ='Profit Loss'!H4*3.3% -> 1134.9329 | I20: ='Profit Loss'!I4*3.3% -> 1237.0769 | J20: ='Profit Loss'!J4*3.3% -> 1336.043 | K20: ='Profit Loss'!K4*3.3% -> 1429.5661
A21: Settlement obligations | B21: 1475 | C21: 913 | D21: 1111 | E21: 1399 | F21: 2316 | G21: ='Profit Loss'!G4*8.2% -> 2563.7603 | H21: ='Profit Loss'!H4*8.2% -> 2820.1364 | I21: ='Profit Loss'!I4*8.2% -> 3073.9486 | J21: ='Profit Loss'!J4*8.2% -> 3319.8645 | K21: ='Profit Loss'!K4*8.2% -> 3552.2551
A22: Restricted security deposits held for customers | B22: 1696 | C22: 1873 | D22: 1568 | E22: 1845 | F22: 1874 | G22: 1874 | H22: 1874 | I22: 1874 | J22: 1874 | K22: 1874
A23: Accrued litigation | B23: 842 | C23: 840 | D23: 1094 | E23: 723 | F23: 930 | G23: 930 | H23: 930 | I23: 930 | J23: 930 | K23: 930
A24: Accrued expenses | B24: 5430 | C24: 6642 | D24: 7801 | E24: 8517 | F24: 10393 | G24: ='Profit Loss'!G4*Assumptions!B40 -> 11536.922 | H24: ='Profit Loss'!H4*Assumptions!B40 -> 12690.614 | I24: ='Profit Loss'!I4*Assumptions!B40 -> 13832.769 | J24: ='Profit Loss'!J4*Assumptions!B40 -> 14939.39 | K24: ='Profit Loss'!K4*Assumptions!B40 -> 15985.148
A25: Current portion of long-term debt | B25: 649 | C25: 792 | D25: 274 | E25: 1337 | F25: 750 | G25: 750 | H25: 750 | I25: 750 | J25: 750 | K25: 750
A26: Other current liabilities | B26: 1228 | C26: 1364 | D26: 1397 | E26: 1609 | F26: 2028 | G26: ='Profit Loss'!G4*7.2% -> 2251.1066 | H26: ='Profit Loss'!H4*7.2% -> 2476.2173 | I26: ='Profit Loss'!I4*7.2% -> 2699.0769 | J26: ='Profit Loss'!J4*7.2% -> 2915.003 | K26: ='Profit Loss'!K4*7.2% -> 3119.0532
A27: Total current liabilities | B27: 11847 | C27: 13162 | D27: 14171 | E27: 16264 | F27: 19220 | G27: =SUM(G20:G26) -> 20937.546 | H27: =SUM(H20:H26) -> 22675.9 | I27: =SUM(I20:I26) -> 24396.871 | J27: =SUM(J20:J26) -> 26064.301 | K27: =SUM(K20:K26) -> 27640.022
A28: Long-term debt | B28: 12023 | C28: 13109 | D28: 13749 | E28: 14344 | F28: 17476 | G28: 17476 | H28: 17476 | I28: 17476 | J28: 17476 | K28: 17476
A29: Deferred income taxes | B29: 86 | C29: 395 | D29: 393 | E29: 369 | F29: 317 | G29: 317 | H29: 317 | I29: 317 | J29: 317 | K29: 317
A30: Other liabilities | B30: 3111 | C30: 3591 | D30: 4034 | E30: 4474 | F30: 4553 | G30: =Table2[[#This Row],[2024]]*(1+Assumptions!B14) -> 5053.83 | H30: =Table2[[#This Row],[2025E]]*(1+Assumptions!B15) -> 5559.213 | I30: =Table2[[#This Row],[2026E]]*(1+Assumptions!B16) -> 6059.5422 | J30: =Table2[[#This Row],[2027E]]*(1+Assumptions!B17) -> 6544.3055 | K30: =Table2[[#This Row],[2028E]]*(1+Assumptions!B18) -> 7002.4069
A31: Total Liabilities | B31: 27067 | C31: 30257 | D31: 32347 | E31: 35451 | F31: 41566 | G31: =G27+G28+G29+G30 -> 43784.376 | H31: =H27+H28+H29+H30 -> 46028.113 | I31: =I27+I28+I29+I30 -> 48249.413 | J31: =J27+J28+J29+J30 -> 50401.607 | K31: =K27+K28+K29+K30 -> 52435.429
A32: Commitments and Contingencies
A33: Redeemable non-controlling interests | B33: 29 | C33: 29 | D33: 21 | E33: 22 | F33: 0 | G33: 0 | H33: 0 | I33: 0 | J33: 0 | K33: 0
A34: Stockholders’ Equity
A35: Additional paid-in-capital | B35: 4982 | C35: 5061 | D35: 5298 | E35: 5893 | F35: 6442 | G35: 6442 | H35: 6442 | I35: 6442 | J35: 6442 | K35: 6442
A36: Class A treasury stock, at cost, 425 and 409 shares, respectively | B36: -36658 | C36: -42588 | D36: -51354 | E36: -60429 | F36: -71431 | G36: =Table2[[#This Row],[2024]]*1.02 -> -72859.62 | H36: =Table2[[#This Row],[2025E]]*1.02 -> -74316.812 | I36: =Table2[[#This Row],[2026E]]*1.02 -> -75803.149 | J36: =Table2[[#This Row],[2027E]]*1.02 -> -77319.212 | K36: =Table2[[#This Row],[2028E]]*1.02 -> -78865.596
A37: Retained earnings | B37: 38747 | C37: 45648 | D37: 53607 | E37: 62564 | F37: 72907 | G37: =Table2[[#This Row],[2024]]+'Profit Loss'!G20+'Cash Flow'!G41 -> 82735.928 | H37: =Table2[[#This Row],[2025E]]-1+'Profit Loss'!H20+'Cash Flow'!H41 -> 93785.201 | I37: =Table2[[#This Row],[2026E]]+'Profit Loss'!I20+'Cash Flow'!I41 -> 105973.22 | J37: =Table2[[#This Row],[2027E]]+'Profit Loss'!J20+'Cash Flow'!J41 -> 119285.23 | K37: =Table2[[#This Row],[2028E]]+'Profit Loss'!K20+'Cash Flow'!K41 -> 133683.46
A38: Accumulated other comprehensive income (loss) | B38: -680 | C38: -809 | D38: -1253 | E38: -1099 | F38: -1433 | G38: -1433 | H38: -1433 | I38: -1433 | J38: -1433 | K38: -1433
A39: Mastercard Incorporated Stockholders' Equity | B39: 6391 | C39: 7312 | D39: 6298 | E39: 6929 | F39: 6485 | G39: =G35+G37+G36+G38 -> 14885.308 | H39: =H35+H37+H36+H38 -> 24477.388 | I39: =I35+I37+I36+I38 -> 35179.067 | J39: =J35+J37+J36+J38 -> 46975.019 | K39: =K35+K37+K36+K38 -> 59826.862
A40: Non-controlling interests | B40: 97 | C40: 71 | D40: 58 | E40: 46 | F40: 30 | G40: 30 | H40: 30 | I40: 30 | J40: 30 | K40: 30
A41: Total Equity | B41: 6488 | C41: 7383 | D41: 6356 | E41: 6975 | F41: 6515 | G41: =G39+G40 -> 14915.308 | H41: =H39+H40 -> 24507.388 | I41: =I39+I40 -> 35209.067 | J41: =J39+J40 -> 47005.019 | K41: =K39+K40 -> 59856.862
A42: Total Liabilities, Redeemable Non-controlling Interests and Equity | B42: 33584 | C42: 37669 | D42: 38724 | E42: 42448 | F42: 48081 | G42: =G31+G41 -> 58699.683 | H42: =H31+H41 -> 70535.502 | I42: =I31+I41 -> 83458.48 | J42: =J31+J41 -> 97406.625 | K42: =K31+K41 -> 112292.29
A43: Class A Common Stock
A44: Stockholders’ Equity
A45: Common stock value | B45: 0 | C45: 0 | D45: 0 | E45: 0 | F45: 0 | G45: 0 | H45: 0 | I45: 0 | J45: 0 | K45: 0
A46: Class B Common Stock
A47: Stockholders’ Equity
A48: Common stock value | B48: 0 | C48: 0 | D48: 0 | E48: 0 | F48: 0 | G48: 0 | H48: 0 | I48: 0 | J48: 0 | K48: 0

Sheet Cash Flow
A1: Consolidated Statement of Cash Flows - USD ($) $ in Millions | B1: 2020 | C1: 2021 | D1: 2022 | E1: 2023 | F1: 2024 | G1: 2025E | H1: 2026E | I1: 2027E | J1: 2028E | K1: 2029E
A2: Mastercard Inc | M2: 2020-2024 | N2: Historicals
A3: Operating Activities | M3: 2025-2029 | N3: Projections
A4: Net income | B4: 6411 | C4: 8687 | D4: 9930 | E4: 11195 | F4: 12874 | G4: ='Profit Loss'!G20 -> 14041.325 | H4: ='Profit Loss'!H20 -> 15786.104 | I4: ='Profit Loss'!I20 -> 17411.45 | J4: ='Profit Loss'!J20 -> 19017.164 | K4: ='Profit Loss'!K20 -> 20568.896
A5: Adjustments to reconcile net income to net cash provided by operating activities:
A6: Amortization of customer and merchant incentives | B6: 1072 | C6: 1371 | D6: 1586 | E6: 1622 | F6: 1830 | G6: =Table3[[#This Row],[2024]]*1.05 -> 1921.5 | H6: =Table3[[#This Row],[2025E]]*1.05 -> 2017.575 | I6: =Table3[[#This Row],[2026E]]*1.05 -> 2118.4538 | J6: =Table3[[#This Row],[2027E]]*1.05 -> 2224.3764 | K6: =Table3[[#This Row],[2028E]]*1.05 -> 2335.5953
A7: Depreciation and amortization | B7: 580 | C7: 726 | D7: 750 | E7: 799 | F7: 897 | G7: =Table3[[#This Row],[2024]]*1.06 -> 950.82 | H7: =Table3[[#This Row],[2025E]]*1.06 -> 1007.8692 | I7: =Table3[[#This Row],[2026E]]*1.06 -> 1068.3414 | J7: =Table3[[#This Row],[2027E]]*1.06 -> 1132.4418 | K7: =Table3[[#This Row],[2028E]]*1.06 -> 1200.3883
A8: (Gains) losses on equity investments, net | B8: -30 | C8: -645 | D8: 145 | E8: 61 | F8: 29 | G8: 29 | H8: 29 | I8: 29 | J8: 29 | K8: 29
A9: Share-based compensation | B9: 254 | C9: 273 | D9: 295 | E9: 460 | F9: 526 | G9: =Table3[[#This Row],[2024]]*1.06 -> 557.56 | H9: =Table3[[#This Row],[2025E]]*1.06 -> 591.0136 | I9: =Table3[[#This Row],[2026E]]*1.06 -> 626.47442 | J9: =Table3[[#This Row],[2027E]]*1.06 -> 664.06288 | K9: =Table3[[#This Row],[2028E]]*1.06 -> 703.90665
A10: Deferred income taxes | B10: 73 | C10: -69 | D10: -651 | E10: -236 | F10: -527 | G10: =Table3[[#This Row],[2024]]*1.03 -> -542.81 | H10: =Table3[[#This Row],[2025E]]*1.03 -> -559.0943 | I10: =Table3[[#This Row],[2026E]]*1.03 -> -575.86713 | J10: =Table3[[#This Row],[2027E]]*1.03 -> -593.14314 | K10: =Table3[[#This Row],[2028E]]*1.03 -> -610.93744
A11: Other | B11: 14 | C11: 36 | D11: 44 | E11: 22 | F11: 191 | G11: =Table3[[#This Row],[2024]]*1.03 -> 196.73 | H11: =Table3[[#This Row],[2025E]]*1.03 -> 202.6319 | I11: =Table3[[#This Row],[2026E]]*1.03 -> 208.71086 | J11: =Table3[[#This Row],[2027E]]*1.03 -> 214.97218 | K11: =Table3[[#This Row],[2028E]]*1.03 -> 221.42135
A12: Changes in operating assets and liabilities:
A13: Accounts receivable | B13: -86 | C13: -397 | D13: -481 | E13: -546 | F13: 186 | G13: =Balance_Sheet!F7-Balance_Sheet!G7 -> -35.804829 | H13: =Balance_Sheet!G7-Balance_Sheet!H7 -> -36.580483 | I13: =Balance_Sheet!H7-Balance_Sheet!I7 -> -36.214678 | J13: =Balance_Sheet!I7-Balance_Sheet!J7 -> -35.087999 | K13: =Balance_Sheet!J7-Balance_Sheet!K7 -> -33.158159
A14: Income taxes receivable | B14: -2 | C14: -87 | D14: 12 | E14: -171 | F14: -165 | G14: -165 | H14: -165 | I14: -165 | J14: -165 | K14: -165
A15: Settlement assets | B15: 1288 | C15: 390 | D15: 48 | E15: 40 | F15: -593 | G15: =Balance_Sheet!F8-Balance_Sheet!G8 -> -416.55958 | H15: =Balance_Sheet!G8-Balance_Sheet!H8 -> -418.95596 | I15: =Balance_Sheet!H8-Balance_Sheet!I8 -> -414.7664 | J15: =Balance_Sheet!I8-Balance_Sheet!J8 -> -401.86255 | K15: =Balance_Sheet!J8-Balance_Sheet!K8 -> -379.76011
A16: Prepaid expenses | B16: -1552 | C16: -2087 | D16: -2175 | E16: -2438 | F16: -3225 | G16: =Balance_Sheet!F10-Balance_Sheet!G10 -> 490.7704 | H16: =Balance_Sheet!G10-Balance_Sheet!H10 -> -250.12296 | I16: =Balance_Sheet!H10-Balance_Sheet!I10 -> -247.62173 | J16: =Balance_Sheet!I10-Balance_Sheet!J10 -> -239.91794 | K16: =Balance_Sheet!J10-Balance_Sheet!K10 -> -226.72246
A17: Accrued litigation and legal settlements | B17: -73 | C17: -1 | D17: 240 | E17: -375 | F17: 205 | G17: 205 | H17: 205 | I17: 205 | J17: 205 | K17: 205
A18: Restricted security deposits held for customers | B18: 326 | C18: 177 | D18: -305 | E18: 277 | F18: 29 | G18: 29 | H18: 29 | I18: 29 | J18: 29 | K18: 29
A19: Accounts payable | B19: 26 | C19: 100 | D19: 190 | E19: -99 | F19: 75 | G19: =(Balance_Sheet!G20-Balance_Sheet!F20)-1 -> 101.75721 | H19: =(Balance_Sheet!H20-Balance_Sheet!G20)-1 -> 102.17572 | I19: =(Balance_Sheet!I20-Balance_Sheet!H20)-1 -> 101.14396 | J19: =(Balance_Sheet!J20-Balance_Sheet!I20)-1 -> 97.966152 | K19: =(Balance_Sheet!K20-Balance_Sheet!J20)-1 -> 92.523013
A20: Settlement obligations | B20: -1242 | C20: -568 | D20: 201 | E20: 282 | F20: 922 | G20: 922 | H20: 922 | I20: 922 | J20: 922 | K20: 922
A21: Accrued expenses | B21: -114 | C21: 1355 | D21: 1188 | E21: 571 | F21: 1587 | G21: =Balance_Sheet!G24-Balance_Sheet!F24 -> 1143.9215 | H21: =Balance_Sheet!H24-Balance_Sheet!G24 -> 1153.6922 | I21: =Balance_Sheet!I24-Balance_Sheet!H24 -> 1142.1552 | J21: =Balance_Sheet!J24-Balance_Sheet!I24 -> 1106.6215 | K21: =Balance_Sheet!K24-Balance_Sheet!J24 -> 1045.7573
A22: Long-term taxes payable | B22: -37 | C22: -52 | D22: -121 | E22: -129 | F22: -163 | G22: -163 | H22: -163 | I22: -163 | J22: -163 | K22: -163
A23: Net change in other assets and liabilities | B23: 316 | C23: 254 | D23: 299 | E23: 645 | F23: 102 | G23: 102 | H23: 102 | I23: 102 | J23: 102 | K23: 102
A24: Net cash provided by operating activities | B24: 7224 | C24: 9463 | D24: 11195 | E24: 11980 | F24: 14780 | G24: =SUM(G4:G23) -> 19368.21 | H24: =SUM(H4:H23) -> 20555.308 | I24: =SUM(I4:I23) -> 22361.259 | J24: =SUM(J4:J23) -> 24146.593 | K24: =SUM(K4:K23) -> 25876.91
A25: Investing Activities
A26: Purchases of investment securities available-for-sale | B26: -220 | C26: -389 | D26: -267 | E26: -300 | F26: -508 | G26: =Table3[[#This Row],[2024]]*1.05 -> -533.4 | H26: =Table3[[#This Row],[2025E]]*1.05 -> -560.07 | I26: =Table3[[#This Row],[2026E]]*1.05 -> -588.0735 | J26: =Table3[[#This Row],[2027E]]*1.05 -> -617.47718 | K26: =Table3[[#This Row],[2028E]]*1.05 -> -648.35103
A27: Purchases of investments held-to-maturity | B27: -198 | C27: -294 | D27: -239 | E27: -347 | F27: -108 | G27: =Table3[[#This Row],[2024]]*1.05 -> -113.4 | H27: =Table3[[#This Row],[2025E]]*1.05 -> -119.07 | I27: =Table3[[#This Row],[2026E]]*1.05 -> -125.0235 | J27: =Table3[[#This Row],[2027E]]*1.05 -> -131.27468 | K27: =Table3[[#This Row],[2028E]]*1.05 -> -137.83841
A28: Proceeds from sales of investment securities available-for-sale | B28: 361 | C28: 83 | D28: 54 | E28: 87 | F28: 199 | G28: =Table3[[#This Row],[2024]]*1.05 -> 208.95 | H28: =Table3[[#This Row],[2025E]]*1.05 -> 219.3975 | I28: =Table3[[#This Row],[2026E]]*1.05 -> 230.36738 | J28: =Table3[[#This Row],[2027E]]*1.05 -> 241.88574 | K28: =Table3[[#This Row],[2028E]]*1.05 -> 253.98003
A29: Proceeds from maturities of investment securities available-for-sale | B29: 140 | C29: 291 | D29: 211 | E29: 191 | F29: 262 | G29: =Table3[[#This Row],[2024]]*1.05 -> 275.1 | H29: =Table3[[#This Row],[2025E]]*1.05 -> 288.855 | I29: =Table3[[#This Row],[2026E]]*1.05 -> 303.29775 | J29: =Table3[[#This Row],[2027E]]*1.05 -> 318.46264 | K29: =Table3[[#This Row],[2028E]]*1.05 -> 334.38577
A30: Proceeds from maturities of investments held-to-maturity | B30: 121 | C30: 296 | D30: 265 | E30: 157 | F30: 378 | G30: =Table3[[#This Row],[2024]]*1.05 -> 396.9 | H30: =Table3[[#This Row],[2025E]]*1.05 -> 416.745 | I30: =Table3[[#This Row],[2026E]]*1.05 -> 437.58225 | J30: =Table3[[#This Row],[2027E]]*1.05 -> 459.46136 | K30: =Table3[[#This Row],[2028E]]*1.05 -> 482.43443
A31: Purchases of property and equipment | B31: -339 | C31: -407 | D31: -442 | E31: -371 | F31: -474 | G31: =Table3[[#This Row],[2024]]*1.05 -> -497.7 | H31: =Table3[[#This Row],[2025E]]*1.05 -> -522.585 | I31: =Table3[[#This Row],[2026E]]*1.05 -> -548.71425 | J31: =Table3[[#This Row],[2027E]]*1.05 -> -576.14996 | K31: =Table3[[#This Row],[2028E]]*1.05 -> -604.95746
A32: Capitalized software | B32: -369 | C32: -407 | D32: -655 | E32: -717 | F32: -720 | G32: =Table3[[#This Row],[2024]]*1.05 -> -756 | H32: =Table3[[#This Row],[2025E]]*1.05 -> -793.8 | I32: =Table3[[#This Row],[2026E]]*1.05 -> -833.49 | J32: =Table3[[#This Row],[2027E]]*1.05 -> -875.1645 | K32: =Table3[[#This Row],[2028E]]*1.05 -> -918.92273
A33: Purchases of equity investments | B33: -214 | C33: -228 | D33: -88 | E33: -89 | F33: -42 | G33: =Table3[[#This Row],[2024]]*1.05 -> -44.1 | H33: =Table3[[#This Row],[2025E]]*1.05 -> -46.305 | I33: =Table3[[#This Row],[2026E]]*1.05 -> -48.62025 | J33: =Table3[[#This Row],[2027E]]*1.05 -> -51.051263 | K33: =Table3[[#This Row],[2028E]]*1.05 -> -53.603826
A34: Proceeds from sales of equity investments | B34: 0 | C34: 186 | D34: 7 | E34: 44 | F34: 125 | G34: =Table3[[#This Row],[2024]]*1.05 -> 131.25 | H34: =Table3[[#This Row],[2025E]]*1.05 -> 137.8125 | I34: =Table3[[#This Row],[2026E]]*1.05 -> 144.70312 | J34: =Table3[[#This Row],[2027E]]*1.05 -> 151.93828 | K34: =Table3[[#This Row],[2028E]]*1.05 -> 159.5352
A35: Acquisition of businesses, net of cash acquired | B35: -989 | C35: -4436 | D35: -313 | E35: 0 | F35: -2511 | G35: 0 | H35: 0 | I35: 0 | J35: 0 | K35: 0
A36: Settlement of interest rate derivative contracts | B36: -175 | C36: 0 | D36: 0 | E36: 0 | F36: 0 | G36: 0 | H36: 0 | I36: 0 | J36: 0 | K36: 0
A37: Other investing activities | B37: 3 | C37: 33 | D37: -3 | E37: -6 | F37: -3 | G37: -3 | H37: -3 | I37: -3 | J37: -3 | K37: -3
A38: Net cash used in investing activities | B38: -1879 | C38: -5272 | D38: -1470 | E38: -1351 | F38: -3402 | G38: =SUM(G26:G37) -> -935.4 | H38: =SUM(H26:H37) -> -982.02 | I38: =SUM(I26:I37) -> -1030.971 | J38: =SUM(J26:J37) -> -1082.3696 | K38: =SUM(K26:K37) -> -1136.338
A39: Financing Activities
A40: Purchases of treasury stock | B40: -4473 | C40: -5904 | D40: -8753 | E40: -9032 | F40: -11035 | G40: =Table3[[#This Row],[2024]]*1.07 -> -11807.45 | H40: =Table3[[#This Row],[2025E]]*1.07 -> -12633.972 | I40: =Table3[[#This Row],[2026E]]*1.07 -> -13518.35 | J40: =Table3[[#This Row],[2027E]]*1.07 -> -14464.634 | K40: =Table3[[#This Row],[2028E]]*1.07 -> -15477.158
A41: Dividends paid | B41: -1605 | C41: -1741 | D41: -1903 | E41: -2158 | F41: -2448 | G41: =-'Profit Loss'!G20*Assumptions!F8 -> -4212.3976 | H41: =-'Profit Loss'!H20*Assumptions!F8 -> -4735.8312 | I41: =-'Profit Loss'!I20*Assumptions!F8 -> -5223.4349 | J41: =-'Profit Loss'!J20*Assumptions!F8 -> -5705.1492 | K41: =-'Profit Loss'!K20*Assumptions!F8 -> -6170.6688
A42: Proceeds from debt, net | B42: 3959 | C42: 2024 | D42: 1123 | E42: 1554 | F42: 3960 | G42: 3960 | H42: 3960 | I42: 3960 | J42: 3960 | K42: 3960
A43: Payment of debt | B43: 0 | C43: -650 | D43: -724 | E43: 0 | F43: -1336 | G43: -1336 | H43: -1336 | I43: -1336 | J43: -1336 | K43: -1336
A44: Acquisition of redeemable non-controlling interests | B44: -49 | C44: 0 | D44: -4 | E44: 0 | F44: 0 | G44: 0 | H44: 0 | I44: 0 | J44: 0 | K44: 0
A45: Acquisition of non-controlling interest | B45: 0 | C45: -133 | D45: 0 | E45: 0 | F45: 0 | G45: 0 | H45: 0 | I45: 0 | J45: 0 | K45: 0
A46: Contingent consideration paid | B46: 0 | C46: -64 | D46: 0 | E46: 0 | F46: 0 | G46: 0 | H46: 0 | I46: 0 | J46: 0 | K46: 0
A47: Tax withholdings related to share-based payments | B47: -150 | C47: -133 | D47: -141 | E47: -89 | F47: -178 | G47: =Table3[[#This Row],[2024]]*1.05 -> -186.9 | H47: =Table3[[#This Row],[2025E]]*1.05 -> -196.245 | I47: =Table3[[#This Row],[2026E]]*1.05 -> -206.05725 | J47: =Table3[[#This Row],[2027E]]*1.05 -> -216.36011 | K47: =Table3[[#This Row],[2028E]]*1.05 -> -227.17812
A48: Cash proceeds from exercise of stock options | B48: 97 | C48: 61 | D48: 90 | E48: 237 | F48: 224 | G48: =Table3[[#This Row],[2024]]*1.05 -> 235.2 | H48: =Table3[[#This Row],[2025E]]*1.05 -> 246.96 | I48: =Table3[[#This Row],[2026E]]*1.05 -> 259.308 | J48: =Table3[[#This Row],[2027E]]*1.05 -> 272.2734 | K48: =Table3[[#This Row],[2028E]]*1.05 -> 285.88707
A49: Other financing activities | B49: 69 | C49: -15 | D49: -16 | E49: 0 | F49: -23 | G49: -23 | H49: -23 | I49: -23 | J49: -23 | K49: -23
A50: Net cash used in financing activities | B50: -2152 | C50: -6555 | D50: -10328 | E50: -9488 | F50: -10836 | G50: =SUM(G40:G49) -> -13370.548 | H50: =SUM(H40:H49) -> -14718.088 | I50: =SUM(I40:I49) -> -16087.534 | J50: =SUM(J40:J49) -> -17512.87 | K50: =SUM(K40:K49) -> -18988.118
A51: Effect of exchange rate changes on cash, cash equivalents, restricted cash and restricted cash equivalents | B51: 257 | C51: -153 | D51: -103 | E51: 128 | F51: -199 | G51: 0 | H51: 0 | I51: 0 | J51: 0 | K51: 0
A52: Net increase (decrease) in cash, cash equivalents, restricted cash and restricted cash equivalents | B52: 3450 | C52: -2517 | D52: -706 | E52: 1269 | F52: 343 | G52: =G24+G38+G50+G51 -> 5062.2625 | H52: =H24+H38+H50+H51 -> 4855.2003 | I52: =I24+I38+I50+I51 -> 5242.7548 | J52: =J24+J38+J50+J51 -> 5551.3539 | K52: =K24+K38+K50+K51 -> 5752.4536
A53: Cash, cash equivalents, restricted cash and restricted cash equivalents - beginning of period | B53: 8969 | C53: 12419 | D53: 9902 | E53: 9196 | F53: 10465 | G53: =Balance_Sheet!F4 -> 8442 | H53: =G54 -> 13504.262 | I53: =H54 -> 18359.463 | J53: =I54 -> 23602.217 | K53: =J54 -> 29153.571
A54: Cash, cash equivalents, restricted cash and restricted cash equivalents - end of period | B54: 12419 | C54: 9902 | D54: 9196 | E54: 10465 | F54: 10808 | G54: =G53+G52 -> 13504.262 | H54: =H53+H52 -> 18359.463 | I54: =I53+I52 -> 23602.217 | J54: =J53+J52 -> 29153.571 | K54: =K53+K52 -> 34906.025
A55: Free Cash Flow | B55: =B24-B31 -> 7563 | C55: =C24-C31 -> 9870 | D55: =D24-D31 -> 11637 | E55: =E24-E31 -> 12351 | F55: =F24-F31 -> 15254 | G55: =G24-ABS(G31) -> 18870.51 | H55: =H24-ABS(H31) -> 20032.723 | I55: =I24-ABS(I31) -> 21812.545 | J55: =J24-ABS(J31) -> 23570.443 | K55: =K24-ABS(K31) -> 25271.952

Sheet Common Size
A1: Common Size Income Statement – Mastercard | B1: 2020 | C1: 2021 | D1: 2022 | E1: 2023 | F1: 2024 | G1: 2025 | H1: 2026 | I1: 2027 | J1: 2028 | K1: 2029
A2: Variables | B2: 2020 | C2: 2021 | D2: 2022 | E2: 2023 | F2: 2024 | G2: 2025E | H2: 2026E | I2: 2027E | J2: 2028E | K2: 2029E | L2: Item | M2: 2025 | N2: 2026 | O2: 2027 | P2: 2028 | Q2: 2029
A3: Net Revenue | B3: ='Profit Loss'!B4/'Profit Loss'!B4 -> 1 | C3: ='Profit Loss'!C4/'Profit Loss'!C4 -> 1 | D3: ='Profit Loss'!D4/'Profit Loss'!D4 -> 1 | E3: ='Profit Loss'!E4/'Profit Loss'!E4 -> 1 | F3: ='Profit Loss'!F4/'Profit Loss'!F4 -> 1 | G3: ='Profit Loss'!G4/'Profit Loss'!G4 -> 1 | H3: ='Profit Loss'!H4/'Profit Loss'!H4 -> 1 | I3: ='Profit Loss'!I4/'Profit Loss'!I4 -> 1 | ... K3: ='Profit Loss'!K4/'Profit Loss'!K4 -> 1 | L3: Revenue Growth | M3: 0.12 | N3: 0.11 | O3: 0.1 | P3: 0.09 | Q3: 0.08
A4: General & Administrative | B4: ='Profit Loss'!B6/Table1[[#This Row],[2020]] -> 0.38624926 | C4: =Table10[[#This Row],[2020]]*(1+2%) -> 0.39397425 | D4: =Table10[[#This Row],[2021]]*(1+2%) -> 0.40185374 | E4: =Table10[[#This Row],[2022]]*(1+2%) -> 0.40989081 | F4: =Table10[[#This Row],[2023]]*(1+2%) -> 0.41808863 | G4: =G3*Table35[[#This Row],[2025]] -> 0.42 | H4: =H3*Table35[[#This Row],[2026]] -> 0.425 | I4: =I3*Table35[[#This Row],[2027]] -> 0.43 | J4: =J3*Table35[[#This Row],[2028]] -> 0.43 | K4: =K3*Table35[[#This Row],[2029]] -> 0.43 | L4: G&A % | M4: 0.42 | N4: 0.425 | O4: 0.43 | P4: 0.43 | Q4: 0.43
A5: Advertising & Marketing | B5: ='Profit Loss'!B7/'Profit Loss'!B4 -> 0.04293837 | C5: ='Profit Loss'!C7/'Profit Loss'!C4 -> 0.04739462 | D5: ='Profit Loss'!D7/'Profit Loss'!D4 -> 0.035481405 | E5: ='Profit Loss'!E7/'Profit Loss'!E4 -> 0.032871145 | F5: ='Profit Loss'!F7/'Profit Loss'!F4 -> 0.028934569 | G5: =Table35[[#This Row],[2025]] -> 0.03 | H5: =Table35[[#This Row],[2025]] -> 0.03 | I5: =Table35[[#This Row],[2025]] -> 0.03 | J5: =Table35[[#This Row],[2025]] -> 0.03 | K5: =Table35[[#This Row],[2025]] -> 0.03 | L5: Marketing % | M5: 0.03 | N5: 0.03 | O5: 0.03 | P5: 0.03 | Q5: 0.03
A6: Depreciation & Amortization | B6: ='Profit Loss'!B8/'Profit Loss'!B4 -> 0.037906019 | C6: ='Profit Loss'!C8/'Profit Loss'!C4 -> 0.038445245 | D6: ='Profit Loss'!D8/'Profit Loss'!D4 -> 0.033727571 | E6: ='Profit Loss'!E8/'Profit Loss'!E4 -> 0.031835206 | F6: ='Profit Loss'!F8/'Profit Loss'!F4 -> 0.031845777 | G6: =Table35[[#This Row],[2025]] -> 0.03 | H6: =Table35[[#This Row],[2025]] -> 0.03 | I6: =Table35[[#This Row],[2025]] -> 0.03 | J6: =Table35[[#This Row],[2025]] -> 0.03 | K6: =Table35[[#This Row],[2025]] -> 0.03 | L6: Depreciation % | M6: 0.03 | N6: 0.029 | O6: 0.028 | P6: 0.027 | Q6: 0.026
A7: Provision for Litigation | B7: ='Profit Loss'!B9/'Profit Loss'!B4 -> 0.00477093 | C7: ='Profit Loss'!C9/'Profit Loss'!C4 -> 0.0049777589 | D7: ='Profit Loss'!D9/'Profit Loss'!D4 -> 0.016009354 | E7: ='Profit Loss'!E9/'Profit Loss'!E4 -> 0.021475815 | F7: ='Profit Loss'!F9/'Profit Loss'!F4 -> 0.024141726 | G7: ='Profit Loss'!G9/'Profit Loss'!G4 -> 0.022836768 | H7: ='Profit Loss'!H9/'Profit Loss'!H4 -> 0.021798733 | I7: ='Profit Loss'!I9/'Profit Loss'!I4 -> 0.02099878 | ... K7: ='Profit Loss'!K9/'Profit Loss'!K4 -> 0.020033882 | L7: Capex % | M7: 0.05 | N7: 0.05 | O7: 0.05 | P7: 0.05 | Q7: 0.05
A8: Total Operating Expenses | B8: ='Profit Loss'!B10/'Profit Loss'!B4 -> 0.47186458 | C8: ='Profit Loss'!C10/'Profit Loss'!C4 -> 0.46610888 | D8: ='Profit Loss'!D10/'Profit Loss'!D4 -> 0.44848676 | E8: ='Profit Loss'!E10/'Profit Loss'!E4 -> 0.44186788 | F8: ='Profit Loss'!F10/'Profit Loss'!F4 -> 0.44679945 | G8: ='Profit Loss'!G10/'Profit Loss'!G4 -> 0.45 | H8: ='Profit Loss'!H10/'Profit Loss'!H4 -> 0.44 | I8: ='Profit Loss'!I10/'Profit Loss'!I4 -> 0.435 | ... K8: ='Profit Loss'!K10/'Profit Loss'!K4 -> 0.425 | L8: Working Capital % | M8: 0.04 | N8: 0.04 | O8: 0.04 | P8: 0.04 | Q8: 0.04
A9: Operating Income | B9: ='Profit Loss'!B11/'Profit Loss'!B4 -> 0.52813542 | C9: ='Profit Loss'!C11/'Profit Loss'!C4 -> 0.53389112 | D9: ='Profit Loss'!D11/'Profit Loss'!D4 -> 0.55151324 | E9: ='Profit Loss'!E11/'Profit Loss'!E4 -> 0.55813212 | F9: ='Profit Loss'!F11/'Profit Loss'!F4 -> 0.55320055 | G9: ='Profit Loss'!G11/'Profit Loss'!G4 -> 0.55 | H9: ='Profit Loss'!H11/'Profit Loss'!H4 -> 0.56 | I9: ='Profit Loss'!I11/'Profit Loss'!I4 -> 0.565 | ... K9: ='Profit Loss'!K11/'Profit Loss'!K4 -> 0.575 | L9: Cash % of Assets | M9: 0.3 | N9: 0.32 | O9: 0.33 | P9: 0.34 | Q9: 0.35
A10: Investment Income | B10: ='Profit Loss'!B13/'Profit Loss'!B4 -> 0.0015685249 | C10: ='Profit Loss'!C13/'Profit Loss'!C4 -> 0.00058250371 | D10: ='Profit Loss'!D13/'Profit Loss'!D4 -> 0.0027431758 | E10: ='Profit Loss'!E13/'Profit Loss'!E4 -> 0.010917205 | F10: ='Profit Loss'!F13/'Profit Loss'!F4 -> 0.01160933 | G10: ='Profit Loss'!G13/'Profit Loss'!G4 -> 0.01087721 | H10: ='Profit Loss'!H13/'Profit Loss'!H4 -> 0.010283908 | I10: ='Profit Loss'!I13/'Profit Loss'!I4 -> 0.0098121689 | ... K10: ='Profit Loss'!K13/'Profit Loss'!K4 -> 0.0091838369 | L10: Interest Rate | M10: 0.035 | N10: 0.035 | O10: 0.035 | P10: 0.035 | Q10: 0.035
A11: Interest Expense | B11: ='Profit Loss'!B15/'Profit Loss'!B4 -> -0.024834978 | C11: ='Profit Loss'!C15/'Profit Loss'!C4 -> -0.022823554 | D11: ='Profit Loss'!D15/'Profit Loss'!D4 -> -0.021180915 | E11: ='Profit Loss'!E15/'Profit Loss'!E4 -> -0.022910192 | F11: ='Profit Loss'!F15/'Profit Loss'!F4 -> -0.02293464 | G11: ='Profit Loss'!G15/'Profit Loss'!G4 -> -0.026232538 | H11: ='Profit Loss'!H15/'Profit Loss'!H4 -> -0.023847762 | I11: ='Profit Loss'!I15/'Profit Loss'!I4 -> -0.02187868 | ... K11: ='Profit Loss'!K15/'Profit Loss'!K4 -> -0.018932745 | L11: Tax Rate | M11: 0.16 | N11: 0.16 | O11: 0.16 | P11: 0.16 | Q11: 0.16
A12: Total Other Income | B12: ='Profit Loss'!B17/'Profit Loss'!B4 -> -0.020979021 | C12: ='Profit Loss'!C17/'Profit Loss'!C4 -> 0.011914849 | D12: ='Profit Loss'!D17/'Profit Loss'!D4 -> -0.02392409 | E12: ='Profit Loss'!E17/'Profit Loss'!E4 -> -0.014702367 | F12: ='Profit Loss'!F17/'Profit Loss'!F4 -> -0.011644833 | G12: ='Profit Loss'!G17/'Profit Loss'!G4 -> -0.015355328 | H12: ='Profit Loss'!H17/'Profit Loss'!H4 -> -0.013563854 | I12: ='Profit Loss'!I17/'Profit Loss'!I4 -> -0.012066511 | ... K12: ='Profit Loss'!K17/'Profit Loss'!K4 -> -0.0097489084
A13: Income Before Tax | B13: ='Profit Loss'!B18/'Profit Loss'!B4 -> 0.5071564 | C13: ='Profit Loss'!C18/'Profit Loss'!C4 -> 0.54580597 | D13: ='Profit Loss'!D18/'Profit Loss'!D4 -> 0.52758915 | E13: ='Profit Loss'!E18/'Profit Loss'!E4 -> 0.54342976 | F13: ='Profit Loss'!F18/'Profit Loss'!F4 -> 0.54155572 | G13: ='Profit Loss'!G18/'Profit Loss'!G4 -> 0.53464467 | H13: ='Profit Loss'!H18/'Profit Loss'!H4 -> 0.54643615 | I13: ='Profit Loss'!I18/'Profit Loss'!I4 -> 0.55293349 | ... K13: ='Profit Loss'!K18/'Profit Loss'!K4 -> 0.56525109 | M13: 2020-2024 | N13: Historicals
A14: Income Tax Expense | B14: ='Profit Loss'!B19/'Profit Loss'!B4 -> 0.088164172 | C14: ='Profit Loss'!C19/'Profit Loss'!C4 -> 0.08578691 | D14: ='Profit Loss'!D19/'Profit Loss'!D4 -> 0.081036111 | E14: ='Profit Loss'!E19/'Profit Loss'!E4 -> 0.097378277 | F14: ='Profit Loss'!F19/'Profit Loss'!F4 -> 0.084496041 | G14: ='Profit Loss'!G19/'Profit Loss'!G4 -> 0.085543148 | H14: ='Profit Loss'!H19/'Profit Loss'!H4 -> 0.087429783 | I14: ='Profit Loss'!I19/'Profit Loss'!I4 -> 0.088469358 | ... K14: ='Profit Loss'!K19/'Profit Loss'!K4 -> 0.090440175 | M14: 2025-2029 | N14: Projections
A15: Net Income | B15: ='Profit Loss'!B20/'Profit Loss'!B4 -> 0.41899222 | C15: ='Profit Loss'!C20/'Profit Loss'!C4 -> 0.46001906 | D15: ='Profit Loss'!D20/'Profit Loss'!D4 -> 0.44655304 | E15: ='Profit Loss'!E20/'Profit Loss'!E4 -> 0.44605148 | F15: ='Profit Loss'!F20/'Profit Loss'!F4 -> 0.45705968 | G15: ='Profit Loss'!G20/'Profit Loss'!G4 -> 0.44910152 | H15: ='Profit Loss'!H20/'Profit Loss'!H4 -> 0.45900636 | I15: ='Profit Loss'!I20/'Profit Loss'!I4 -> 0.46446413 | ... K15: ='Profit Loss'!K20/'Profit Loss'!K4 -> 0.47481092
A16: EBITDA | B16: ='Profit Loss'!B25/'Profit Loss'!B4 -> 0.56604144 | C16: ='Profit Loss'!C25/'Profit Loss'!C4 -> 0.57233637 | D16: ='Profit Loss'!D25/'Profit Loss'!D4 -> 0.58524081 | E16: ='Profit Loss'!E25/'Profit Loss'!E4 -> 0.58996733 | F16: ='Profit Loss'!F25/'Profit Loss'!F4 -> 0.58504633 | G16: ='Profit Loss'!G25/'Profit Loss'!G4 -> 0.58098508 | H16: ='Profit Loss'!H25/'Profit Loss'!H4 -> 0.59042172 | I16: ='Profit Loss'!I25/'Profit Loss'!I4 -> 0.59514262 | ... K16: ='Profit Loss'!K25/'Profit Loss'!K4 -> 0.60542432
A18: Common Size Balance Sheet – Mastercard | B18: 2020 | C18: 2021 | D18: 2022 | E18: 2023 | F18: 2024 | G18: 2025 | H18: 2026 | I18: 2027 | J18: 2028 | K18: 2029
A19: Variables | B19: 2020 | C19: 2021 | D19: 2022 | E19: 2023 | F19: 2024 | G19: 2025E | H19: 2026E | I19: 2027E | J19: 2028E | K19: 2029E
A20: Cash & Cash Equivalents | B20: =Balance_Sheet!B4/Balance_Sheet!B18 -> 0.30112554 | C20: =Balance_Sheet!C4/Balance_Sheet!C18 -> 0.1970055 | D20: =Balance_Sheet!D4/Balance_Sheet!D18 -> 0.18097304 | E20: =Balance_Sheet!E4/Balance_Sheet!E18 -> 0.20231813 | F20: =Balance_Sheet!F4/Balance_Sheet!F18 -> 0.17557871 | G20: =M9 -> 0.3 | H20: =N9 -> 0.32 | I20: =O9 -> 0.33 | J20: =P9 -> 0.34 | K20: =Q9 -> 0.35
A21: Accounts Receivable | B21: =Balance_Sheet!B7/Balance_Sheet!B18 -> 0.078787518 | C21: =Balance_Sheet!C7/Balance_Sheet!C18 -> 0.079800366 | D21: =Balance_Sheet!D7/Balance_Sheet!D18 -> 0.088446441 | E21: =Balance_Sheet!E7/Balance_Sheet!E18 -> 0.013946476 | F21: =Balance_Sheet!F7/Balance_Sheet!F18 -> 0.006863418 | G21: =Balance_Sheet!G7/Balance_Sheet!G18 -> 0.0062318024 | H21: =Balance_Sheet!H7/Balance_Sheet!H18 -> 0.0057047204 | I21: =Balance_Sheet!I7/Balance_Sheet!I18 -> 0.0052553076 | ... K21: =Balance_Sheet!K7/Balance_Sheet!K18 -> 0.0045136326
A22: Settlement Assets | B22: =Balance_Sheet!B8/Balance_Sheet!B18 -> 0.050797999 | C22: =Balance_Sheet!C8/Balance_Sheet!C18 -> 0.03501553 | D22: =Balance_Sheet!D8/Balance_Sheet!D18 -> 0.032796199 | E22: =Balance_Sheet!E8/Balance_Sheet!E18 -> 0.095646438 | F22: =Balance_Sheet!F8/Balance_Sheet!F18 -> 0.078471746 | G22: =Balance_Sheet!G8/Balance_Sheet!G18 -> 0.07137278 | H22: =Balance_Sheet!H8/Balance_Sheet!H18 -> 0.065336114 | I22: =Balance_Sheet!I8/Balance_Sheet!I18 -> 0.060188994 | ... K22: =Balance_Sheet!K8/Balance_Sheet!K18 -> 0.051694596
A23: Total Current Assets | B23: =SUM(B20:B22) -> 0.43071105 | C23: =SUM(C20:C22) -> 0.31182139 | D23: =SUM(D20:D22) -> 0.30221568 | E23: =SUM(E20:E22) -> 0.31191104 | F23: =SUM(F20:F22) -> 0.26091387 | G23: =SUM(G20:G22) -> 0.37760458 | H23: =SUM(H20:H22) -> 0.39104083 | I23: =SUM(I20:I22) -> 0.3954443 | ... K23: =SUM(K20:K22) -> 0.40620823
A24: PPE | B24: =Balance_Sheet!B12/Balance_Sheet!B18 -> 0.056634111 | C24: =Balance_Sheet!C12/Balance_Sheet!C18 -> 0.050625183 | D24: =Balance_Sheet!D12/Balance_Sheet!D18 -> 0.0518025 | E24: =Balance_Sheet!E12/Balance_Sheet!E18 -> 0.048553524 | F24: =Balance_Sheet!F12/Balance_Sheet!F18 -> 0.044466629 | G24: =Balance_Sheet!G12/Balance_Sheet!G18 -> 0.037879591 | H24: =Balance_Sheet!H12/Balance_Sheet!H18 -> 0.032784353 | I24: =Balance_Sheet!I12/Balance_Sheet!I18 -> 0.028816236 | ... K24: =Balance_Sheet!K12/Balance_Sheet!K18 -> 0.023164581
A25: Intangible Assets | B25: =Balance_Sheet!B14/Balance_Sheet!B18 -> 0.14768938 | C25: =Balance_Sheet!C14/Balance_Sheet!C18 -> 0.20340333 | D25: =Balance_Sheet!D14/Balance_Sheet!D18 -> 0.19424646 | E25: =Balance_Sheet!E14/Balance_Sheet!E18 -> 0.18045609 | F25: =Balance_Sheet!F14/Balance_Sheet!F18 -> 0.19119819 | G25: =Balance_Sheet!G14/Balance_Sheet!G18 -> 0.15661073 | H25: =Balance_Sheet!H14/Balance_Sheet!H18 -> 0.13033153 | I25: =Balance_Sheet!I14/Balance_Sheet!I18 -> 0.11015058 | ... K25: =Balance_Sheet!K14/Balance_Sheet!K18 -> 0.081866706
A26: Other Assets | B26: =Balance_Sheet!B17/Balance_Sheet!B18 -> 0.15974869 | C26: =Balance_Sheet!C17/Balance_Sheet!C18 -> 0.18566991 | D26: =Balance_Sheet!D17/Balance_Sheet!D18 -> 0.19574424 | E26: =Balance_Sheet!E17/Balance_Sheet!E18 -> 0.19612231 | F26: =Balance_Sheet!F17/Balance_Sheet!F18 -> 0.20712964 | G26: =Balance_Sheet!G17/Balance_Sheet!G18 -> 0.18828565 | H26: =Balance_Sheet!H17/Balance_Sheet!H18 -> 0.17236057 | I26: =Balance_Sheet!I17/Balance_Sheet!I18 -> 0.15878216 | ... K26: =Balance_Sheet!K17/Balance_Sheet!K18 -> 0.13637343
A27: Total Assets | B27: 1 | C27: 1 | D27: 1 | E27: 1 | F27: 1 | G27: 1 | H27: 1 | I27: 1 | J27: 1 | K27: 1
A28: Liabilities
A29: Accounts Payable | B29: =Balance_Sheet!B20/Balance_Sheet!B18 -> 0.015691996 | C29: =Balance_Sheet!C20/Balance_Sheet!C18 -> 0.019591707 | D29: =Balance_Sheet!D20/Balance_Sheet!D18 -> 0.023912819 | E29: =Balance_Sheet!E20/Balance_Sheet!E18 -> 0.019647569 | F29: =Balance_Sheet!F20/Balance_Sheet!F18 -> 0.019321562 | G29: =Balance_Sheet!G20/Balance_Sheet!G18 -> 0.017576879 | H29: =Balance_Sheet!H20/Balance_Sheet!H18 -> 0.016090237 | I29: =Balance_Sheet!I20/Balance_Sheet!I18 -> 0.014822663 | ... K29: =Balance_Sheet!K20/Balance_Sheet!K18 -> 0.012730759
A30: Settlement Obligations | B30: =Balance_Sheet!B21/Balance_Sheet!B18 -> 0.043919724 | C30: =Balance_Sheet!C21/Balance_Sheet!C18 -> 0.024237437 | D30: =Balance_Sheet!D21/Balance_Sheet!D18 -> 0.028690218 | E30: =Balance_Sheet!E21/Balance_Sheet!E18 -> 0.032957972 | F30: =Balance_Sheet!F21/Balance_Sheet!F18 -> 0.048168715 | G30: =Balance_Sheet!G21/Balance_Sheet!G18 -> 0.04367588 | H30: =Balance_Sheet!H21/Balance_Sheet!H18 -> 0.039981801 | I30: =Balance_Sheet!I21/Balance_Sheet!I18 -> 0.036832071 | ... K30: =Balance_Sheet!K21/Balance_Sheet!K18 -> 0.031634007
A31: Accrued Expenses | B31: =Balance_Sheet!B24/Balance_Sheet!B18 -> 0.16168414 | C31: =Balance_Sheet!C24/Balance_Sheet!C18 -> 0.17632536 | D31: =Balance_Sheet!D24/Balance_Sheet!D18 -> 0.2014513 | E31: =Balance_Sheet!E24/Balance_Sheet!E18 -> 0.2006455 | F31: =Balance_Sheet!F24/Balance_Sheet!F18 -> 0.21615607 | G31: =Balance_Sheet!G24/Balance_Sheet!G18 -> 0.19654146 | H31: =Balance_Sheet!H24/Balance_Sheet!H18 -> 0.1799181 | I31: =Balance_Sheet!I24/Balance_Sheet!I18 -> 0.16574432 | ... K31: =Balance_Sheet!K24/Balance_Sheet!K18 -> 0.14235303
A32: Other Current Liabilities | B32: =Balance_Sheet!B26/Balance_Sheet!B18 -> 0.036565031 | C32: =Balance_Sheet!C26/Balance_Sheet!C18 -> 0.036210146 | D32: =Balance_Sheet!D26/Balance_Sheet!D18 -> 0.036075819 | E32: =Balance_Sheet!E26/Balance_Sheet!E18 -> 0.037905202 | F32: =Balance_Sheet!F26/Balance_Sheet!F18 -> 0.042178823 | G32: =Balance_Sheet!G26/Balance_Sheet!G18 -> 0.038349553 | H32: =Balance_Sheet!H26/Balance_Sheet!H18 -> 0.035105971 | I32: =Balance_Sheet!I26/Balance_Sheet!I18 -> 0.032340355 | ... K32: =Balance_Sheet!K26/Balance_Sheet!K18 -> 0.027776201
A33: Total Current Liabilities | B33: =Balance_Sheet!B27/Balance_Sheet!B18 -> 0.35275727 | C33: =Balance_Sheet!C27/Balance_Sheet!C18 -> 0.34941198 | D33: =Balance_Sheet!D27/Balance_Sheet!D18 -> 0.36594877 | E33: =Balance_Sheet!E27/Balance_Sheet!E18 -> 0.38315115 | F33: =Balance_Sheet!F27/Balance_Sheet!F18 -> 0.3997421 | G33: =Balance_Sheet!G27/Balance_Sheet!G18 -> 0.35668924 | H33: =Balance_Sheet!H27/Balance_Sheet!H18 -> 0.32148209 | I33: =Balance_Sheet!I27/Balance_Sheet!I18 -> 0.29232345 | ... K33: =Balance_Sheet!K27/Balance_Sheet!K18 -> 0.24614354
A34: Long-Term Debt | B34: =Balance_Sheet!B28/Balance_Sheet!B18 -> 0.35799786 | C34: =Balance_Sheet!C28/Balance_Sheet!C18 -> 0.34800499 | D34: =Balance_Sheet!D28/Balance_Sheet!D18 -> 0.35505113 | E34: =Balance_Sheet!E28/Balance_Sheet!E18 -> 0.33791934 | F34: =Balance_Sheet!F28/Balance_Sheet!F18 -> 0.36346998 | G34: =Balance_Sheet!G28/Balance_Sheet!G18 -> 0.29771881 | H34: =Balance_Sheet!H28/Balance_Sheet!H18 -> 0.24776176 | I34: =Balance_Sheet!I28/Balance_Sheet!I18 -> 0.20939753 | ... K34: =Balance_Sheet!K28/Balance_Sheet!K18 -> 0.15562956
A35: Deferred Taxes | B35: =Balance_Sheet!B29/Balance_Sheet!B18 -> 0.0025607432 | C35: =Balance_Sheet!C29/Balance_Sheet!C18 -> 0.010486076 | D35: =Balance_Sheet!D29/Balance_Sheet!D18 -> 0.010148745 | E35: =Balance_Sheet!E29/Balance_Sheet!E18 -> 0.0086929891 | F35: =Balance_Sheet!F29/Balance_Sheet!F18 -> 0.0065930409 | G35: =Balance_Sheet!G29/Balance_Sheet!G18 -> 0.0054003698 | H35: =Balance_Sheet!H29/Balance_Sheet!H18 -> 0.0044941908 | I35: =Balance_Sheet!I29/Balance_Sheet!I18 -> 0.0037982959 | ... K35: =Balance_Sheet!K29/Balance_Sheet!K18 -> 0.0028229899
A36: Total Liabilities | B36: =Balance_Sheet!B31/Balance_Sheet!B18 -> 0.80594926 | C36: =Balance_Sheet!C31/Balance_Sheet!C18 -> 0.80323343 | D36: =Balance_Sheet!D31/Balance_Sheet!D18 -> 0.83532176 | E36: =Balance_Sheet!E31/Balance_Sheet!E18 -> 0.83516302 | F36: =Balance_Sheet!F31/Balance_Sheet!F18 -> 0.86449949 | G36: =Balance_Sheet!G31/Balance_Sheet!G18 -> 0.7459048 | H36: =Balance_Sheet!H31/Balance_Sheet!H18 -> 0.65255244 | I36: =Balance_Sheet!I31/Balance_Sheet!I18 -> 0.57812475 | ... K36: =Balance_Sheet!K31/Balance_Sheet!K18 -> 0.46695484
A37: Total Equity | B37: =Balance_Sheet!B41/Balance_Sheet!B18 -> 0.19318723 | C37: =Balance_Sheet!C41/Balance_Sheet!C18 -> 0.19599671 | D37: =Balance_Sheet!D41/Balance_Sheet!D18 -> 0.16413594 | E37: =Balance_Sheet!E41/Balance_Sheet!E18 -> 0.1643187 | F37: =Balance_Sheet!F41/Balance_Sheet!F18 -> 0.13550051 | G37: =Balance_Sheet!G41/Balance_Sheet!G18 -> 0.2540952 | H37: =Balance_Sheet!H41/Balance_Sheet!H18 -> 0.34744756 | I37: =Balance_Sheet!I41/Balance_Sheet!I18 -> 0.42187525 | ... K37: =Balance_Sheet!K41/Balance_Sheet!K18 -> 0.53304516
A39: Asset Turnover Ratio | B39: 2020 | C39: 2021 | D39: 2022 | E39: 2023 | F39: 2024 | G39: 2025E | H39: 2026E | I39: 2027E | J39: 2028E | K39: 2029E
A40: Sales / Total Assets | B40: ='Profit Loss'!B4/Balance_Sheet!B18 -> 0.45560386 | C40: ='Profit Loss'!C4/Balance_Sheet!C18 -> 0.50131408 | D40: ='Profit Loss'!D4/Balance_Sheet!D18 -> 0.57424336 | E40: ='Profit Loss'!E4/Balance_Sheet!E18 -> 0.59126461 | F40: ='Profit Loss'!F4/Balance_Sheet!F18 -> 0.58582392 | G40: ='Profit Loss'!G4/Balance_Sheet!G18 -> 0.53263268 | H40: ='Profit Loss'!H4/Balance_Sheet!H18 -> 0.48758294 | I40: ='Profit Loss'!I4/Balance_Sheet!I18 -> 0.44917159 | ... K40: ='Profit Loss'!K4/Balance_Sheet!K18 -> 0.38578057
A42: Debt Scheduling | B42: 2020 | C42: 2021 | D42: 2022 | E42: 2023 | F42: 2024 | G42: 2025E | H42: 2026E | I42: 2027E | J42: 2028E | K42: 2029E
A43: Total Debt | B43: =Balance_Sheet!B28+Balance_Sheet!B25 -> 12672 | C43: =Balance_Sheet!C28+Balance_Sheet!C25 -> 13901 | D43: =Balance_Sheet!D28+Balance_Sheet!D25 -> 14023 | E43: =Balance_Sheet!E28+Balance_Sheet!E25 -> 15681 | F43: =Balance_Sheet!F28+Balance_Sheet!F25 -> 18226 | G43: =Balance_Sheet!G28+Balance_Sheet!G25 -> 18226 | H43: =Balance_Sheet!H28+Balance_Sheet!H25 -> 18226 | I43: =Balance_Sheet!I28+Balance_Sheet!I25 -> 18226 | ... K43: =Balance_Sheet!K28+Balance_Sheet!K25 -> 18226
A44: Secured Debt | B44: =B43*10% -> 1267.2 | C44: =C43*10% -> 1390.1 | D44: =D43*10% -> 1402.3 | E44: =E43*10% -> 1568.1 | F44: =F43*10% -> 1822.6 | G44: =G43*10% -> 1822.6 | H44: =H43*10% -> 1822.6 | I44: =I43*10% -> 1822.6 | ... K44: =K43*10% -> 1822.6
A45: Unsecured Debt | B45: =B43-B44 -> 11404.8 | C45: =C43-C44 -> 12510.9 | D45: =D43-D44 -> 12620.7 | E45: =E43-E44 -> 14112.9 | F45: =F43-F44 -> 16403.4 | G45: =G43-G44 -> 16403.4 | H45: =H43-H44 -> 16403.4 | I45: =I43-I44 -> 16403.4 | ... K45: =K43-K44 -> 16403.4
A47: Depreciation, Interest, and Tax Schedule | B47: 2020 | C47: 2021 | D47: 2022 | E47: 2023 | F47: 2024 | G47: 2025E | H47: 2026E | I47: 2027E | J47: 2028E | K47: 2029E
A48: Depreciation % of Revenue | B48: ='Profit Loss'!B8/'Profit Loss'!B4 -> 0.037906019 | C48: ='Profit Loss'!C8/'Profit Loss'!C4 -> 0.038445245 | D48: ='Profit Loss'!D8/'Profit Loss'!D4 -> 0.033727571 | E48: ='Profit Loss'!E8/'Profit Loss'!E4 -> 0.031835206 | F48: ='Profit Loss'!F8/'Profit Loss'!F4 -> 0.031845777 | G48: ='Profit Loss'!G8/'Profit Loss'!G4 -> 0.03098508 | H48: ='Profit Loss'!H8/'Profit Loss'!H4 -> 0.030421715 | I48: ='Profit Loss'!I8/'Profit Loss'!I4 -> 0.030142617 | ... K48: ='Profit Loss'!K8/'Profit Loss'!K4 -> 0.030424324
A49: Interest % of Debt | B49: ='Profit Loss'!B15/'Common Size'!B43 -> -0.029987374 | C49: ='Profit Loss'!C15/'Common Size'!C43 -> -0.031004964 | D49: ='Profit Loss'!D15/'Common Size'!D43 -> -0.033587677 | E49: ='Profit Loss'!E15/'Common Size'!E43 -> -0.03666858 | F49: ='Profit Loss'!F15/'Common Size'!F43 -> -0.035443871 | G49: ='Profit Loss'!G15/'Common Size'!G43 -> -0.045 | H49: ='Profit Loss'!H15/'Common Size'!H43 -> -0.045 | I49: ='Profit Loss'!I15/'Common Size'!I43 -> -0.045 | ... K49: ='Profit Loss'!K15/'Common Size'!K43 -> -0.045
A50: Tax Rate | B50: ='Profit Loss'!B19/'Profit Loss'!B18 -> 0.17384021 | C50: ='Profit Loss'!C19/'Profit Loss'!C18 -> 0.15717474 | D50: ='Profit Loss'!D19/'Profit Loss'!D18 -> 0.153597 | E50: ='Profit Loss'!E19/'Profit Loss'!E18 -> 0.17919202 | F50: ='Profit Loss'!F19/'Profit Loss'!F18 -> 0.15602465 | G50: ='Profit Loss'!G19/'Profit Loss'!G18 -> 0.16 | H50: ='Profit Loss'!H19/'Profit Loss'!H18 -> 0.16 | I50: ='Profit Loss'!I19/'Profit Loss'!I18 -> 0.16 | ... K50: ='Profit Loss'!K19/'Profit Loss'!K18 -> 0.16
A52: Dividend Schedule | B52: 2020 | C52: 2021 | D52: 2022 | E52: 2023 | F52: 2024 | G52: 2025E | H52: 2026E | I52: 2027E | J52: 2028E | K52: 2029E
A53: Net Income | B53: ='Profit Loss'!B20 -> 6411 | C53: ='Profit Loss'!C20 -> 8687 | D53: ='Profit Loss'!D20 -> 9930 | E53: ='Profit Loss'!E20 -> 11195 | F53: ='Profit Loss'!F20 -> 12874 | G53: ='Profit Loss'!G20 -> 14041.325 | H53: ='Profit Loss'!H20 -> 15786.104 | I53: ='Profit Loss'!I20 -> 17411.45 | ... K53: ='Profit Loss'!K20 -> 20568.896
A54: Dividend Payout % | B54: =Assumptions!F8 -> 0.3 | C54: =Assumptions!F8 -> 0.3 | D54: =Assumptions!F8 -> 0.3 | E54: =Assumptions!F8 -> 0.3 | F54: =Assumptions!F8 -> 0.3 | G54: =Assumptions!F8 -> 0.3 | H54: =Assumptions!F8 -> 0.3 | I54: =Assumptions!F8 -> 0.3 | J54: =Assumptions!F8 -> 0.3 | K54: =Assumptions!F8 -> 0.3
A55: Dividends Paid | B55: =B53*B54 -> 1923.3 | C55: =C53*C54 -> 2606.1 | D55: =D53*D54 -> 2979 | E55: =E53*E54 -> 3358.5 | F55: =F53*F54 -> 3862.2 | G55: =G53*G54 -> 4212.3976 | H55: =H53*H54 -> 4735.8312 | I55: =I53*I54 -> 5223.4349 | ... K55: =K53*K54 -> 6170.6688
A56: Retained Earnings Added | B56: =B53-B55 -> 4487.7 | C56: =C53-C55 -> 6080.9 | D56: =D53-D55 -> 6951 | E56: =E53-E55 -> 7836.5 | F56: =F53-F55 -> 9011.8 | G56: =G53-G55 -> 9828.9277 | H56: =H53-H55 -> 11050.273 | I56: =I53-I55 -> 12188.015 | ... K56: =K53-K55 -> 14398.227
A58: Calculate Ke | B58: Value
A59: Risk-free rate (Rf) | B59: 0.045
A60: Beta | B60: {=Table23[Value]} -> 1.0378473
A61: Market Risk Premium (Rm−Rf) | B61: 0.055
A62: Cost of Equity (Ke) | B62: =B59+B60*B61 -> 0.1020816
A64: WACC Calculation | B64: Value
A65: Weight of Equity (E/V) | B65: 0.8
A66: Cost of Equity (Ke) | B66: =B62 -> 0.1020816
A67: Weight of Debt (D/V) | B67: 0.2
A68: Cost of Debt (Kd) | B68: 0.04
A69: Tax Rate | B69: =Assumptions!B21 -> 0.16
A70: WACC | B70: =(B65*B66)+(B67*B68*(1-B69)) -> 0.088385281
A72: FCFF / FCFE Calculation | B72: 2020 | C72: 2021 | D72: 2022 | E72: 2023 | F72: 2024 | G72: 2025E | H72: 2026E | I72: 2027E | J72: 2028E | K72: 2029E
A73: EBIT | B73: ='Profit Loss'!B25 -> 8661 | C73: ='Profit Loss'!C25 -> 10808 | D73: ='Profit Loss'!D25 -> 13014 | E73: ='Profit Loss'!E25 -> 14807 | F73: ='Profit Loss'!F11 -> 15582 | G73: ='Profit Loss'!G11 -> 17195.954 | H73: ='Profit Loss'!H11 -> 19259.468 | I73: ='Profit Loss'!I11 -> 21180.256 | J73: ='Profit Loss'!J11 -> 23077.107 | K73: ='Profit Loss'!K11 -> 24909.106
A74: Tax Rate | B74: ='Profit Loss'!B19/'Profit Loss'!B18 -> 0.17384021 | C74: ='Profit Loss'!C19/'Profit Loss'!C18 -> 0.15717474 | D74: ='Profit Loss'!D19/'Profit Loss'!D18 -> 0.153597 | E74: ='Profit Loss'!E19/'Profit Loss'!E18 -> 0.17919202 | F74: ='Profit Loss'!F19/'Profit Loss'!F18 -> 0.15602465 | G74: ='Profit Loss'!G19/'Profit Loss'!G18 -> 0.16 | H74: ='Profit Loss'!H19/'Profit Loss'!H18 -> 0.16 | I74: ='Profit Loss'!I19/'Profit Loss'!I18 -> 0.16 | ... K74: ='Profit Loss'!K19/'Profit Loss'!K18 -> 0.16
A75: EBIT(1−Tax) | B75: =B73*(1-B74) -> 7155.37 | C75: =C73*(1-C74) -> 9109.2555 | D75: =D73*(1-D74) -> 11015.089 | E75: =E73*(1-E74) -> 12153.704 | F75: =F73*(1-F74) -> 13150.824 | G75: =G73*(1-G74) -> 14444.601 | H75: =H73*(1-H74) -> 16177.953 | I75: =I73*(1-I74) -> 17791.415 | ... K75: =K73*(1-K74) -> 20923.649
A76: Depreciation | B76: ='Profit Loss'!B8 -> 580 | C76: ='Profit Loss'!C8 -> 726 | D76: ='Profit Loss'!D8 -> 750 | E76: ='Profit Loss'!E8 -> 799 | F76: ='Profit Loss'!F8 -> 897 | G76: ='Profit Loss'!G8 -> 968.76 | H76: ='Profit Loss'!H8 -> 1046.2608 | I76: ='Profit Loss'!I8 -> 1129.9617 | ... K76: ='Profit Loss'!K8 -> 1317.9873
A77: Capital Expenditure | B77: ='Cash Flow'!B31+'Cash Flow'!B32 -> -708 | C77: ='Cash Flow'!C31+'Cash Flow'!C32 -> -814 | D77: ='Cash Flow'!D31+'Cash Flow'!D32 -> -1097 | E77: ='Cash Flow'!E31+'Cash Flow'!E32 -> -1088 | F77: ='Cash Flow'!F31+'Cash Flow'!F32 -> -1194 | G77: ='Cash Flow'!G31+'Cash Flow'!G32 -> -1253.7 | H77: ='Cash Flow'!H31+'Cash Flow'!H32 -> -1316.385 | I77: ='Cash Flow'!I31+'Cash Flow'!I32 -> -1382.2043 | ... K77: ='Cash Flow'!K31+'Cash Flow'!K32 -> -1523.8802
A78: Discount Factor | G78: 0.92 | H78: 0.85 | I78: 0.78 | J78: 0.72 | K78: 0.66
A79: Present Value of FCFF | G79: =G78*G86 -> 22527.684 | H79: =H78*H86 -> 23177.354 | I79: =I78*I86 -> 23338.526 | J79: =J78*J86 -> 23419.001 | K79: =K78*K86 -> 23117.432
A80: Terminal Value (after 2029) | G80: =K86*1.03/(0.0883-0.03) -> 618819.98
A81: PV of Terminal Value | G81: =G80*K78 -> 408421.19
A82: Enterprise Value (DCF) | G82: =SUM(G79:K79)+G81 -> 524001.18
A83: Equity Value | G83: =G82-B92+B93+B94 -> 516091.18
A84: Intrinsic Share Price | G84: =G83/'Profit Loss'!G24 -> 568.09456
A85: Change in Working Capital | B85: =Balance_Sheet!B7+Balance_Sheet!B8+Balance_Sheet!B10-Balance_Sheet!B20-Balance_Sheet!B24-Balance_Sheet!B26-Balance_Sheet!B21 -> -2425 | C85: =Balance_Sheet!C7+Balance_Sheet!C8+Balance_Sheet!C10-Balance_Sheet!C20-Balance_Sheet!C24-Balance_Sheet!C26-Balance_Sheet!C21 -> -3061 | D85: =Balance_Sheet!D7+Balance_Sheet!D8+Balance_Sheet!D10-Balance_Sheet!D20-Balance_Sheet!D24-Balance_Sheet!D26-Balance_Sheet!D21 -> -4194 | E85: =Balance_Sheet!E7+Balance_Sheet!E8+Balance_Sheet!E10-Balance_Sheet!E20-Balance_Sheet!E24-Balance_Sheet!E26-Balance_Sheet!E21 -> -5096 | F85: =Balance_Sheet!F7+Balance_Sheet!F8+Balance_Sheet!F10-Balance_Sheet!F20-Balance_Sheet!F24-Balance_Sheet!F26-Balance_Sheet!F21 -> -8571 | G85: =Balance_Sheet!G7+Balance_Sheet!G8+Balance_Sheet!G10-Balance_Sheet!G20-Balance_Sheet!G24-Balance_Sheet!G26-Balance_Sheet!G21 -> -10326.952 | H85: =Balance_Sheet!H7+Balance_Sheet!H8+Balance_Sheet!H10-Balance_Sheet!H20-Balance_Sheet!H24-Balance_Sheet!H26-Balance_Sheet!H21 -> -11359.647 | I85: =Balance_Sheet!I7+Balance_Sheet!I8+Balance_Sheet!I10-Balance_Sheet!I20-Balance_Sheet!I24-Balance_Sheet!I26-Balance_Sheet!I21 -> -12382.015 | ... K85: =Balance_Sheet!K7+Balance_Sheet!K8+Balance_Sheet!K10-Balance_Sheet!K20-Balance_Sheet!K24-Balance_Sheet!K26-Balance_Sheet!K21 -> -14308.657
A86: FCFF | B86: =B75+B76+B77-B85 -> 9452.37 | C86: =C75+C76+C77-C85 -> 12082.255 | D86: =D75+D76+D77-D85 -> 14862.089 | E86: =E75+E76+E77-E85 -> 16960.704 | F86: =F75+F76+F77-F85 -> 21424.824 | G86: =G75+G76+G77-G85 -> 24486.613 | H86: =H75+H76+H77-H85 -> 27267.476 | I86: =I75+I76+I77-I85 -> 29921.187 | ... K86: =K75+K76+K77-K85 -> 35026.412
A87: Net Borrowings | B87: =C43-B43 -> 1229 | C87: =B43-C43 -> -1229 | D87: =C43-D43 -> -122 | E87: =D43-E43 -> -1658 | F87: =E43-F43 -> -2545 | G87: =F43-G43 -> 0 | H87: =G43-H43 -> 0 | I87: =H43-I43 -> 0 | J87: =I43-J43 -> 0 | K87: =J43-K43 -> 0
A88: FCFE | B88: =B15+B76-B77-B85+B87 -> 4942.419 | C88: =C15+C76-C77-C85+C87 -> 3372.46 | D88: =D15+D76-D77-D85+D87 -> 5919.4466 | E88: =E15+E76-E77-E85+E87 -> 5325.4461 | F88: =F15+F76-F77-F85+F87 -> 8117.4571 | G88: =G15+G76-G77-G85+G87 -> 12549.861 | H88: =H15+H76-H77-H85+H87 -> 13722.752 | I88: =I15+I76-I77-I85+I87 -> 14894.645 | ... K88: =K15+K76-K77-K85+K87 -> 17150.999
A90: Enterprise Value Calculation | B90: Company | F90: Input | G90: Assumptions
A91: Market Capitalization | B91: =450*'Profit Loss'!F24 -> 417150 | F91: Start Growth | G91: 0.24
A92: Total Debt | B92: =Balance_Sheet!F28+Balance_Sheet!F25 -> 18226 | F92: Terminal Growth | G92: 0.025
A93: Cash & Cash Equivalents | B93: =Balance_Sheet!F4 -> 8442 | F93: Forecast Years | G93: 5
A94: Investments (if any) | B94: =Balance_Sheet!F6 -> 1874
A95: Enterprise Value | B95: =B91+B92-B93-B94 -> 425060 | F95: Terminal Growth Rate Used | G95: 3-4%
F96: WACC Used | G96: 0.088
A97: Valuation Ratios | B97: Formula | C97: Company | F97: TV % of EV | G97: 0.68
A98: P/E | B98: Market Cap / Net Income | C98: =B91/'Profit Loss'!F20 -> 32.402517
A99: P/B | B99: Market Cap / Equity | C99: =B91/Balance_Sheet!F41 -> 64.029163
A100: EV/EBITDA | B100: EV / EBITDA | C100: =B95/'Profit Loss'!F25 -> 25.794041
A101: EV/EBIT | B101: EV / EBIT | C101: =B95/'Profit Loss'!F11 -> 27.278912
A102: P/S | B102: Market Cap / Revenue | C102: =B91/'Profit Loss'!F4 -> 14.809884

Sheet Ind_P&L
A1: Income Statement- USD ($) shares in Millions, $ in Millions | B1: 2020 | C1: 2021 | D1: 2022 | E1: 2023 | F1: 2024
A2: Mastercard Inc
A3: Net Revenue / Total Revenue | B3: 132310 | C3: 162672 | D3: 183399 | E3: 196337 | F3: 222366
A4: Operating Expenses
A5: General & Administrative | B5: 15843 | C5: 18675 | D5: 19642 | E5: 21409 | F5: 23108
A6: Advertising & Marketing | B6: 7324 | C6: 8067 | D6: 7560 | E6: 7213 | F6: 7416
A7: Depreciation & Amortization | B7: 3277 | C7: 3607 | D7: 3646 | E7: 3806 | F7: 4109
A8: Provision for Litigation | B8: 84 | C8: 97 | D8: 1224 | E8: 1466 | F8: 1142
A9: Total Operating Expenses | B9: 89910 | C9: 103424 | D9: 111197 | E9: 117306 | F9: 130026
A10: Operating Income | B10: 42400 | C10: 59248 | D10: 72202 | E10: 79031 | F10: 92340
A11: Other Income (Expense)
A12: Investment Income | B12: 1234 | C12: 1017 | D12: 1207 | E12: 1692 | F12: 1925
A13: Equity Investment Gains/Losses | B13: 30 | C13: 645 | D13: -145 | E13: -61 | F13: -29
A14: Interest Expense | B14: -3630 | C14: -4105 | D14: -4267 | E14: -4742 | F14: -5043
A15: Other Income (Expense) | B15: 1506 | C15: 1146 | D15: -680 | E15: 104 | F15: 115
A16: Total Other Income (Expense) | B16: -860 | C16: -1297 | D16: -3885 | E16: -3007 | F16: -3032
A17: Income Before Taxes | B17: 41540 | C17: 57951 | D17: 68317 | E17: 76024 | F17: 89308
A18: Income Tax Expense | B18: 8269 | C18: 9730 | D18: 10165 | E18: 12721 | F18: 13176
A19: Net Income (Industry Total) | B19: 33271 | C19: 48221 | D19: 58152 | E19: 63303 | F19: 76132
A20: Basic EPS | B20: 4.2 | C20: 6.1 | D20: 7.3 | E20: 8.4 | F20: 9.9
A21: Diluted EPS | B21: 4.1 | C21: 6 | D21: 7.2 | E21: 8.3 | F21: 9.8
A22: EBITDA | B22: 45677 | C22: 62855 | D22: 75848 | E22: 82837 | F22: 96449
A23: Operating Maargin | B23: 0.32045953 | C23: 0.36421757 | D23: 0.39368808 | E23: 0.40252729 | F23: 0.41526133
... A25: Total | B25: 372516.3 | C25: 469110.1 | D25: 527748.5 | E25: 572618.7 | F25: 653078.7
A27: Calculated from Ind dump

Sheet Ind_bala
A1: Consolidated Balance Sheet - USD ($) $ in Millions | B1: 2020 | C1: 2021 | D1: 2022 | E1: 2023 | F1: 2024
A2: Mastercard Inc
A3: Assets
A4: Cash & Cash Equivalents | B4: 69864 | C4: 93017 | D4: 120397 | E4: 146313 | F4: 178016
A5: Restricted Cash | B5: 1487 | C5: 1480 | D5: 1483 | E5: 2375 | F5: 3256
A6: Investments | B6: 30499 | C6: 15353 | D6: 9476 | E6: 12801 | F6: 12833
A7: Accounts Receivable | B7: 8517 | C7: 9183 | D7: 9406 | E7: 7601 | F7: 7332
A8: Settlement / Customer Assets | B8: 45674 | C8: 48722 | D8: 45699 | E8: 51703 | F8: 54027
A9: Other Current Assets | B9: 11097 | C9: 12568 | D9: 12531 | E9: 13598 | F9: 15380
A10: Total Current Assets | B10: 167138 | C10: 154977 | D10: 149044 | E10: 175147 | F10: 175384
A11: Property & Equipment | B11: 18372 | C11: 18887 | D11: 20341 | E11: 21466 | F11: 22932
A12: Goodwill | B12: 89194 | C12: 101138 | D12: 94806 | E12: 99589 | F12: 109730
A13: Intangible Assets | B13: 40152 | C13: 41202 | D13: 42594 | E13: 45836 | F13: 50247
A14: Deferred Tax Assets | B14: 5573 | C14: 8254 | D14: 8550 | E14: 9517 | F14: 10646
A15: Other Assets | B15: 47560 | C15: 49710 | D15: 49789 | E15: 52930 | F15: 58596
A16: Total Assets | B16: 367989 | C16: 374168 | D16: 365124 | E16: 404485 | F16: 427535
A17: Liabilities
A18: Accounts Payable | B18: 24457 | C18: 28237 | D18: 30889 | E18: 32461 | F18: 34368
A19: Settlement Obligations | B19: 9780 | C19: 10851 | D19: 11663 | E19: 14604 | F19: 17343
A20: Accrued Expenses | B20: 17857 | C20: 19453 | D20: 21293 | E20: 23238 | F20: 26944
A21: Short-Term Debt | B21: 5526 | C21: 7337 | D21: 6502 | E21: 8406 | F21: 7974
A22: Other Current Liabilities | B22: 16809 | C22: 18441 | D22: 18859 | E22: 20094 | F22: 22983
A23: Total Current Liabilities | B23: 74429 | C23: 84319 | D23: 89206 | E23: 98803 | F23: 109612
A24: Long-Term Debt | B24: 84015 | C24: 92201 | D24: 99228 | E24: 102307 | F24: 117801
A25: Deferred Taxes | B25: 5323 | C25: 7362 | D25: 7587 | E25: 7762 | F25: 7865
A26: Other Liabilities | B26: 49483 | C26: 51273 | D26: 51889 | E26: 54110 | F26: 55921
A27: Total Liabilities | B27: 213250 | C27: 235155 | D27: 247910 | E27: 262982 | F27: 291199
A28: Equity
A29: Paid-in Capital | B29: 91991 | C29: 95023 | D29: 98956 | E29: 103464 | F29: 110989
A30: Treasury Stock | B30: -45165 | C30: -54468 | D30: -67433 | E30: -81474 | F30: -98516
A31: Retained Earnings | B31: 96250 | C31: 121517 | D31: 135685 | E31: 158785 | F31: 182547
A32: AOCI | B32: -6085 | C32: -7632 | D32: -8289 | E32: -7878 | F32: -9463
A33: Non-controlling Interest | B33: 1748 | C33: 1573 | D33: 1295 | E33: 2606 | F33: 779
A34: Total Equity | B34: 138739 | C34: 156013 | D34: 160214 | E34: 175503 | F34: 186336
A35: Total | B35: 1681523 | C35: 1795314 | D35: 1834694 | E35: 2019134 | F35: 2190596
A37: Calculated from Ind dump

Sheet Ind_Cashflow
A1: Cash Flow Statement - USD ($) $ in Millions | B1: 2020 | C1: 2021 | D1: 2022 | E1: 2023 | F1: 2024
A2: Mastercard Inc
A3: Operating Cash Flow
A4: Net Income | B4: 33271 | C4: 48221 | D4: 58152 | E4: 63303 | F4: 76132
A5: Depreciation & Amortization | B5: 7894 | C5: 8720 | D5: 9122 | E5: 9648 | F5: 10436
A6: Share-based Compensation | B6: 3104 | C6: 3486 | D6: 3722 | E6: 3991 | F6: 4215
A7: Deferred Income Taxes | B7: 1207 | C7: 1496 | D7: 1389 | E7: 1742 | F7: 1963
A8: Equity Investment Gains/Losses | B8: -30 | C8: -645 | D8: 145 | E8: 61 | F8: 29
A9: Other Non-cash Adjustments | B9: 5902 | C9: 6611 | D9: 7084 | E9: 7393 | F9: 8104
A10: Working Capital Changes | B10: -6983 | C10: -4728 | D10: -3915 | E10: -2506 | F10: -3221
A11: Net Cash from Operating Activities | B11: 44365 | C11: 63161 | D11: 75699 | E11: 83632 | F11: 97658
A12: Investing Cash Flow
A13: Purchases of Investments | B13: -29418 | C13: -22095 | D13: -18760 | E13: -19487 | F13: -21331
A14: Proceeds from Investments | B14: 18227 | C14: 19541 | D14: 16330 | E14: 17606 | F14: 18104
A15: Capital Expenditures | B15: -4986 | C15: -5392 | D15: -5874 | E15: -6331 | F15: -7145
A16: Acquisitions | B16: -7458 | C16: -6723 | D16: -4615 | E16: -3971 | F16: -5004
A17: Equity Investments | B17: -1842 | C17: -1004 | D17: -906 | E17: -1117 | F17: -1242
A18: Other Investing Activities | B18: 812 | C18: 901 | D18: 774 | E18: 633 | F18: 689
A19: Net Cash From Investing Activities | B19: -24665 | C19: -14772 | D19: -13051 | E19: -12667 | F19: -15929
A20: Financing Cash Flow
A21: Share Repurchases | B21: -20984 | C21: -29107 | D21: -36414 | E21: -42155 | F21: -48207
A22: Dividends Paid | B22: -7220 | C22: -8114 | D22: -9136 | E22: -10071 | F22: -11298
A23: Net Debt Issued (Repaid) | B23: 10841 | C23: 11652 | D23: 9981 | E23: 6884 | F23: 9113
A24: Stock Option Proceeds | B24: 1362 | C24: 1541 | D24: 1623 | E24: 1704 | F24: 1896
A25: Other Financing Activities | B25: -1115 | C25: -1208 | D25: -1322 | E25: -1411 | F25: -1530
A26: Net Cash from Financing Activities | B26: -17116 | C26: -25236 | D26: -35268 | E26: -45049 | F26: -50026
A27: Cash Movement
A28: Net Change in Cash | B28: 2584 | C28: 23153 | D28: 27380 | E28: 25916 | F28: 31703
A29: Beginning Cash Balance | B29: 67280 | C29: 69864 | D29: 93017 | E29: 120397 | F29: 146313
A30: Ending Cash Balance | B30: 69864 | C30: 93017 | D30: 120397 | E30: 146313 | F30: 178016
A31: Total | B31: 144896 | C31: 232340 | D31: 295554 | E31: 344458 | F31: 419438
A33: Calculated from Ind dump

Sheet Ind dump
A1: Mastercard Consolidated Statement of Operations - USD ($) shares in Millions, $ in Millions | B1: 12 Months Ended | C1: 12 Months Ended 2 | D1: 12 Months Ended 3 | E1: 12 Months Ended 4 | F1: 12 Months Ended | I1: Mastercard Consolidated Balance Sheet - USD ($) $ in Millions | J1: Dec. 31, 2020 | K1: Dec. 31, 2021 | L1: Dec. 31, 2022 | M1: Dec. 31, 2023 | N1: Dec. 31, 2024
B2: Dec. 31, 2020 | C2: Dec. 31, 2021 | D2: Dec. 31, 2022 | E2: Dec. 31, 2023 | F2: Dec. 31, 2024
A3: Income Statement [Abstract] | I3: Assets
A4: Net revenue | B4: 15301 | C4: 18884 | D4: 22237 | E4: 25098 | F4: 28167 | I4: Cash and cash equivalents | J4: 10113 | K4: 7421 | L4: 7008 | M4: 8588 | N4: 8442
A5: Operating Expenses | I5: Restricted cash for litigation settlement | J5: 586 | K5: 586 | L5: 589 | M5: 32 | N5: 492
A6: General and administrative | B6: 5910 | C6: 7087 | D6: 8078 | E6: 8927 | F6: 10193 | I6: Investments | J6: 483 | K6: 473 | L6: 400 | M6: 1845 | N6: 1874
A7: Advertising and marketing | B7: 657 | C7: 895 | D7: 789 | E7: 825 | F7: 815 | I7: Accounts receivable | J7: 2646 | K7: 3006 | L7: 3425 | M7: 592 | N7: 330
A8: Depreciation and amortization | B8: 580 | C8: 726 | D8: 750 | E8: 799 | F8: 897 | I8: Settlement assets | J8: 1706 | K8: 1319 | L8: 1270 | M8: 4060 | N8: 3773
A9: Provision for litigation | B9: 73 | C9: 94 | D9: 356 | E9: 539 | F9: 680 | I9: Restricted security deposits held for customers | J9: 1696 | K9: 1873 | L9: 1568 | M9: 1233 | N9: 1821
A10: Total operating expenses | B10: 7220 | C10: 8802 | D10: 9973 | E10: 11090 | F10: 12585 | I10: Prepaid expenses and other current assets | J10: 1883 | K10: 2271 | L10: 2346 | M10: 2611 | N10: 2992
A11: Operating income | B11: 8081 | C11: 10082 | D11: 12264 | E11: 14008 | F11: 15582 | I11: Total current assets | J11: 19113 | K11: 16949 | L11: 16606 | M11: 18961 | N11: 19724
A12: Other Income (Expense) | I12: Property, equipment and right-of-use assets, net | J12: 1902 | K12: 1907 | L12: 2006 | M12: 2061 | N12: 2138
A13: Investment income | B13: 24 | C13: 11 | D13: 61 | E13: 274 | F13: 327 | I13: Deferred income taxes | J13: 491 | K13: 486 | L13: 1151 | M13: 1355 | N13: 1614
A14: Gains (losses) on equity investments, net | B14: 30 | C14: 645 | D14: -145 | E14: -61 | F14: -29 | I14: Goodwill | J14: 4960 | K14: 7662 | L14: 7522 | M14: 7660 | N14: 9193
A15: Interest expense | B15: -380 | C15: -431 | D15: -471 | E15: -575 | F15: -646 | I15: Other intangible assets, net | J15: 1753 | K15: 3671 | L15: 3859 | M15: 4086 | N15: 5453
A16: Other income (expense), net | B16: 5 | C16: 0 | D16: 23 | E16: -7 | F16: 20 | I16: Other assets | J16: 5365 | K16: 6994 | L16: 7580 | M16: 8325 | N16: 9959
A17: Total other income (expense) | B17: -321 | C17: 225 | D17: -532 | E17: -369 | F17: -328 | I17: Total Assets | J17: 33584 | K17: 37669 | L17: 38724 | M17: 42448 | N17: 48081
A18: Income before income taxes | B18: 7760 | C18: 10307 | D18: 11732 | E18: 13639 | F18: 15254 | I18: Liabilities, Redeemable Non-controlling Interests and Equity
A19: Income tax expense | B19: 1349 | C19: 1620 | D19: 1802 | E19: 2444 | F19: 2380 | I19: Accounts payable | J19: 527 | K19: 738 | L19: 926 | M19: 834 | N19: 929
A20: Net Income | B20: 6411 | C20: 8687 | D20: 9930 | E20: 11195 | F20: 12874 | I20: Settlement obligations | J20: 1475 | K20: 913 | L20: 1111 | M20: 1399 | N20: 2316
A21: Basic Earnings per Share | B21: 6.4 | C21: 8.79 | D21: 10.26 | E21: 11.86 | F21: 13.91 | I21: Restricted security deposits held for customers | J21: 1696 | K21: 1873 | L21: 1568 | M21: 1845 | N21: 1874
A22: Basic weighted-average shares outstanding | B22: 1002 | C22: 988 | D22: 968 | E22: 944 | F22: 925 | I22: Accrued litigation | J22: 842 | K22: 840 | L22: 1094 | M22: 723 | N22: 930
A23: Diluted Earnings per Share | B23: 6.37 | C23: 8.76 | D23: 10.22 | E23: 11.83 | F23: 13.89 | I23: Accrued expenses | J23: 5430 | K23: 6642 | L23: 7801 | M23: 8517 | N23: 10393
A24: Diluted weighted-average shares outstanding | B24: 1006 | C24: 992 | D24: 971 | E24: 946 | F24: 927 | I24: Current portion of long-term debt | J24: 649 | K24: 792 | L24: 274 | M24: 1337 | N24: 750
I25: Other current liabilities | J25: 1228 | K25: 1364 | L25: 1397 | M25: 1609 | N25: 2028
I26: Total current liabilities | J26: 11847 | K26: 13162 | L26: 14171 | M26: 16264 | N26: 19220
A27: Sources:SEC EDGAR Data Bases | I27: Long-term debt | J27: 12023 | K27: 13109 | L27: 13749 | M27: 14344 | N27: 17476
I28: Deferred income taxes | J28: 86 | K28: 395 | L28: 393 | M28: 369 | N28: 317
I29: Other liabilities | J29: 3111 | K29: 3591 | L29: 4034 | M29: 4474 | N29: 4553
I30: Total Liabilities | J30: 27067 | K30: 30257 | L30: 32347 | M30: 35451 | N30: 41566
I31: Commitments and Contingencies
I32: Redeemable non-controlling interests | J32: 29 | K32: 29 | L32: 21 | M32: 22 | N32: 0
I33: Stockholders’ Equity
I34: Additional paid-in-capital | J34: 4982 | K34: 5061 | L34: 5298 | M34: 5893 | N34: 6442
I35: Class A treasury stock, at cost, 425 and 409 shares, respectively | J35: -36658 | K35: -42588 | L35: -51354 | M35: -60429 | N35: -71431
I36: Retained earnings | J36: 38747 | K36: 45648 | L36: 53607 | M36: 62564 | N36: 72907
I37: Accumulated other comprehensive income (loss) | J37: -680 | K37: -809 | L37: -1253 | M37: -1099 | N37: -1433
I38: Mastercard Incorporated Stockholders' Equity | J38: 6391 | K38: 7312 | L38: 6298 | M38: 6929 | N38: 6485
I39: Non-controlling interests | J39: 97 | K39: 71 | L39: 58 | M39: 46 | N39: 30
I40: Total Equity | J40: 6488 | K40: 7383 | L40: 6356 | M40: 6975 | N40: 6515
I41: Total Liabilities, Redeemable Non-controlling Interests and Equity | J41: 33584 | K41: 37669 | L41: 38724 | M41: 42448 | N41: 48081
I42: Class A Common Stock
I43: Stockholders’ Equity
I44: Common stock value | J44: 0 | K44: 0 | L44: 0 | M44: 0 | N44: 0
I45: Class B Common Stock
I46: Stockholders’ Equity
I47: Common stock value | J47: 0 | K47: 0 | L47: 0 | M47: 0 | N47: 0
I48: Sources:SEC EDGAR Data Bases
A49: Visa inc | I49: Visa Inc | K49: 12 Months Ended
A50: CONSOLIDATED STATEMENTS OF OPERATIONS - USD ($) shares in Millions, $ in Millions | B50: 12 Months Ended | I50: Particulars | J50: 2024 | K50: 2023 | L50: 2022 | M50: 2021 | N50: 2020
B51: Sep. 30, 2024 | C51: Sep. 30, 2023 | D51: Sep. 30, 2022 | E51: Sep. 30, 2021 | F51: Sep. 30, 2020 | I51: Cash and cash equivalents | J51: 16286 | K51: 15689 | L51: 15689 | M51: 16487 | N51: 16289
A52: Net revenue | B52: 35926 | C52: 32653 | D52: 29310 | E52: 24105 | F52: 21846 | I52: Restricted cash equivalents—U.S. litigation escrow | J52: 1764 | K52: 1449 | L52: 1449 | M52: 894 | N52: 901
A53: Operating Expenses | I53: Investment securities | J53: -64 | K53: -106 | L53: -106 | M53: -1 | N53: 3
A54: Personnel | B54: 6264 | C54: 5831 | D54: 4990 | E54: 4240 | F54: 3785 | I54: Settlement receivable | J54: 2183 | K54: 1932 | L54: 1932 | M54: 1758 | N54: 1264
A55: Marketing | B55: 1560 | C55: 1341 | D55: 1336 | E55: 1136 | F55: 971 | I55: Accounts receivable | J55: 2291 | K55: 2020 | L55: 2020 | M55: 1968 | N55: 1618
A56: Network and processing | B56: 778 | C56: 736 | D56: 743 | E56: 730 | F56: 727 | I56: Customer collateral | J56: 3005 | K56: 2342 | L56: 2342 | M56: 2260 | N56: 1850
A57: Professional fees | B57: 635 | C57: 545 | D57: 505 | E57: 403 | F57: 408 | I57: Current portion of client incentives | J57: 1577 | K57: 1272 | L57: 1272 | M57: 1359 | N57: 1214
A58: Depreciation and amortization | B58: 1034 | C58: 943 | D58: 861 | E58: 804 | F58: 767 | I58: Prepaid expenses and other current assets | J58: 2584 | K58: 2668 | L58: 2668 | M58: 856 | N58: 757
A59: General and administrative | B59: 1598 | C59: 1330 | D59: 1194 | E59: 985 | F59: 1096 | I59: Total current assets | J59: 33532 | K59: 30205 | L59: 30205 | M59: 27607 | N59: 27645
A60: Litigation provision | B60: 462 | C60: 927 | D60: 868 | E60: 3 | F60: 11 | I60: Client incentives | J60: 8177 | K60: 6099 | L60: 6099 | M60: 5243 | N60: 4176
A61: Total operating expenses | B61: 12331 | C61: 11653 | D61: 10497 | E61: 8301 | F61: 7765 | I61: Property, equipment and technology, net | J61: 3425 | K61: 3223 | L61: 3223 | M61: 2715 | N61: 2737
A62: Operating income | B62: 23595 | C62: 21000 | D62: 18813 | E62: 15804 | F62: 14081 | I62: Goodwill | J62: 17997 | K62: 17787 | L62: 17787 | M62: 15958 | N62: 15910
A63: Non-operating Income (Expense) | I63: Intangible assets, net | J63: 26104 | K63: 25065 | L63: 25065 | M63: 27664 | N63: 27808
A64: Interest expense | B64: -641 | C64: -644 | D64: -538 | E64: -513 | F64: -516 | I64: Other assets | J64: 3731 | K64: 3737 | L64: 3737 | M64: 4002 | N64: 3413
A65: Investment income (expense) and other | B65: 962 | C65: 681 | D65: -139 | E65: 772 | F65: 225 | I65: Total assets | J65: 90499 | K65: 85501 | L65: 85501 | M65: 82896 | N65: 80919
A66: Total non-operating income (expense) | B66: 321 | C66: 37 | D66: -677 | E66: 259 | F66: -291 | I66: Liabilities
A67: Income before income taxes | B67: 23916 | C67: 21037 | D67: 18136 | E67: 16063 | F67: 13790 | I67: Accounts payable | J67: 375 | K67: 340 | L67: 340 | M67: 266 | N67: 174
A68: Income tax provision | B68: 4173 | C68: 3764 | D68: 3179 | E68: 3752 | F68: 2924 | I68: Settlement payable | J68: 3269 | K68: 3281 | L68: 3281 | M68: 2443 | N68: 1736
A69: Net income | B69: 19743 | C69: 17273 | D69: 14957 | E69: 12311 | F69: 10866 | I69: Accrued compensation and benefits | J69: 1506 | K69: 1359 | L69: 1359 | M69: 1211 | N69: 821
A70: Class A common stock | I70: Accrued liabilities | J70: 5015 | K70: 3726 | L70: 3726 | M70: 2334 | N70: 1840
A71: Earnings Per Share | I71: Current maturities of debt | J71: 0 | K71: 2250 | L71: 2250 | M71: 999 | N71: 2999
A72: Basic earnings per share (in dollars per share) | B72: 9.74 | C72: 8.29 | D72: 7.01 | E72: 5.63 | F72: 4.9 | I72: Accrued litigation | J72: 1751 | K72: 1456 | L72: 1456 | M72: 983 | N72: 914
A73: Basic weighted-average shares outstanding (in shares) | B73: 1621 | C73: 1618 | D73: 1651 | E73: 1691 | F73: 1697 | I73: Total current liabilities | J73: 23098 | K73: 20853 | L73: 20853 | M73: 15739 | N73: 14510
A74: Diluted earnings per share (in dollars per share) | B74: 9.73 | C74: 8.28 | D74: 7 | E74: 5.63 | F74: 4.89 | I74: Long-term debt | J74: 20463 | K74: 20200 | L74: 20200 | M74: 19978 | N74: 21071
A75: Diluted weighted-average shares outstanding (in shares) | B75: 2029 | C75: 2085 | D75: 2136 | E75: 2188 | F75: 2223 | I75: Deferred tax liabilities | J75: 5114 | K75: 5332 | L75: 5332 | M75: 6128 | N75: 5237
A76: Class B-1 common stock | I76: Other liabilities | J76: 3091 | K76: 3535 | L76: 3535 | M76: 3462 | N76: 3891
A77: Earnings Per Share | I77: Total liabilities | J77: 51766 | K77: 49920 | L77: 49920 | M77: 45307 | N77: 44709
A78: Basic earnings per share (in dollars per share) | B78: 15.46 | C78: 13.26 | D78: 11.33 | E78: 9.14 | F78: 7.94 | I78: Commitments and contingencies (Note 18 and Note 20)
A79: Basic weighted-average shares outstanding (in shares) | B79: 148 | C79: 245 | D79: 245 | E79: 245 | F79: 245 | I79: Equity
A80: Diluted earnings per share (in dollars per share) | B80: 15.45 | C80: 13.24 | D80: 11.31 | E80: 9.13 | F80: 7.93 | I80: Preferred stock | J80: 1698 | K80: 2324 | L80: 2324 | M80: 3080 | N80: 1543
A81: Diluted weighted-average shares outstanding (in shares) | B81: 148 | C81: 245 | D81: 245 | E81: 245 | F81: 245 | I81: Common stock and additional paid-in capital | J81: 20452 | K81: 19545 | L81: 19545 | M81: 18855
A82: Class B-2 common stock | I82: Right to recover for covered losses | J82: -140 | K82: -35 | L82: -35 | M82: -133 | N82: -39
A83: Earnings Per Share | I83: Accumulated income | J83: 18040 | K83: 16116 | L83: 16116 | M83: 15351 | N83: 14088
A84: Basic earnings per share (in dollars per share) | B84: 15.45 | C84: 0 | D84: 0 | E84: 0 | F84: 0 | I84: Accumulated other comprehensive income (loss):
A85: Basic weighted-average shares outstanding (in shares) | B85: 49 | C85: 0 | D85: 0 | E85: 0 | F85: 0 | I85: Defined benefit pension and other postretirement plans | J85: -155 | K85: -169 | L85: -169 | M85: -49 | N85: -196
A86: Diluted earnings per share (in dollars per share) | B86: 15.43 | C86: 0 | D86: 0 | E86: 0 | F86: 0 | I86: Derivative instruments | J86: -177 | K86: 418 | L86: 418 | M86: -257 | N86: -291
A87: Diluted weighted-average shares outstanding (in shares) | B87: 49 | C87: 0 | D87: 0 | E87: 0 | F87: 0 | I87: Foreign currency translation adjustments | J87: -921 | K87: -2512 | L87: -2512 | M87: 743 | N87: 838
A88: Class C common stock | I88: Total accumulated other comprehensive income (loss) | J88: -1317 | K88: -2369
A89: Earnings Per Share | I89: Total equity | J89: 38733 | K89: 35581 | L89: 35581 | M89: 37589 | N89: 36210
A90: Basic earnings per share (in dollars per share) | B90: 38.97 | C90: 33.17 | D90: 28.03 | E90: 22.53 | F90: 19.58 | I90: Total liabilities and equity | J90: 90499 | K90: 85501 | L90: 85501 | M90: 82896 | N90: 80919
A91: Basic weighted-average shares outstanding (in shares) | B91: 16 | C91: 10 | D91: 10 | E91: 10 | F91: 11 | I91: Accumulated other comprehensive income (loss), net:
A92: Diluted earnings per share (in dollars per share) | B92: 38.92 | C92: 33.13 | D92: 28 | E92: 22.51 | F92: 19.56 | I92: Total accumulated other comprehensive income (loss), net | L92: -2369 | M92: 436 | N92: 354
A93: Diluted weighted-average shares outstanding (in shares) | B93: 16 | C93: 10 | D93: 10 | E93: 10 | F93: 11 | I93: Commitments and contingencies (Note 18)
I94: Additional paid-in capital | N94: 16721
I95: Series A convertible participating preferred stock
I96: Series B convertible participating preferred stock
I97: Series C convertible participating preferred stock
I98: Class A common stock
I99: Common stock | N99: 0
A100: Sources:SEC EDGAR Data Bases | I100: Class B common stock
...

Sheet Beta
A1: Date | B1: Index Close | C1: Stock Close | D1: Index Return | E1: Stock Return | F1: Source:Investing.com
A2: 45322 | B2: 4845.65 | C2: 449.23 | F2: Period | G2: 2022-2024
A3: 45321 | B3: 4924.97 | C3: 445.19 | D3: =(B2-Table21[[#This Row],[Index Close]])/Table21[[#This Row],[Index Close]] -> -0.016105682 | E3: =(C2-Table21[[#This Row],[Stock Close]])/Table21[[#This Row],[Stock Close]] -> 0.0090747771
A4: 45320 | B4: 4927.93 | C4: 440.58 | D4: =(B3-Table21[[#This Row],[Index Close]])/Table21[[#This Row],[Index Close]] -> -0.00060065788 | E4: =(C3-Table21[[#This Row],[Stock Close]])/Table21[[#This Row],[Stock Close]] -> 0.01046348 | F4: Slope | G4: Value
A5: 45317 | B5: 4890.97 | C5: 438.53 | D5: =(B4-Table21[[#This Row],[Index Close]])/Table21[[#This Row],[Index Close]] -> 0.0075567832 | E5: =(C4-Table21[[#This Row],[Stock Close]])/Table21[[#This Row],[Stock Close]] -> 0.0046747087 | F5: Slope | G5: =SLOPE(E3:E600, D3:D600) -> 1.0378473
A6: 45316 | B6: 4894.16 | C6: 436.8 | D6: =(B5-Table21[[#This Row],[Index Close]])/Table21[[#This Row],[Index Close]] -> -0.00065179724 | E6: =(C5-Table21[[#This Row],[Stock Close]])/Table21[[#This Row],[Stock Close]] -> 0.0039606227 | G6: =SLOPE(E4:E601, D4:D601) -> 1.0432746
A7: 45315 | B7: 4868.55 | C7: 438.7 | D7: =(B6-Table21[[#This Row],[Index Close]])/Table21[[#This Row],[Index Close]] -> 0.0052602931 | E7: =(C6-Table21[[#This Row],[Stock Close]])/Table21[[#This Row],[Stock Close]] -> -0.0043309779 | F7: Beta | G7: Value
A8: 45314 | B8: 4864.6 | C8: 438.76 | D8: =(B7-Table21[[#This Row],[Index Close]])/Table21[[#This Row],[Index Close]] -> 0.00081198865 | E8: =(C7-Table21[[#This Row],[Stock Close]])/Table21[[#This Row],[Stock Close]] -> -0.00013674902 | F8: Beta | G8: =_xlfn.COVARIANCE.P(E3:E600, D3:D600) / _xlfn.VAR.P(D3:D600) -> 1.0378473
A9: 45313 | B9: 4850.43 | C9: 439.75 | D9: =(B8-Table21[[#This Row],[Index Close]])/Table21[[#This Row],[Index Close]] -> 0.0029213905 | E9: =(C8-Table21[[#This Row],[Stock Close]])/Table21[[#This Row],[Stock Close]] -> -0.0022512791
A10: 45310 | B10: 4839.81 | C10: 436.78 | D10: =(B9-Table21[[#This Row],[Index Close]])/Table21[[#This Row],[Index Close]] -> 0.002194301 | E10: =(C9-Table21[[#This Row],[Stock Close]])/Table21[[#This Row],[Stock Close]] -> 0.0067997619
A11: 45309 | B11: 4780.94 | C11: 430.72 | D11: =(B10-Table21[[#This Row],[Index Close]])/Table21[[#This Row],[Index Close]] -> 0.012313478 | E11: =(C10-Table21[[#This Row],[Stock Close]])/Table21[[#This Row],[Stock Close]] -> 0.014069465
A12: 45308 | B12: 4739.21 | C12: 427.42 | D12: =(B11-Table21[[#This Row],[Index Close]])/Table21[[#This Row],[Index Close]] -> 0.008805265 | E12: =(C11-Table21[[#This Row],[Stock Close]])/Table21[[#This Row],[Stock Close]] -> 0.0077207431
A13: 45307 | B13: 4765.98 | C13: 428.35 | D13: =(B12-Table21[[#This Row],[Index Close]])/Table21[[#This Row],[Index Close]] -> -0.0056168931 | E13: =(C12-Table21[[#This Row],[Stock Close]])/Table21[[#This Row],[Stock Close]] -> -0.0021711217
A14: 45303 | B14: 4783.83 | C14: 429.1 | D14: =(B13-Table21[[#This Row],[Index Close]])/Table21[[#This Row],[Index Close]] -> -0.0037313199 | E14: =(C13-Table21[[#This Row],[Stock Close]])/Table21[[#This Row],[Stock Close]] -> -0.0017478443
A15: 45302 | B15: 4780.24 | C15: 426.72 | D15: =(B14-Table21[[#This Row],[Index Close]])/Table21[[#This Row],[Index Close]] -> 0.00075100832 | E15: =(C14-Table21[[#This Row],[Stock Close]])/Table21[[#This Row],[Stock Close]] -> 0.0055774278
A16: 45301 | B16: 4783.45 | C16: 428.27 | D16: =(B15-Table21[[#This Row],[Index Close]])/Table21[[#This Row],[Index Close]] -> -0.00067106377 | E16: =(C15-Table21[[#This Row],[Stock Close]])/Table21[[#This Row],[Stock Close]] -> -0.0036192122
A17: 45300 | B17: 4756.5 | C17: 422.6 | D17: =(B16-Table21[[#This Row],[Index Close]])/Table21[[#This Row],[Index Close]] -> 0.0056659308 | E17: =(C16-Table21[[#This Row],[Stock Close]])/Table21[[#This Row],[Stock Close]] -> 0.013416943
A18: 45299 | B18: 4763.54 | C18: 421.98 | D18: =(B17-Table21[[#This Row],[Index Close]])/Table21[[#This Row],[Index Close]] -> -0.0014778925 | E18: =(C17-Table21[[#This Row],[Stock Close]])/Table21[[#This Row],[Stock Close]] -> 0.0014692639
A19: 45296 | B19: 4697.24 | C19: 419.42 | D19: =(B18-Table21[[#This Row],[Index Close]])/Table21[[#This Row],[Index Close]] -> 0.014114672 | E19: =(C18-Table21[[#This Row],[Stock Close]])/Table21[[#This Row],[Stock Close]] -> 0.006103667
A20: 45295 | B20: 4688.68 | C20: 419.77 | D20: =(B19-Table21[[#This Row],[Index Close]])/Table21[[#This Row],[Index Close]] -> 0.0018256738 | E20: =(C19-Table21[[#This Row],[Stock Close]])/Table21[[#This Row],[Stock Close]] -> -0.00083378993
... A523: 44564 | B523: 4796.6 | C523: 370.95 | D523: =(B522-Table21[[#This Row],[Index Close]])/Table21[[#This Row],[Index Close]] -> -0.00064629112 | E523: =(C522-Table21[[#This Row],[Stock Close]])/Table21[[#This Row],[Stock Close]] -> 0.011969268

Sheet Regression
A1: Subject Descripton | B1: Units | C1: Scale | D1: Country/Series-specific Notes | E1: 2020 | F1: 2021 | G1: 2022 | H1: 2023 | I1: 2024 | J1: 2025E | K1: 2026E | L1: 2027E | M1: 2028E | N1: 2029E | O1: Estimates Starts After
A2: Gross domestic product, constant prices | B2: National currency | C2: Billions | D2: Source: IMF / World Bank | E2: 84900 | F2: 96500 | G2: 100600 | H2: 105400 | I2: 110000 | J2: 115300 | K2: 120700 | L2: 126000 | M2: 131400 | N2: 136900 | O2: 2024
A3: Gross domestic product, constant prices | B3: Percent change | D3: See notes for: Gross domestic product, constant prices (National currency). | E3: -0.031 | F3: 0.06 | G3: 0.035 | H3: 0.032 | I3: 0.031 | J3: 0.032 | K3: 0.032 | L3: 0.031 | M3: 0.03 | N3: 0.03 | O3: 2024
A4: Inflation, average consumer prices | B4: Index | D4: Source: CEIC | E4: 103 | F4: 108 | G4: 118 | H4: 126 | I4: 133 | J4: 138 | K4: 143 | L4: 148 | M4: 153 | N4: 158 | O4: 2024
A5: Inflation, average consumer prices | B5: Percent change | D5: See notes for: Inflation, average consumer prices (Index). | E5: 0.032 | F5: 0.047 | G5: 0.087 | H5: 0.068 | I5: 0.055 | J5: 0.042 | K5: 0.038 | L5: 0.035 | M5: 0.033 | N5: 0.032 | O5: 2024
A7: Years | B7: GDP | C7: % Change in GDP | D7: Inflation | E7: % Change in Inflation | F7: Industry | G7: Company
A8: 2020 | B8: 84900 | C8: -0.031 | D8: 103 | E8: 0.032 | F8: 37000 | G8: 15301
A9: 2021 | B9: 96500 | C9: 0.06 | D9: 108 | E9: 0.047 | F9: 43000 | G9: 18884
A10: 2022 | B10: 100600 | C10: 0.035 | D10: 118 | E10: 0.087 | F10: 52000 | G10: 22237
A11: 2023 | B11: 105400 | C11: 0.032 | D11: 126 | E11: 0.068 | F11: 58000 | G11: 25098
A12: 2024 | B12: 110000 | C12: 0.031 | D12: 133 | E12: 0.055 | F12: 64000 | G12: 28167
A13: 2025E | B13: 115300 | C13: 0.032 | D13: 138 | E13: 0.042
A14: 2026E | B14: 120700 | C14: 0.032 | D14: 143 | E14: 0.038
A15: 2027E | B15: 126000 | C15: 0.031 | D15: 148 | E15: 0.035
A16: 2028E | B16: 131400 | C16: 0.03 | D16: 153 | E16: 0.033
A17: 2029E | B17: 136900 | C17: 0.03 | D17: 158 | E17: 0.032
A19: SUMMARY OUTPUT
A21: Regression Statistics
A22: Multiple R | B22: 0.99806315
A23: R Square | B23: 0.99613006
A24: Adjusted R Square | B24: 0.99419509
A25: Standard Error | B25: 302.20906
A26: Observations | B26: 4
A28: ANOVA
B29: df | C29: SS | D29: MS | E29: F | F29: Significance F
A30: Regression | B30: 1 | C30: 47017208 | D30: 47017208 | E30: 514.80396 | F30: 0.0019368454
A31: Residual | B31: 2 | C31: 182660.63 | D31: 91330.317
A32: Total | B32: 3 | C32: 47199869
B34: Coefficients | C34: Standard Error | D34: t Stat | E34: P-value | F34: Lower 95% | G34: Upper 95% | H34: Lower 95.0% | I34: Upper 95.0%
A35: Intercept | B35: -46177.127 | C35: 3078.8889 | D35: -14.997984 | E35: 0.0044162116 | F35: -59424.517 | G35: -32929.738 | H35: -59424.517 | I35: -32929.738
A36: 84900 | B36: 0.67659275 | C36: 0.029819915 | D36: 22.689292 | E36: 0.0019368454 | F36: 0.54828801 | G36: 0.80489749 | H36: 0.54828801 | I36: 0.80489749
A38: SUMMARY OUTPUT
A40: Regression Statistics
A41: Multiple R | B41: 0.99814483
A42: R Square | B42: 0.9962931
A43: Adjusted R Square | B43: 0.99443964
A44: Standard Error | B44: 295.77473
A45: Observations | B45: 4
A47: ANOVA
B48: df | C48: SS | D48: MS | E48: F | F48: Significance F
A49: Regression | B49: 1 | C49: 47024904 | D49: 47024904 | E49: 537.53381 | F49: 0.0018551728
A50: Residual | B50: 2 | C50: 174965.38 | D50: 87482.69
A51: Total | B51: 3 | C51: 47199869
B53: Coefficients | C53: Standard Error | D53: t Stat | E53: P-value | F53: Lower 95% | G53: Upper 95% | H53: Lower 95.0% | I53: Upper 95.0%
A54: Intercept | B54: -21055.146 | C54: 1931.5734 | D54: -10.900515 | E54: 0.0083112291 | F54: -29366.035 | G54: -12744.256 | H54: -29366.035 | I54: -12744.256
A55: 103 | B55: 368.26099 | C55: 15.883742 | D55: 23.184775 | E55: 0.0018551728 | F55: 299.91877 | G55: 436.60322 | H55: 299.91877 | I55: 436.60322
A57: SUMMARY OUTPUT
A59: Regression Statistics
A60: Multiple R | B60: 0.99688926
A61: R Square | B61: 0.99378821
A62: Adjusted R Square | B62: 0.99068231
A63: Standard Error | B63: 382.8811
A64: Observations | B64: 4
A66: ANOVA
B67: df | C67: SS | D67: MS | E67: F | F67: Significance F
A68: Regression | B68: 1 | C68: 46906673 | D68: 46906673 | E68: 319.96817 | F68: 0.0031107354
A69: Residual | B69: 2 | C69: 293195.87 | D69: 146597.93
A70: Total | B70: 3 | C70: 47199869
B72: Coefficients | C72: Standard Error | D72: t Stat | E72: P-value | F72: Lower 95% | G72: Upper 95% | H72: Lower 95.0% | I72: Upper 95.0%
A73: Intercept | B73: -349.5514 | C73: 1352.3108 | D73: -0.25848451 | E73: 0.82020244 | F73: -6168.0752 | G73: 5468.9724 | H73: -6168.0752 | I73: 5468.9724
A74: 37000 | B74: 0.44140187 | C74: 0.024676342 | D74: 17.887654 | E74: 0.0031107354 | F74: 0.33522814 | G74: 0.5475756 | H74: 0.33522814 | I74: 0.5475756

Sheet DCF Valuation
A1: DCF Valuation of Mastercard inc
A2: Assumptions | B2: Column1
A3: A | B3: B
A4: Risk Free Rate | B4: 0.045
A5: Market Return | B5: 0.1
A6: Beta | B6: {=Table23[Value]} -> 1.0378473
A7: Tax Rate | B7: 0.16
A8: Terminal Growth | B8: 0.03
A9: Cost of Equity (CAPM) | B9: =B4+B6*(B5-B4) -> 0.1020816
A10: Cost of Debt | B10: =WACC!B13 -> 0.045
A11: Equity Weight | B11: =WACC!B23 -> 0.95389284
A12: Debt Weight | B12: =WACC!B24 -> 0.046107156
A13: WACC | B13: =WACC!B28 -> 0.09911776
A14: Revenue Growth | B14: 0.1
A15: Market Risk Premium | B15: 0.055
A16: Timeline Headers | B16: 2025E | C16: 2026E | D16: 2027E | E16: 2028E | F16: 2029E | G16: Total
A17: Revenue | B17: ='Profit Loss'!G4 -> 31265.37 | C17: ='Profit Loss'!H4 -> 34391.907 | D17: ='Profit Loss'!I4 -> 37487.179 | E17: ='Profit Loss'!J4 -> 40486.153 | F17: ='Profit Loss'!K4 -> 43320.184 | G17: =SUM(B17:F17) -> 186950.79
A18: EBIT | B18: ='Profit Loss'!G11 -> 17195.954 | C18: ='Profit Loss'!H11 -> 19259.468 | D18: ='Profit Loss'!I11 -> 21180.256 | E18: ='Profit Loss'!J11 -> 23077.107 | F18: ='Profit Loss'!K11 -> 24909.106 | G18: =SUM(B18:F18) -> 105621.89
A19: NOPAT | B19: =B18*0.84 -> 14444.601 | C19: =C18*0.84 -> 16177.953 | D19: =D18*0.84 -> 17791.415 | E19: =E18*0.84 -> 19384.77 | F19: =F18*0.84 -> 20923.649 | G19: =SUM(B19:F19) -> 88722.388
A20: Depreciation and Amortization | B20: ='Profit Loss'!G8 -> 968.76 | C20: ='Profit Loss'!H8 -> 1046.2608 | D20: ='Profit Loss'!I8 -> 1129.9617 | E20: ='Profit Loss'!J8 -> 1220.3586 | F20: ='Profit Loss'!K8 -> 1317.9873 | G20: =SUM(B20:F20) -> 5683.3283
A21: Capital Expenditure | B21: ='Cash Flow'!G31-'Cash Flow'!G32 -> 258.3 | C21: ='Cash Flow'!H31-'Cash Flow'!H32 -> 271.215 | D21: ='Cash Flow'!I31-'Cash Flow'!I32 -> 284.77575 | E21: ='Cash Flow'!J31-'Cash Flow'!J32 -> 299.01454 | F21: ='Cash Flow'!K31-'Cash Flow'!K32 -> 313.96526 | G21: =SUM(B21:F21) -> 1427.2706
A22: Change in Working Capital | B22: =2%*(B17-'Profit Loss'!F4) -> 61.9674 | C22: =2%*(C17-'Profit Loss'!G4) -> 62.53074 | D22: =2%*(D17-'Profit Loss'!H4) -> 61.905433 | E22: =2%*(E17-'Profit Loss'!I4) -> 59.979486 | F22: =2%*(F17-'Profit Loss'!J4) -> 56.680614 | G22: =SUM(B22:F22) -> 303.06367
A23: Free Cash Flow to Firm | B23: ='Cash Flow'!G55 -> 18870.51 | C23: ='Cash Flow'!H55 -> 20032.723 | D23: ='Cash Flow'!I55 -> 21812.545 | E23: ='Cash Flow'!J55 -> 23570.443 | F23: ='Cash Flow'!K55 -> 25271.952 | G23: =SUM(B23:F23) -> 109558.17
A24: Discount Factor | B24: =1/(1+$B$13)^1 -> 0.90982062 | C24: =1/(1+$B$13)^2 -> 0.82777356 | D24: =1/(1+$B$13)^3 -> 0.75312545 | E24: =1/(1+$B$13)^4 -> 0.68520906 | F24: =1/(1+$B$13)^5 -> 0.62341733 | G24: =SUM(B24:F24) -> 3.799346
A25: Present Value FCFF | B25: =B23*B24 -> 17168.779 | C25: =C23*C24 -> 16582.558 | D25: =D23*D24 -> 16427.583 | E25: =E23*E24 -> 16150.681 | F25: =F23*F24 -> 15754.973 | G25: =SUM(B25:F25) -> 82084.575
A26: Column1 | B26: Column2
A27: Terminal Value | B27: =F23*(1+$B$8)/($B$13-$B$8) -> 376605.25
A28: Discount Terminal Value | B28: =B27*F24 -> 234782.24
A29: Enterprise Value | B29: =G25+B28 -> 316866.81
A30: Equity Value | B30: =B29-B32 -> 333546.84
A31: Intrinsic Value | B31: =B30/'Profit Loss'!G24 -> 367.15633
A32: Net Debt | B32: =(Balance_Sheet!K28+Balance_Sheet!K25)-Balance_Sheet!K4 -> -16680.025
A33: Valuation Summary | B33: Values
A34: Enterprise Value | B34: =B29 -> 316866.81
A35: Equity Value | B35: =B30 -> 333546.84
A36: DCF Fair Value(Intrinsic) | B36: =B31 -> 367.15633
A37: Current Price | B37: 450
A38: Upside | B38: =(B36-B37)/B37 -> -0.18409704
A39: Recommendation | B39: =IF(B37>B36,"BUY",IF(B36=B37,"HOLD","SELL")) -> BUY

Sheet DDM FCFF Relative Valuation
A1: Mastercard Inc — DDM,FCFF,FCFE,Relative Valuation Model
A2: Dividend Discount Model (Reference only) | B2: Amount | C2: 2020 | D2: 2021 | E2: 2022 | F2: 2023 | G2: 2024 | H2: 2025 | I2: 2026 | J2: 2027 | K2: 2028 | L2: 2029
A3: Dividend Per Share | C3: =K34/O23 -> 1.9175627 | D3: =K35/O23 -> 2.0800478 | E3: =K36/O23 -> 2.2735962 | F3: =K37/O23 -> 2.5782557 | G3: =K38/O23 -> 2.9247312 | H3: =K39/O23 -> 3.1003584 | I3: =K40/O23 -> 3.2867384 | J3: =K41/O23 -> 3.483871 | K3: =K42/O23 -> 3.692951 | L3: =K43/O23 -> 3.9139785
A4: Growth In Dividend | B4: =(D3/C3)-1 -> 0.084735202 | G4: =(G3/C3)^0.25-1 -> 0.11130711 | H4: =(G4-($G$4-$L$4)/5) -> 0.099045691 | I4: =(H4-($G$4-$L$4)/5) -> 0.086784268 | J4: =(I4-($G$4-$L$4)/5) -> 0.074522845 | K4: =(J4-($G$4-$L$4)/5) -> 0.062261423 | L4: 0.05
A5: Long Term Growth | B5: 0.035 | C5: Note: Mastercard distributes capital primarily through share buybacks rather than dividends; therefore DDM significantly understates intrinsic value and is excluded from target price calculation.
A6: Long Term Ke | B6: ='Common Size'!B62 -> 0.1020816
A8: Terminal value (Do*(1+g)/(Ke-g)) | B8: =L3*(1+B5)/(B6-B5) -> 60.388656
A9: PV Of Terminal Value | B9: =B8/(1+$B$6)^5 -> 37.143823
A10: PV Of Dividends | B10: =SUM(C3:L3) -> 29.252091
A11: Total PV Of Firm | B11: =B10+B9 -> 66.395914
A12: Intrinsic Value (DDM) | B12: =B11 -> 66.395914
A13: Traded price as on 31st March | B13: 430
A14: Diff | B14: =B12-B13 -> -363.60409
A15: Value of security | B15: =B12 -> 66.395914
A17: Legacy DDM Check | B17: Amount | C17: 2020 | D17: 2021 | E17: 2022 | F17: 2023 | G17: 2024 | H17: 2025 | I17: 2026 | J17: 2027 | K17: 2028 | L17: 2029 | N17: Column1 | O17: Column2
A18: DDM | C18: ='Cash Flow'!B24-('Cash Flow'!B31+'Cash Flow'!B32)+('Cash Flow'!B42-'Cash Flow'!B43) -> 11891 | D18: ='Cash Flow'!C24-('Cash Flow'!C31+'Cash Flow'!C32)+('Cash Flow'!C42-'Cash Flow'!C43) -> 12951 | E18: ='Cash Flow'!D24-('Cash Flow'!D31+'Cash Flow'!D32)+('Cash Flow'!D42-'Cash Flow'!D43) -> 14139 | F18: ='Cash Flow'!E24-('Cash Flow'!E31+'Cash Flow'!E32)+('Cash Flow'!E42-'Cash Flow'!E43) -> 14622 | G18: ='Cash Flow'!F24-('Cash Flow'!F31+'Cash Flow'!F32)+('Cash Flow'!F42-'Cash Flow'!F43) -> 21270 | H18: ='Cash Flow'!G24-('Cash Flow'!G31+'Cash Flow'!G32)+('Cash Flow'!G42-'Cash Flow'!G43) -> 25917.91 | I18: ='Cash Flow'!H24-('Cash Flow'!H31+'Cash Flow'!H32)+('Cash Flow'!H42-'Cash Flow'!H43) -> 27167.693 | J18: ='Cash Flow'!I24-('Cash Flow'!I31+'Cash Flow'!I32)+('Cash Flow'!I42-'Cash Flow'!I43) -> 29039.464 | ... L18: ='Cash Flow'!K24-('Cash Flow'!K31+'Cash Flow'!K32)+('Cash Flow'!K42-'Cash Flow'!K43) -> 32696.79 | N18: Required Return (Ke) | O18: 0.09
A19: Growth In DDM | C19: =(D18/C18)-1 -> 0.089143049 | G19: =C19 -> 0.089143049 | H19: =(G19-($G$19-$L$19)/5) -> 0.081314439 | I19: =(H19-($G$19-$L$19)/5) -> 0.07348583 | J19: =(I19-($G$19-$L$19)/5) -> 0.06565722 | K19: =(J19-($G$19-$L$19)/5) -> 0.05782861 | L19: 0.05 | N19: Long Term Growth (g) | O19: 0.05
A20: Long Term Growth Rate | B20: 0.035 | N20: Terminal Value | O20: 102.6279
A21: Long Term Ke(DDM) | B21: 0.1021 | N21: PV of Terminal Value | O21: 43.3511
A22: Terminal value (DDM*(1+g)/(Ke-g)) | B22: =L18*(1+B20)/(B21-B20) -> 504339.46 | N22: Intrinsic Value Per Share | O22: 61.0731
A23: PV Of Terminal Value | B23: =B22/(1+$B$21)^10 -> 190771.25 | N23: Outstanding Shares | O23: 837
A24: PV Of DDM | B24: =SUM(C18:L18) -> 220588.76
A25: Total PV Of Firm | B25: =B24+B23 -> 411360.01
A26: No OF Outstanding shares | B26: ='Profit Loss'!K24 -> 837.93458
A27: Intrinsic Value Per Share (DDM) | B27: =B25/B26 -> 490.9214
A28: Traded price as on 31st March | B28: 430
A29: Diff | B29: =B27-B28 -> 60.921398
A30: Value Of Security | B30: =B25/B26 -> 490.9214
A31: Previous Close | B31: -
A33: Relative Valuation | B33: Company | C33: Industry | D33: Implied | E33: Price | G33: Calculations | H33: Values | J33: Year | K33: Total Dividend | L33: Dividend Per Share (DPS) | M33: PV of DPS
A34: P/E | B34: =B28/Table18[[#This Row],[Values]] -> 30.895604 | C34: 30 | D34: =Table18[[#This Row],[Values]] -> 13.917838 | E34: =D34*C34 -> 417.53514 | G34: EPS | H34: ='Profit Loss'!F20/'Profit Loss'!F22 -> 13.917838 | J34: 2020 | K34: 1605 | L34: 1.9154 | M34: 1.7573
A35: P/BV | B35: =B28/Table18[[#This Row],[Values]] -> 61.05142 | C35: 12 | D35: =Table18[[#This Row],[Values]] -> 7.0432432 | E35: =D35*C35 -> 84.518919 | G35: BVPS | H35: =Balance_Sheet!F41/'Profit Loss'!F22 -> 7.0432432 | J35: 2021 | K35: 1741 | L35: 2.0777 | M35: 1.7488
A36: P/S | B36: =B28/Table18[[#This Row],[Values]] -> 14.121135 | C36: 14 | D36: =Table18[[#This Row],[Values]] -> 30.450811 | E36: =D36*C36 -> 426.31135 | G36: Sales Per Share | H36: ='Profit Loss'!F4/'Profit Loss'!F22 -> 30.450811 | J36: 2022 | K36: 1903 | L36: 2.2711 | M36: 1.7537
A37: EV/EBITA | B37: =H39 -> 24.730505 | C37: 24 | D37: =H40 -> 17.815135 | E37: =D37*C37 -> 427.56324 | G37: Enterprise Value | H37: =(B28*'Profit Loss'!F22)+'Common Size'!B92-Balance_Sheet!F4 -> 407534 | J37: 2023 | K37: 2158 | L37: 2.5754 | M37: 1.8245
A38: EV/EBIT | B38: =Table18[[#This Row],[Values]] -> 26.154152 | C38: 26 | D38: =H41 -> 16.845405 | E38: =D38*C38 -> 437.98054 | G38: EV/EBIT | H38: =H37/'Profit Loss'!F11 -> 26.154152 | J38: 2024 | K38: 2448 | L38: 2.9215 | M38: 1.8988
D39: Target Price | E39: =AVERAGE(E34:E38) -> 358.78184 | G39: EV/EBITDA | H39: =H37/'Profit Loss'!F25 -> 24.730505 | J39: 2025 | K39: 2595 | L39: 3.0969 | M39: 1.8466
A40: Economic Vale Add(EVA) | B40: Residual Valuation | G40: EBITDA Per Share | H40: ='Profit Loss'!F25/'Profit Loss'!F22 -> 17.815135 | J40: 2026 | K40: 2751 | L40: 3.2831 | M40: 1.796
A41: Networth | B41: =Balance_Sheet!F41 -> 6515 | G41: EBIT Per Share | H41: ='Profit Loss'!F11/'Profit Loss'!F22 -> 16.845405 | J41: 2027 | K41: 2916 | L41: 3.48 | M41: 1.7465
A42: g | B42: 0.04 | G42: Cost of Equity Table | J42: 2028 | K42: 3091 | L42: 3.6889 | M42: 1.6985
A43: Ke | B43: 10.21 | G43: Input | H43: Value | J43: 2029 | K43: 3276 | L43: 3.9096 | M43: 1.6515
A44: Investor Expectation | B44: =B41*B43 -> 66518.15 | G44: Risk Free Rate | H44: 0.04
A45: NOPAT | B45: =H41*(1-D66) -> 14.150141 | G45: Beta | H45: {=Table23[Value]} -> 1.0378473
A46: PAT | B46: =B45*B51 -> 11856.892 | G46: Market Return | H46: 0.1
G47: Market Premium | H47: 0.06
A48: Residual Income | B48: =B46-B44 -> -54661.258 | G48: Cost of Equity (Ke) (CAPM) | H48: =H44+(H45*H47) -> 0.10227084
A49: Terminal Value | B49: =B48/(B43-B42) -> -5374.755 | G49: sensitivity Table
A50: PV Of EVA | B50: =B49/(1+B43) -> -479.46075 | G50: g \ Ke | H50: 9% | I50: 10% | J50: 11%
A51: No of Outstanding Shares | B51: =B26 -> 837.93458 | G51: 0.04 | H51: 550 | I51: 500 | J51: 460
A52: Value OF Firm (EVA) | B52: =B53+B49 -> 1140.245 | G52: 0.05 | H52: 620 | I52: 615 | J52: 580
A53: Book Value | B53: =Balance_Sheet!F41 -> 6515 | G53: 0.06 | H53: 700 | I53: 690 | J53: 650
A54: Value Of Firm (Per Share) | B54: =B52/B51 -> 1.3607805
A55: Note: EVA undervalues asset-light fintech companies due to low invested capital base.
A56: Final Valuation Summary
A57: Method | B57: Value
A58: DDM | B58: =B15 -> 66.395914
A59: FCFF | B59: =B106 -> 338.00514
A60: Relative Valuation | B60: =E39 -> 358.78184
A61: EVA | B61: =B52 -> 1140.245
A62: Final Fair Value Range | B62: =(B59+B60)/2 -> 348.39349
A63: Assumptions | J63: Assumptions
A64: Year | B64: Revenue Growth | C64: EBIT Margin | D64: Tax Rate | E64: Dep % of Revenue | F64: Capex % of Revenue | G64: Working Capital % of Revenue | H64: FCFE Growth (if used) | J64: Year | K64: EBIT Growth | L64: Dep Growth | M64: Capex Growth | N64: WC Growth
A65: 2024 | B65: Actual | C65: Actual | D65: 0.156 | E65: Actual | F65: Actual | G65: Actual | H65: – | J65: 2025E | K65: 0.18 | L65: 0.08 | M65: 0.08 | N65: 0.1
A66: 2025E | B66: 0.18 | C66: 0.54 | D66: 0.16 | E66: 0.055 | F66: 0.07 | G66: 0.25 | H66: 0.18 | J66: 2026E | K66: 0.16 | L66: 0.08 | M66: 0.08 | N66: 0.1
A67: 2026E | B67: 0.16 | C67: 0.54 | D67: 0.16 | E67: 0.055 | F67: 0.07 | G67: 0.25 | H67: 0.16 | J67: 2027E | K67: 0.13 | L67: 0.08 | M67: 0.08 | N67: 0.1
A68: 2027E | B68: 0.13 | C68: 0.54 | D68: 0.16 | E68: 0.055 | F68: 0.07 | G68: 0.25 | H68: 0.13 | J68: 2028E | K68: 0.1 | L68: 0.08 | M68: 0.08 | N68: 0.1
A69: 2028E | B69: 0.1 | C69: 0.54 | D69: 0.16 | E69: 0.055 | F69: 0.07 | G69: 0.25 | H69: 0.1 | J69: 2029E | K69: 0.07 | L69: 0.08 | M69: 0.08 | N69: 0.1
A70: 2029E | B70: 0.07 | C70: 0.54 | D70: 0.16 | E70: 0.055 | F70: 0.07 | G70: 0.25 | H70: 0.07 | J70: Terminal | K70: 0.05 | L70: Stable | M70: Stable | N70: Stable
A71: Terminal | B71: 0.05 | C71: Stable | D71: 0.16 | E71: Stable | F71: Stable | G71: Stable | H71: 0.05
A73: FCFF DCF Assumptions | D73: WC Calculation
A74: Assumption | B74: Value | D74: Year | E74: Revenue | F74: WC % | G74: Working Capital | H74: Δ Working Capital
A75: Risk Free Rate | B75: ='DCF Valuation'!B4 -> 0.045 | D75: 2024A | E75: ='Profit Loss'!F4 -> 28167 | F75: 0.1 | G75: =E75*F75 -> 2816.7 | H75: -
A76: Beta | B76: ='DCF Valuation'!B6 -> 1.0378473 | D76: 2025E | E76: ='Profit Loss'!G4 -> 31265.37 | F76: 0.1 | G76: =E76*F76 -> 3126.537 | H76: =G76-G75 -> 309.837
A77: Market Premium | B77: ='DCF Valuation'!B15 -> 0.055 | D77: 2026E | E77: ='Profit Loss'!H4 -> 34391.907 | F77: 0.1 | G77: =E77*F77 -> 3439.1907 | H77: =G77-G76 -> 312.6537
A78: Cost of Equity (Ke) | B78: ='DCF Valuation'!B9 -> 0.1020816 | D78: 2027E | E78: ='Profit Loss'!I4 -> 37487.179 | F78: 0.1 | G78: =E78*F78 -> 3748.7179 | H78: =G78-G77 -> 309.52716
A79: Cost of Debt | B79: ='DCF Valuation'!B10 -> 0.045 | D79: 2028E | E79: ='Profit Loss'!J4 -> 40486.153 | F79: 0.1 | G79: =E79*F79 -> 4048.6153 | H79: =G79-G78 -> 299.89743
A80: Tax Rate | B80: ='DCF Valuation'!B7 -> 0.16 | D80: 2029E | E80: ='Profit Loss'!K4 -> 43320.184 | F80: 0.1 | G80: =E80*F80 -> 4332.0184 | H80: =G80-G79 -> 283.40307
A81: Debt Weight | B81: ='DCF Valuation'!B12 -> 0.046107156
A82: Equity Weight | B82: ='DCF Valuation'!B11 -> 0.95389284
A83: WACC | B83: ='DCF Valuation'!B13 -> 0.09911776
A84: Terminal Growth (g) | B84: ='DCF Valuation'!B8 -> 0.03
A85: Shares Outstanding | B85: 837.93458
A87: FCFF (Enterprise Value) Calculation
A88: Year | B88: EBIT | C88: Tax Rate | D88: NOPAT | E88: Depreciation | F88: Capex | G88: Δ Working Capital | H88: FCFF
A89: 2025E | B89: ='Profit Loss'!G25 -> 18164.714 | C89: 0.16 | D89: =B89*(1-C89) -> 15258.359 | E89: ='Profit Loss'!G8 -> 968.76 | F89: =('Cash Flow'!G31-'Cash Flow'!G32) -> 258.3 | G89: =H76 -> 309.837 | H89: =D89+E89-F89-G89 -> 15658.982
A90: 2026E | B90: ='Profit Loss'!H25 -> 20305.729 | C90: 0.16 | D90: =B90*(1-C90) -> 17056.812 | E90: ='Profit Loss'!H8 -> 1046.2608 | F90: =('Cash Flow'!H31-'Cash Flow'!H32) -> 271.215 | G90: =H77 -> 312.6537 | H90: =D90+E90-F90-G90 -> 17519.204
A91: 2027E | B91: ='Profit Loss'!I25 -> 22310.218 | C91: 0.16 | D91: =B91*(1-C91) -> 18740.583 | E91: ='Profit Loss'!I8 -> 1129.9617 | F91: =('Cash Flow'!I31-'Cash Flow'!I32) -> 284.77575 | G91: =H78 -> 309.52716 | H91: =D91+E91-F91-G91 -> 19276.242
A92: 2028E | B92: ='Profit Loss'!J25 -> 24297.466 | C92: 0.16 | D92: =B92*(1-C92) -> 20409.871 | E92: ='Profit Loss'!J8 -> 1220.3586 | F92: =('Cash Flow'!J31-'Cash Flow'!J32) -> 299.01454 | G92: =H79 -> 299.89743 | H92: =D92+E92-F92-G92 -> 21031.318
A93: 2029E | B93: ='Profit Loss'!K25 -> 26227.093 | C93: 0.16 | D93: =B93*(1-C93) -> 22030.758 | E93: ='Profit Loss'!K8 -> 1317.9873 | F93: =('Cash Flow'!K31-'Cash Flow'!K32) -> 313.96526 | G93: =H80 -> 283.40307 | H93: =D93+E93-F93-G93 -> 22751.377
A95: Discounted FCFF
A96: Year | B96: FCFF | C96: Discount Factor (8.7%) | D96: PV FCFF | E96: Total PV FCFF
A97: 2025 | B97: =H89 -> 15658.982 | C97: =1/(1+$B$83)^1 -> 0.90982062 | D97: =Table50[[#This Row],[FCFF]]*Table50[[#This Row],[Discount Factor (8.7%)]] -> 14246.865 | E97: =SUM(D97:D101) -> 71860.679
A98: 2026 | B98: =H90 -> 17519.204 | C98: =1/(1+$B$83)^2 -> 0.82777356 | D98: =Table50[[#This Row],[FCFF]]*Table50[[#This Row],[Discount Factor (8.7%)]] -> 14501.934
A99: 2027 | B99: =H91 -> 19276.242 | C99: =1/(1+$B$83)^3 -> 0.75312545 | D99: =Table50[[#This Row],[FCFF]]*Table50[[#This Row],[Discount Factor (8.7%)]] -> 14517.428
A100: 2028 | B100: =H92 -> 21031.318 | C100: =1/(1+$B$83)^4 -> 0.68520906 | D100: =Table50[[#This Row],[FCFF]]*Table50[[#This Row],[Discount Factor (8.7%)]] -> 14410.85
A101: 2029 | B101: =H93 -> 22751.377 | C101: =1/(1+$B$83)^5 -> 0.62341733 | D101: =Table50[[#This Row],[FCFF]]*Table50[[#This Row],[Discount Factor (8.7%)]] -> 14183.603
A102: Terminal Value | B102: =H93*(1+B84)/(B83-B84) -> 339043.37
A103: Discount Terminal Value | B103: =B102*C101 -> 211365.51
A104: Enterprise Value | B104: =E97+B103 -> 283226.19
A105: Equity Value | B105: =B104-0 -> 283226.19
A106: Intrinsic Share Price | B106: =B105/B85 -> 338.00514
...

Sheet Competition
A1: Competitors of Mastercard Inc | B1: Last Price | C1: Market Cap ($ mn) | D1: Sales ($ mn) | E1: Net Profit ($ mn) | F1: Total Assets ($ mn)
A2: Mastercard | B2: 548 | C2: 510000 | D2: 28167 | E2: 12874 | F2: 48081
A3: Visa | B3: 331 | C3: 690000 | D3: 40000 | E3: 20058 | F3: 99627
A4: American Express | B4: 359.15 | C4: 255000 | D4: 72229 | E4: 10833 | F4: 271461
A5: PayPal | B5: 40.42 | C5: 42000 | D5: 33172 | E5: 5233 | F5: 80173
A6: Block inc | B6: 49.8 | C6: 29800 | D6: 24121 | E6: 2897 | F6: 36777
A7: Global Payments | B7: 120 | C7: 31000 | D7: 9700 | E7: 1200 | F7: 52000
C8: =SUM(Table28[Market Cap ($ mn)]) -> 1557800 | E8: =SUBTOTAL(109,Table28[Net Profit ($ mn)]) -> 53095

Sheet Credit Ratio
A1: Credit Ratios of Mastercard Inc
A2: Rating Grid | B2: Take Average of Five Years for the GRID Rating
A4: Credit Rating | B4: AAA | C4: AA | F4: A | G4: BBB
A5: Operating Margin | B5: 0.245 | C5: 0.165 | F5: 0.1 | G5: 0.075
A6: Debt / EBITDA | B6: 1.3 X | C6: 1.8 X | F6: 2.2 X | G6: 2.5 X
A7: EBITDA / Interest | B7: 25.0x | C7: 20.0 x | F7: 17.5 x | G7: 15.0 x
A8: FCF / Debt | B8: 0.3 | C8: 0.24 | F8: 0.2 | G8: 0.17
A9: Debt / Capital | B9: 0.25 | C9: 0.3 | F9: 0.35 | G9: 0.4
A11: Particulars | B11: 2020 | C11: 2021 | D11: 2022 | E11: 2023 | F11: 2024 | G11: AVERAGE | H11: RATING
A12: EBIDTA | B12: ='Profit Loss'!B25 -> 8661 | C12: ='Profit Loss'!C25 -> 10808 | D12: ='Profit Loss'!D25 -> 13014 | E12: ='Profit Loss'!E25 -> 14807 | F12: ='Profit Loss'!F25 -> 16479 | G12: =AVERAGE(B12:F12) -> 12753.8
A13: FCF after Dividends | B13: ='Common Size'!B88-'Common Size'!B55 -> 3019.119 | C13: ='Common Size'!C88-'Common Size'!C55 -> 766.36002 | D13: ='Common Size'!D88-'Common Size'!D55 -> 2940.4466 | E13: ='Common Size'!E88-'Common Size'!E55 -> 1966.9461 | F13: ='Common Size'!F88-'Common Size'!F55 -> 4255.2571 | G13: =AVERAGE(B13:F13) -> 2589.6257
A14: Operating Margin | B14: ='Common Size'!B9 -> 0.52813542 | C14: ='Common Size'!C9 -> 0.53389112 | D14: ='Common Size'!D9 -> 0.55151324 | E14: ='Common Size'!E9 -> 0.55813212 | F14: ='Common Size'!F9 -> 0.55320055 | G14: =AVERAGE(B14:F14) -> 0.54497449 | H14: AAA
A15: Debt / EBIT | B15: ='Common Size'!B43/'Common Size'!B73 -> 1.4631105 | C15: ='Common Size'!C43/'Common Size'!C73 -> 1.2861769 | D15: ='Common Size'!D43/'Common Size'!D73 -> 1.0775319 | E15: ='Common Size'!E43/'Common Size'!E73 -> 1.0590261 | F15: ='Common Size'!F43/'Common Size'!F73 -> 1.169683 | G15: =AVERAGE(B15:F15) -> 1.2111057 | H15: AAA
A16: EBITDA / Interest | B16: =Table10[[#This Row],[2020]]/-'Common Size'!B11 -> 22.792105 | C16: =Table10[[#This Row],[2020]]/-'Common Size'!C11 -> 24.800757 | D16: =Table10[[#This Row],[2020]]/-'Common Size'!D11 -> 26.724126 | E16: =Table10[[#This Row],[2020]]/-'Common Size'!E11 -> 24.70697 | F16: =Table10[[#This Row],[2020]]/-'Common Size'!F11 -> 24.680633 | G16: =AVERAGE(B16:F16) -> 24.740918 | H16: AA
A17: FCF / DEBT | B17: ='Common Size'!B86/'Common Size'!B43 -> 0.74592566 | C17: ='Common Size'!C86/'Common Size'!C43 -> 0.86916448 | D17: ='Common Size'!D86/'Common Size'!D43 -> 1.0598366 | E17: ='Common Size'!E86/'Common Size'!E43 -> 1.0816086 | F17: ='Common Size'!F86/'Common Size'!F43 -> 1.1755088 | G17: =AVERAGE(B17:F17) -> 0.98640882 | H17: AAA
A18: DEBT / Capital | B18: ='Common Size'!B43/('Common Size'!B43+Balance_Sheet!F41) -> 0.66044718 | C18: ='Common Size'!C43/('Common Size'!C43+Balance_Sheet!G41) -> 0.48240046 | D18: ='Common Size'!D43/('Common Size'!D43+Balance_Sheet!H41) -> 0.3639465 | E18: ='Common Size'!E43/('Common Size'!E43+Balance_Sheet!I41) -> 0.30813479 | F18: ='Common Size'!F43/('Common Size'!F43+Balance_Sheet!J41) -> 0.27940695 | G18: =AVERAGE(B18:F18) -> 0.41886717 | H18: BB
A19: Debt / EBITDA | B19: ='Common Size'!B43/'Profit Loss'!F25 -> 0.7689787 | C19: ='Common Size'!C43/'Profit Loss'!G25 -> 0.76527494 | D19: ='Common Size'!D43/'Profit Loss'!H25 -> 0.69059329 | E19: ='Common Size'!E43/'Profit Loss'!I25 -> 0.70286181 | F19: ='Common Size'!F43/'Profit Loss'!J25 -> 0.75011938 | G19: =AVERAGE(B19:F19) -> 0.73556562 | H19: AAA

Sheet Ratios
A1: Ratio Analysis of Mastercard Inc
A2: Column1 | B2: Column2 | C2: Column3 | D2: Column4 | E2: Column5 | F2: Column6 | G2: Column7 | H2: Column8 | I2: Column9 | J2: Column10 | K2: Column11 | L2: Column12 | M2: Column13
A3: Year End | B3: Computation Formula | C3: Company | I3: Industry
A4: Operational & Financial Ratios | C4: 2020 | D4: 2021 | E4: 2022 | F4: 2023 | G4: 2024 | I4: =C4 -> 2020 | J4: 2021 | K4: 2022 | L4: 2023 | M4: 2024
A5: Earnings Per Share (Rs) | B5: PAT/Number of Shares | C5: ='Profit Loss'!B20/'Profit Loss'!B24 -> 6.3727634 | D5: ='Profit Loss'!C20/'Profit Loss'!C24 -> 8.7570565 | E5: ='Profit Loss'!D20/'Profit Loss'!D24 -> 10.226571 | F5: ='Profit Loss'!E20/'Profit Loss'!E24 -> 11.834038 | G5: ='Profit Loss'!F20/'Profit Loss'!F24 -> 13.88781 | I5: N/A | J5: N/A | K5: N/A | L5: N/A | M5: N/A
A6: DPS(Rs) | B6: Dividend/Number of Shares | C6: =-'Cash Flow'!B41/'Profit Loss'!B24 -> 1.5954274 | D6: =-'Cash Flow'!C41/'Profit Loss'!C24 -> 1.7550403 | E6: =-'Cash Flow'!D41/'Profit Loss'!D24 -> 1.9598352 | F6: =-'Cash Flow'!E41/'Profit Loss'!E24 -> 2.2811839 | G6: =-'Cash Flow'!F41/'Profit Loss'!F24 -> 2.6407767 | I6: N/A | J6: N/A | K6: N/A | L6: N/A | M6: N/A
A7: Book Value Per share | B7: Share holders Equity/Number of Shares | C7: =Balance_Sheet!B41/'Profit Loss'!B24 -> 6.4493042 | D7: =Balance_Sheet!C41/'Profit Loss'!C24 -> 7.4425403 | E7: =Balance_Sheet!D41/'Profit Loss'!D24 -> 6.545829 | F7: =Balance_Sheet!E41/'Profit Loss'!E24 -> 7.3731501 | G7: =Balance_Sheet!F41/'Profit Loss'!F24 -> 7.0280475 | I7: N/A | J7: N/A | K7: N/A | L7: N/A | M7: N/A
A8: Effective Tax Rate(%) | B8: Tax/PBT | C8: ='Profit Loss'!B19/'Profit Loss'!B18 -> 0.17384021 | D8: ='Profit Loss'!C19/'Profit Loss'!C18 -> 0.15717474 | E8: ='Profit Loss'!D19/'Profit Loss'!D18 -> 0.153597 | F8: ='Profit Loss'!E19/'Profit Loss'!E18 -> 0.17919202 | G8: ='Profit Loss'!F19/'Profit Loss'!F18 -> 0.15602465 | I8: ='Ind_P&L'!B18/'Ind_P&L'!B17 -> 0.19906115 | J8: ='Ind_P&L'!C18/'Ind_P&L'!C17 -> 0.16790047 | K8: ='Ind_P&L'!D18/'Ind_P&L'!D17 -> 0.14879166 | L8: ='Ind_P&L'!E18/'Ind_P&L'!E17 -> 0.16732874 | M8: ='Ind_P&L'!F18/'Ind_P&L'!F17 -> 0.14753438
A9: Dividend Pay Out Ratio(%) | B9: DPS/EPS | C9: ='DDM FCFF Relative Valuation'!C3/'Profit Loss'!B23 -> 0.30103025 | D9: ='DDM FCFF Relative Valuation'!D3/'Profit Loss'!C23 -> 0.23744838 | E9: ='DDM FCFF Relative Valuation'!E3/'Profit Loss'!D23 -> 0.22246538 | F9: ='DDM FCFF Relative Valuation'!F3/'Profit Loss'!E23 -> 0.21794215 | G9: ='DDM FCFF Relative Valuation'!G3/'Profit Loss'!F23 -> 0.2105638 | I9: N/A | J9: N/A | K9: N/A | L9: N/A | M9: N/A
A10: Retention Ratio | B10: 1-Dividend Payout Ratio | C10: =1-C9 -> 0.69896975 | D10: =1-D9 -> 0.76255162 | E10: =1-E9 -> 0.77753462 | F10: =1-F9 -> 0.78205785 | G10: =1-G9 -> 0.7894362 | I10: N/A | J10: N/A | K10: N/A | L10: N/A | M10: N/A
A11: Margin/Profitability Ratios
A12: Gross Margin | B12: Gross Profit/Net Sales | C12: N/A | D12: N/A | E12: N/A | F12: N/A | G12: N/A | I12: N/A | J12: N/A | K12: N/A | L12: N/A | M12: N/A
A13: ROE (%) | B13: PAT/Share Holders Equity | C13: ='Profit Loss'!B20/Balance_Sheet!B41 -> 0.98813194 | D13: ='Profit Loss'!C20/Balance_Sheet!C41 -> 1.176622 | E13: ='Profit Loss'!D20/Balance_Sheet!D41 -> 1.5623033 | F13: ='Profit Loss'!E20/Balance_Sheet!E41 -> 1.6050179 | G13: ='Profit Loss'!F20/Balance_Sheet!F41 -> 1.9760553 | I13: ='Ind_P&L'!B19/Ind_bala!B34 -> 0.23981 | J13: ='Ind_P&L'!C19/Ind_bala!C34 -> 0.30908322 | K13: ='Ind_P&L'!D19/Ind_bala!D34 -> 0.36296453 | L13: ='Ind_P&L'!E19/Ind_bala!E34 -> 0.36069469 | M13: ='Ind_P&L'!F19/Ind_bala!F34 -> 0.40857376
A14: EBIDTA Margin | B14: EBIDTA / Net Sales | C14: ='Profit Loss'!B25/'Profit Loss'!B4 -> 0.56604144 | D14: ='Profit Loss'!C25/'Profit Loss'!C4 -> 0.57233637 | E14: ='Profit Loss'!D25/'Profit Loss'!D4 -> 0.58524081 | F14: ='Profit Loss'!E25/'Profit Loss'!E4 -> 0.58996733 | G14: ='Profit Loss'!F25/'Profit Loss'!F4 -> 0.58504633 | I14: ='Ind_P&L'!B10/'Ind_P&L'!B3 -> 0.32045953 | J14: ='Ind_P&L'!C10/'Ind_P&L'!C3 -> 0.36421757 | K14: ='Ind_P&L'!D10/'Ind_P&L'!D3 -> 0.39368808 | L14: ='Ind_P&L'!E10/'Ind_P&L'!E3 -> 0.40252729 | M14: ='Ind_P&L'!F10/'Ind_P&L'!F3 -> 0.41526133
A15: EBIT Margin(%) | B15: PBIT/Net Sales | C15: ='Profit Loss'!B11/'Profit Loss'!B4 -> 0.52813542 | D15: ='Profit Loss'!C11/'Profit Loss'!C4 -> 0.53389112 | E15: ='Profit Loss'!D11/'Profit Loss'!D4 -> 0.55151324 | F15: ='Profit Loss'!E11/'Profit Loss'!E4 -> 0.55813212 | G15: ='Profit Loss'!F11/'Profit Loss'!F4 -> 0.55320055 | I15: ='Ind_P&L'!B17/'Ind_P&L'!B3 -> 0.31395964 | J15: ='Ind_P&L'!C17/'Ind_P&L'!C3 -> 0.35624447 | K15: ='Ind_P&L'!D17/'Ind_P&L'!D3 -> 0.37250476 | L15: ='Ind_P&L'!E17/'Ind_P&L'!E3 -> 0.38721178 | M15: ='Ind_P&L'!F17/'Ind_P&L'!F3 -> 0.40162615
A16: PAT Margin (%) (Net Profit Margin) | B16: PAT/Net Sales | C16: ='Profit Loss'!B20/'Profit Loss'!B4 -> 0.41899222 | D16: ='Profit Loss'!C20/'Profit Loss'!C4 -> 0.46001906 | E16: ='Profit Loss'!D20/'Profit Loss'!D4 -> 0.44655304 | F16: ='Profit Loss'!E20/'Profit Loss'!E4 -> 0.44605148 | G16: ='Profit Loss'!F20/'Profit Loss'!F4 -> 0.45705968 | I16: ='Ind_P&L'!B19/'Ind_P&L'!B3 -> 0.25146247 | J16: ='Ind_P&L'!C19/'Ind_P&L'!C3 -> 0.29643085 | K16: ='Ind_P&L'!D19/'Ind_P&L'!D3 -> 0.31707916 | L16: ='Ind_P&L'!E19/'Ind_P&L'!E3 -> 0.32242012 | M16: ='Ind_P&L'!F19/'Ind_P&L'!F3 -> 0.34237249
A17: ROA (%) | B17: PAT/Total Assets | C17: ='Profit Loss'!B20/Balance_Sheet!B18 -> 0.19089447 | D17: ='Profit Loss'!C20/Balance_Sheet!C18 -> 0.23061403 | E17: ='Profit Loss'!D20/Balance_Sheet!D18 -> 0.25643012 | F17: ='Profit Loss'!E20/Balance_Sheet!E18 -> 0.26373445 | G17: ='Profit Loss'!F20/Balance_Sheet!F18 -> 0.26775649 | I17: ='Ind_P&L'!B19/Ind_bala!B16 -> 0.090413029 | J17: ='Ind_P&L'!C19/Ind_bala!C16 -> 0.12887526 | K17: ='Ind_P&L'!D19/Ind_bala!D16 -> 0.15926644 | L17: ='Ind_P&L'!E19/Ind_bala!E16 -> 0.15650271 | M17: ='Ind_P&L'!F19/Ind_bala!F16 -> 0.17807197
A18: Growth Ratio
A19: Net Sales Growth(%) | B19: (Sales of Current Year - Sales of Previous Year)/Sales of Previous Year | D19: =('Profit Loss'!C4-'Profit Loss'!B4)/'Profit Loss'!B4 -> 0.2341677 | E19: =('Profit Loss'!D4-'Profit Loss'!C4)/'Profit Loss'!C4 -> 0.17755772 | F19: =('Profit Loss'!E4-'Profit Loss'!D4)/'Profit Loss'!D4 -> 0.12865944 | G19: =('Profit Loss'!F4-'Profit Loss'!E4)/'Profit Loss'!E4 -> 0.12228066 | J19: =('Ind_P&L'!C3-'Ind_P&L'!B3)/'Ind_P&L'!B3 -> 0.22947623 | K19: =('Ind_P&L'!D3-'Ind_P&L'!C3)/'Ind_P&L'!C3 -> 0.1274159 | L19: =('Ind_P&L'!E3-'Ind_P&L'!D3)/'Ind_P&L'!D3 -> 0.070545641 | M19: =('Ind_P&L'!F3-'Ind_P&L'!E3)/'Ind_P&L'!E3 -> 0.13257308
A20: Operating Profit Growth(%) | B20: (Current Op Profit - Previous Year Op Profit)/Previous Year Op Profit | D20: =('Profit Loss'!C11-'Profit Loss'!B11)/'Profit Loss'!B11 -> 0.24761787 | E20: =('Profit Loss'!D11-'Profit Loss'!C11)/'Profit Loss'!C11 -> 0.21642531 | F20: =('Profit Loss'!E11-'Profit Loss'!D11)/'Profit Loss'!D11 -> 0.14220483 | G20: =('Profit Loss'!F11-'Profit Loss'!E11)/'Profit Loss'!E11 -> 0.11236436 | J20: =('Ind_P&L'!C10-'Ind_P&L'!B10)/'Ind_P&L'!B10 -> 0.39735849 | K20: =('Ind_P&L'!D10-'Ind_P&L'!C10)/'Ind_P&L'!C10 -> 0.21864029 | L20: =('Ind_P&L'!E10-'Ind_P&L'!D10)/'Ind_P&L'!D10 -> 0.094581868 | M20: =('Ind_P&L'!F10-'Ind_P&L'!E10)/'Ind_P&L'!E10 -> 0.16840227
A21: PAT Growth(%) | B21: Growth in PAT | D21: =(Table1[[#This Row],[2021]]-Table1[[#This Row],[2020]])/Table1[[#This Row],[2020]] -> 0.3734375 | E21: =(Table1[[#This Row],[2022]]-Table1[[#This Row],[2021]])/Table1[[#This Row],[2021]] -> 0.16723549 | F21: =(Table1[[#This Row],[2023]]-Table1[[#This Row],[2022]])/Table1[[#This Row],[2022]] -> 0.15594542 | G21: =(Table1[[#This Row],[2024]]-Table1[[#This Row],[2023]])/Table1[[#This Row],[2023]] -> 0.17284992 | J21: =('Ind_P&L'!C19-'Ind_P&L'!B19)/'Ind_P&L'!B19 -> 0.44934027 | K21: =('Ind_P&L'!D19-'Ind_P&L'!C19)/'Ind_P&L'!C19 -> 0.20594762 | L21: =('Ind_P&L'!E19-'Ind_P&L'!D19)/'Ind_P&L'!D19 -> 0.088578209 | M21: =('Ind_P&L'!F19-'Ind_P&L'!E19)/'Ind_P&L'!E19 -> 0.20266022
A22: EPS Growth(%) | B22: Growth in EPS | D22: =('Profit Loss'!C23-'Profit Loss'!B23)/'Profit Loss'!B23 -> 0.37519623 | E22: =('Profit Loss'!D23-'Profit Loss'!C23)/'Profit Loss'!C23 -> 0.16666667 | F22: =('Profit Loss'!E20-'Profit Loss'!D20)/'Profit Loss'!D20 -> 0.12739174 | G22: =('Profit Loss'!F20-'Profit Loss'!E20)/'Profit Loss'!E20 -> 0.14997767 | J22: =J21 -> 0.44934027 | K22: =K21 -> 0.20594762 | L22: =L21 -> 0.088578209 | M22: =M21 -> 0.20266022
A23: Solvency Ratios/Capital Structure
A24: Total Debt/Equity(x) | B24: Total Debt/Total Equity | C24: =(Balance_Sheet!B28+Balance_Sheet!B25)/Balance_Sheet!B41 -> 1.9531443 | D24: =(Balance_Sheet!C28+Balance_Sheet!C25)/Balance_Sheet!C41 -> 1.882839 | E24: =(Balance_Sheet!D28+Balance_Sheet!D25)/Balance_Sheet!D41 -> 2.2062618 | F24: =(Balance_Sheet!E28+Balance_Sheet!E25)/Balance_Sheet!E41 -> 2.248172 | G24: =(Balance_Sheet!F28+Balance_Sheet!F25)/Balance_Sheet!F41 -> 2.7975441 | I24: =(Ind_bala!B24+Ind_bala!B21)/Ind_bala!B34 -> 0.64539171 | J24: =(Ind_bala!C24+Ind_bala!C21)/Ind_bala!C34 -> 0.63801093 | K24: =(Ind_bala!D24+Ind_bala!D21)/Ind_bala!D34 -> 0.65992984 | L24: =(Ind_bala!E24+Ind_bala!E21)/Ind_bala!E34 -> 0.63083252 | M24: =(Ind_bala!F24+Ind_bala!F21)/Ind_bala!F34 -> 0.67499034
A25: Interest Cover(x) (Times Interest Earned) | B25: EBIT/Interest | C25: ='Profit Loss'!B11/ABS('Profit Loss'!B15) -> 21.265789 | D25: ='Profit Loss'!C11/ABS('Profit Loss'!C15) -> 23.392111 | E25: ='Profit Loss'!D11/ABS('Profit Loss'!D15) -> 26.038217 | F25: ='Profit Loss'!E11/ABS('Profit Loss'!E15) -> 24.361739 | G25: ='Profit Loss'!F11/ABS('Profit Loss'!F15) -> 24.120743 | I25: =-'Ind_P&L'!B10/'Ind_P&L'!B14 -> 11.680441 | J25: =-'Ind_P&L'!C10/'Ind_P&L'!C14 -> 14.43313 | K25: =-'Ind_P&L'!D10/'Ind_P&L'!D14 -> 16.921022 | L25: =-'Ind_P&L'!E10/'Ind_P&L'!E14 -> 16.666175 | M25: =-'Ind_P&L'!F10/'Ind_P&L'!F14 -> 18.310529
A26: Total Debt Ratio | B26: Debt/(Debt+Equity) | C26: =(Balance_Sheet!B28+Balance_Sheet!B25)/((Balance_Sheet!B28+Balance_Sheet!B25)+Balance_Sheet!B41) -> 0.66137787 | D26: =(Balance_Sheet!C28+Balance_Sheet!C25)/((Balance_Sheet!C28+Balance_Sheet!C25)+Balance_Sheet!C41) -> 0.65311971 | E26: =(Balance_Sheet!D28+Balance_Sheet!D25)/((Balance_Sheet!D28+Balance_Sheet!D25)+Balance_Sheet!D41) -> 0.68811031 | F26: =(Balance_Sheet!E28+Balance_Sheet!E25)/((Balance_Sheet!E28+Balance_Sheet!E25)+Balance_Sheet!E41) -> 0.69213453 | G26: =(Balance_Sheet!F28+Balance_Sheet!F25)/((Balance_Sheet!F28+Balance_Sheet!F25)+Balance_Sheet!F41) -> 0.73667192 | I26: =(Ind_bala!B24+Ind_bala!B21)/((Ind_bala!B24+Ind_bala!B21)+Ind_bala!B34) -> 0.39224198 | J26: =(Ind_bala!C24+Ind_bala!C21)/((Ind_bala!C24+Ind_bala!C21)+Ind_bala!C34) -> 0.38950347 | K26: =(Ind_bala!D24+Ind_bala!D21)/((Ind_bala!D24+Ind_bala!D21)+Ind_bala!D34) -> 0.3975649 | L26: =(Ind_bala!E24+Ind_bala!E21)/((Ind_bala!E24+Ind_bala!E21)+Ind_bala!E34) -> 0.38681625 | M26: =(Ind_bala!F24+Ind_bala!F21)/((Ind_bala!F24+Ind_bala!F21)+Ind_bala!F34) -> 0.40298163
A27: Du Pont Analysis
A28: PAT / Sales | B28: Net Profit margin | C28: ='Profit Loss'!B20/'Profit Loss'!B4 -> 0.41899222 | D28: ='Profit Loss'!C20/'Profit Loss'!C4 -> 0.46001906 | E28: ='Profit Loss'!D20/'Profit Loss'!D4 -> 0.44655304 | F28: ='Profit Loss'!E20/'Profit Loss'!E4 -> 0.44605148 | G28: ='Profit Loss'!F20/'Profit Loss'!F4 -> 0.45705968 | I28: =I16 -> 0.25146247 | J28: =J16 -> 0.29643085 | K28: =K16 -> 0.31707916 | L28: =L16 -> 0.32242012 | M28: =M16 -> 0.34237249
A29: Total Asset Turnover | B29: Sales / Total Assets | C29: ='Profit Loss'!B4/Balance_Sheet!B18 -> 0.45560386 | D29: ='Profit Loss'!C4/Balance_Sheet!C18 -> 0.50131408 | E29: ='Profit Loss'!D4/Balance_Sheet!D18 -> 0.57424336 | F29: ='Profit Loss'!E4/Balance_Sheet!E18 -> 0.59126461 | G29: ='Profit Loss'!F4/Balance_Sheet!F18 -> 0.58582392 | I29: ='Ind_P&L'!B3/Ind_bala!B16 -> 0.35954879 | J29: ='Ind_P&L'!C3/Ind_bala!C16 -> 0.43475658 | K29: ='Ind_P&L'!D3/Ind_bala!D16 -> 0.50229237 | L29: ='Ind_P&L'!E3/Ind_bala!E16 -> 0.48539995 | M29: ='Ind_P&L'!F3/Ind_bala!F16 -> 0.5201118
A30: Assets/Equity | B30: Equity Multiplier | C30: =Balance_Sheet!B18/Balance_Sheet!B41 -> 5.1763255 | D30: =Balance_Sheet!C18/Balance_Sheet!C41 -> 5.1021265 | E30: =Balance_Sheet!D18/Balance_Sheet!D41 -> 6.092511 | F30: =Balance_Sheet!E18/Balance_Sheet!E41 -> 6.0857348 | G30: =Balance_Sheet!F18/Balance_Sheet!F41 -> 7.380046 | I30: =Ind_bala!B16/Ind_bala!B34 -> 2.6523833 | J30: =Ind_bala!C16/Ind_bala!C34 -> 2.398313 | K30: =Ind_bala!D16/Ind_bala!D34 -> 2.2789769 | L30: =Ind_bala!E16/Ind_bala!E34 -> 2.3047184 | M30: =Ind_bala!F16/Ind_bala!F34 -> 2.2944305
A31: ROE (%) | C31: =PRODUCT(C28:C30) -> 0.98813194 | D31: =PRODUCT(D28:D30) -> 1.176622 | E31: =PRODUCT(E28:E30) -> 1.5623033 | F31: =PRODUCT(F28:F30) -> 1.6050179 | G31: =PRODUCT(G28:G30) -> 1.9760553 | I31: =PRODUCT(I28:I30) -> 0.23981 | J31: =PRODUCT(J28:J30) -> 0.30908322 | K31: =PRODUCT(K28:K30) -> 0.36296453 | L31: =PRODUCT(L28:L30) -> 0.36069469 | M31: =AVERAGE(Table39[[#This Row],[Column9]:[Column12]]) -> 0.31813811
A32: Extended Dupont
A33: Tax Ratio | B33: PAT / PBT | C33: ='Profit Loss'!B20/'Profit Loss'!B18 -> 0.82615979 | D33: ='Profit Loss'!C20/'Profit Loss'!C18 -> 0.84282526 | E33: ='Profit Loss'!D20/'Profit Loss'!D18 -> 0.846403 | F33: ='Profit Loss'!E20/'Profit Loss'!E18 -> 0.82080798 | G33: ='Profit Loss'!F20/'Profit Loss'!F18 -> 0.84397535 | I33: ='Ind_P&L'!B19/'Ind_P&L'!B17 -> 0.80093885 | J33: ='Ind_P&L'!C19/'Ind_P&L'!C17 -> 0.83209953 | K33: ='Ind_P&L'!D19/'Ind_P&L'!D17 -> 0.85120834 | L33: ='Ind_P&L'!E19/'Ind_P&L'!E17 -> 0.83267126 | M33: ='Ind_P&L'!F19/'Ind_P&L'!F17 -> 0.85246562
A34: Financial Leverage | B34: PBT / EBIT | C34: ='Profit Loss'!B20/'Profit Loss'!B11 -> 0.79334241 | D34: ='Profit Loss'!C20/'Profit Loss'!C11 -> 0.8616346 | E34: ='Profit Loss'!D20/'Profit Loss'!D11 -> 0.80968689 | F34: ='Profit Loss'!E20/'Profit Loss'!E11 -> 0.79918618 | G34: ='Profit Loss'!F20/'Profit Loss'!F11 -> 0.82620973 | I34: ='Ind_P&L'!B19/'Ind_P&L'!B10 -> 0.7846934 | J34: ='Ind_P&L'!C19/'Ind_P&L'!C10 -> 0.81388401 | K34: ='Ind_P&L'!D19/'Ind_P&L'!D10 -> 0.80540705 | L34: ='Ind_P&L'!E19/'Ind_P&L'!E10 -> 0.80098949 | M34: ='Ind_P&L'!F19/'Ind_P&L'!F10 -> 0.82447477
A35: OPM | B35: EBIT / Net Sales | C35: ='Profit Loss'!B25/'Profit Loss'!B4 -> 0.56604144 | D35: ='Profit Loss'!C25/'Profit Loss'!C4 -> 0.57233637 | E35: ='Profit Loss'!D25/'Profit Loss'!D4 -> 0.58524081 | F35: ='Profit Loss'!E25/'Profit Loss'!E4 -> 0.58996733 | G35: ='Profit Loss'!F25/'Profit Loss'!F4 -> 0.58504633 | I35: =I14 -> 0.32045953 | J35: =J14 -> 0.36421757 | K35: =K14 -> 0.39368808 | L35: =L14 -> 0.40252729 | M35: =M14 -> 0.41526133
A36: Total Asset Turnover | B36: Sales / Total Assets | C36: ='Profit Loss'!B4/Balance_Sheet!B18 -> 0.45560386 | D36: ='Profit Loss'!C4/Balance_Sheet!C18 -> 0.50131408 | E36: ='Profit Loss'!D4/Balance_Sheet!D18 -> 0.57424336 | F36: ='Profit Loss'!E4/Balance_Sheet!E18 -> 0.59126461 | G36: ='Profit Loss'!F4/Balance_Sheet!F18 -> 0.58582392 | I36: ='Ind_P&L'!B3/Ind_bala!B16 -> 0.35954879 | J36: ='Ind_P&L'!C3/Ind_bala!C16 -> 0.43475658 | K36: ='Ind_P&L'!D3/Ind_bala!D16 -> 0.50229237 | L36: ='Ind_P&L'!E3/Ind_bala!E16 -> 0.48539995 | M36: ='Ind_P&L'!F3/Ind_bala!F16 -> 0.5201118
A37: Leverage | B37: Total Assets / Networth | C37: =Balance_Sheet!B18/Balance_Sheet!B41 -> 5.1763255 | D37: =Balance_Sheet!C18/Balance_Sheet!C41 -> 5.1021265 | E37: =Balance_Sheet!D18/Balance_Sheet!D41 -> 6.092511 | F37: =Balance_Sheet!E18/Balance_Sheet!E41 -> 6.0857348 | G37: =Balance_Sheet!F18/Balance_Sheet!F41 -> 7.380046 | I37: =Ind_bala!B16/Ind_bala!B34 -> 2.6523833 | J37: =Ind_bala!C16/Ind_bala!C34 -> 2.398313 | K37: =Ind_bala!D16/Ind_bala!D34 -> 2.2789769 | L37: =Ind_bala!E16/Ind_bala!E34 -> 2.3047184 | M37: =Ind_bala!F16/Ind_bala!F34 -> 2.2944305
A38: ROE | C38: =PRODUCT(C33:C37) -> 0.87494736 | D38: =PRODUCT(D33:D37) -> 1.0630976 | E38: =PRODUCT(E33:E37) -> 1.4032053 | F38: =PRODUCT(F33:F37) -> 1.3925551 | G38: =PRODUCT(G33:G37) -> 1.7637479 | I38: =PRODUCT(I33:I37) -> 0.19207315 | J38: =PRODUCT(J33:J37) -> 0.257188 | K38: =PRODUCT(K33:K37) -> 0.30895844 | L38: =PRODUCT(L33:L37) -> 0.3003401 | M38: =AVERAGE(Table39[[#This Row],[Column9]:[Column12]]) -> 0.26463992
A40: Credit Ratios
A41: Operating Margin | B41: Operating Income / Sales | C41: ='Profit Loss'!B11/'Profit Loss'!B4 -> 0.52813542 | D41: ='Profit Loss'!C11/'Profit Loss'!C4 -> 0.53389112 | E41: ='Profit Loss'!D11/'Profit Loss'!D4 -> 0.55151324 | F41: ='Profit Loss'!E11/'Profit Loss'!E4 -> 0.55813212 | G41: ='Profit Loss'!F11/'Profit Loss'!F4 -> 0.55320055 | I41: ='Ind_P&L'!B10/'Ind_P&L'!B3 -> 0.32045953 | J41: ='Ind_P&L'!C10/'Ind_P&L'!C3 -> 0.36421757 | K41: ='Ind_P&L'!D10/'Ind_P&L'!D3 -> 0.39368808 | L41: ='Ind_P&L'!E10/'Ind_P&L'!E3 -> 0.40252729 | M41: ='Ind_P&L'!F10/'Ind_P&L'!F3 -> 0.41526133
A42: Debt to Capital | B42: Total Debt / (Total Debt + networth) | C42: =(Balance_Sheet!B28+Balance_Sheet!B25)/((Balance_Sheet!B28+Balance_Sheet!B25)+Balance_Sheet!B41) -> 0.66137787 | D42: =(Balance_Sheet!C28+Balance_Sheet!C25)/((Balance_Sheet!C28+Balance_Sheet!C25)+Balance_Sheet!C41) -> 0.65311971 | E42: =(Balance_Sheet!D28+Balance_Sheet!D25)/((Balance_Sheet!D28+Balance_Sheet!D25)+Balance_Sheet!D41) -> 0.68811031 | F42: =(Balance_Sheet!E28+Balance_Sheet!E25)/((Balance_Sheet!E28+Balance_Sheet!E25)+Balance_Sheet!E41) -> 0.69213453 | G42: =(Balance_Sheet!F28+Balance_Sheet!F25)/((Balance_Sheet!F28+Balance_Sheet!F25)+Balance_Sheet!F41) -> 0.73667192 | I42: =(Ind_bala!B24+Ind_bala!B21)/((Ind_bala!B24+Ind_bala!B21)+Ind_bala!B34) -> 0.39224198 | J42: =(Ind_bala!C24+Ind_bala!C21)/((Ind_bala!C24+Ind_bala!C21)+Ind_bala!C34) -> 0.38950347 | K42: =(Ind_bala!D24+Ind_bala!D21)/((Ind_bala!D24+Ind_bala!D21)+Ind_bala!D34) -> 0.3975649 | L42: =(Ind_bala!E24+Ind_bala!E21)/((Ind_bala!E24+Ind_bala!E21)+Ind_bala!E34) -> 0.38681625 | M42: =(Ind_bala!F24+Ind_bala!F21)/((Ind_bala!F24+Ind_bala!F21)+Ind_bala!F34) -> 0.40298163
A43: Debt to EBITDA | B43: Debt / EBITDA | C43: =(Balance_Sheet!B28+Balance_Sheet!B25)/'Profit Loss'!B25 -> 1.4631105 | D43: =(Balance_Sheet!C28+Balance_Sheet!C25)/'Profit Loss'!C25 -> 1.2861769 | E43: =(Balance_Sheet!D28+Balance_Sheet!D25)/'Profit Loss'!D25 -> 1.0775319 | F43: =(Balance_Sheet!E28+Balance_Sheet!E25)/'Profit Loss'!E25 -> 1.0590261 | G43: =(Balance_Sheet!F28+Balance_Sheet!F25)/'Profit Loss'!F25 -> 1.1060137 | I43: =(Ind_bala!B24+Ind_bala!B21)/'Ind_P&L'!B22 -> 1.9603083 | J43: =(Ind_bala!C24+Ind_bala!C21)/'Ind_P&L'!C22 -> 1.5836131 | K43: =(Ind_bala!D24+Ind_bala!D21)/'Ind_P&L'!D22 -> 1.3939722 | L43: =(Ind_bala!E24+Ind_bala!E21)/'Ind_P&L'!E22 -> 1.3365163 | M43: =(Ind_bala!F24+Ind_bala!F21)/'Ind_P&L'!F22 -> 1.3040571
A44: EBITDA/ Debt | B44: EBITDA / Total Debt | C44: ='Cash Flow'!B24/(Balance_Sheet!B28+Balance_Sheet!B25) -> 0.57007576 | D44: ='Cash Flow'!C24/(Balance_Sheet!C28+Balance_Sheet!C25) -> 0.68074239 | E44: ='Cash Flow'!D24/(Balance_Sheet!D28+Balance_Sheet!D25) -> 0.79833131 | F44: ='Cash Flow'!E24/(Balance_Sheet!E28+Balance_Sheet!E25) -> 0.76398189 | G44: ='Cash Flow'!F24/(Balance_Sheet!F28+Balance_Sheet!F25) -> 0.81092944 | I44: =Ind_Cashflow!B11/(Ind_bala!B24+Ind_bala!B21) -> 0.49547135 | J44: =Ind_Cashflow!C11/(Ind_bala!C24+Ind_bala!C21) -> 0.63454158 | K44: =Ind_Cashflow!D11/(Ind_bala!D24+Ind_bala!D21) -> 0.71596519 | L44: =Ind_Cashflow!E11/(Ind_bala!E24+Ind_bala!E21) -> 0.75539458 | M44: =Ind_Cashflow!F11/(Ind_bala!F24+Ind_bala!F21) -> 0.77645001
A45: Coverage Ratios
B46: EBIDTA / Interest Expense | C46: ='Profit Loss'!B25/ABS('Profit Loss'!B15) -> 22.792105 | D46: ='Profit Loss'!C25/ABS('Profit Loss'!C15) -> 25.076566 | E46: ='Profit Loss'!D25/ABS('Profit Loss'!D15) -> 27.630573 | F46: ='Profit Loss'!E25/ABS('Profit Loss'!E15) -> 25.751304 | G46: ='Profit Loss'!F25/ABS('Profit Loss'!F15) -> 25.509288 | I46: =Table39[[#This Row],[Column3]] -> 22.792105 | J46: =Table39[[#This Row],[Column4]] -> 25.076566 | K46: =Table39[[#This Row],[Column5]] -> 27.630573 | L46: =Table39[[#This Row],[Column6]] -> 25.751304 | M46: =Table39[[#This Row],[Column7]] -> 25.509288
B47: EBIT / Interest Expense | C47: ='Profit Loss'!B11/ABS('Profit Loss'!B15) -> 21.265789 | D47: ='Profit Loss'!C11/ABS('Profit Loss'!C15) -> 23.392111 | E47: ='Profit Loss'!D11/ABS('Profit Loss'!D15) -> 26.038217 | F47: ='Profit Loss'!E11/ABS('Profit Loss'!E15) -> 24.361739 | G47: ='Profit Loss'!F11/ABS('Profit Loss'!F15) -> 24.120743 | I47: ='Ind_P&L'!B10/ABS('Ind_P&L'!B14) -> 11.680441 | J47: ='Ind_P&L'!C10/ABS('Ind_P&L'!C14) -> 14.43313 | K47: ='Ind_P&L'!D10/ABS('Ind_P&L'!D14) -> 16.921022 | L47: ='Ind_P&L'!E10/ABS('Ind_P&L'!E14) -> 16.666175 | M47: ='Ind_P&L'!F10/ABS('Ind_P&L'!F14) -> 18.310529
A49: Valuation Ratios
A50: Market Price | B50: 430
A51: Market Capitalization | C51: =B50*'Profit Loss'!B22 -> 430860 | D51: =B50*'Profit Loss'!C22 -> 424840 | E51: =B50*'Profit Loss'!D22 -> 416240 | F51: =B50*'Profit Loss'!E22 -> 405920 | G51: =B50*'Profit Loss'!F22 -> 397750 | I51: =B50*'Ind_P&L'!B22 -> 19641110 | J51: =B50*'Ind_P&L'!C22 -> 27027650 | K51: =B50*'Ind_P&L'!D22 -> 32614640 | L51: =B50*'Ind_P&L'!E22 -> 35619910 | M51: =B50*'Ind_P&L'!F22 -> 41473070
A52: P/E | B52: Price Per Share/EPS | C52: =B50/'Profit Loss'!B23 -> 67.503925 | D52: =B50/'Profit Loss'!C23 -> 49.086758 | E52: =B50/'Profit Loss'!D23 -> 42.074364 | F52: =B50/'Profit Loss'!E23 -> 36.348267 | G52: =B50/'Profit Loss'!F23 -> 30.957523 | I52: =B50/'Ind_P&L'!B21 -> 104.87805 | J52: =B50/'Ind_P&L'!C21 -> 71.666667 | K52: =B50/'Ind_P&L'!D21 -> 59.722222 | L52: =B50/'Ind_P&L'!E21 -> 51.807229 | M52: =B50/'Ind_P&L'!F21 -> 43.877551
A53: Price to Book Value | B53: Market Cap / Shareholders Equity | C53: =C51/Balance_Sheet!B41 -> 66.408755 | D53: =D51/Balance_Sheet!C41 -> 57.543004 | E53: =E51/Balance_Sheet!D41 -> 65.487728 | F53: =F51/Balance_Sheet!E41 -> 58.196416 | G53: =G51/Balance_Sheet!F41 -> 61.05142 | I53: =I51/Ind_bala!B34 -> 141.56877 | J53: =J51/Ind_bala!C34 -> 173.23973 | K53: =K51/Ind_bala!D34 -> 203.56923 | L53: =L51/Ind_bala!E34 -> 202.95898 | M53: =M51/Ind_bala!F34 -> 222.57143
A54: Price to Sales | B54: Market Cap / Revenue | C54: =C51/'Profit Loss'!B4 -> 28.158944 | D54: =D51/'Profit Loss'!C4 -> 22.497352 | E54: =E51/'Profit Loss'!D4 -> 18.718352 | F54: =F51/'Profit Loss'!E4 -> 16.1734 | G54: =G51/'Profit Loss'!F4 -> 14.121135 | I54: =I51/'Ind_P&L'!B3 -> 148.44766 | J54: =J51/'Ind_P&L'!C3 -> 166.14814 | K54: =K51/'Ind_P&L'!D3 -> 177.83434 | L54: =L51/'Ind_P&L'!E3 -> 181.4223 | M54: =M51/'Ind_P&L'!F3 -> 186.50814
A55: Enterprise Value
A56: MV of Debt | C56: =Balance_Sheet!B28+Balance_Sheet!B25 -> 12672 | D56: =Balance_Sheet!C28+Balance_Sheet!C25 -> 13901 | E56: =Balance_Sheet!D28+Balance_Sheet!D25 -> 14023 | F56: =Balance_Sheet!E28+Balance_Sheet!E25 -> 15681 | G56: =Balance_Sheet!F28+Balance_Sheet!F25 -> 18226 | I56: =Ind_bala!B24+Ind_bala!B21 -> 89541 | J56: =Ind_bala!C24+Ind_bala!C21 -> 99538 | K56: =Ind_bala!D24+Ind_bala!D21 -> 105730 | L56: =Ind_bala!E24+Ind_bala!E21 -> 110713 | M56: =Ind_bala!F24+Ind_bala!F21 -> 125775
A57: MV of Equity | C57: =C51 -> 430860 | D57: =D51 -> 424840 | E57: =E51 -> 416240 | F57: =F51 -> 405920 | G57: =G51 -> 397750 | I57: =I51 -> 19641110 | J57: =J51 -> 27027650 | K57: =K51 -> 32614640 | L57: =L51 -> 35619910 | M57: =M51 -> 41473070
A58: Cash | C58: =Balance_Sheet!B4 -> 10113 | D58: =Balance_Sheet!C4 -> 7421 | E58: =Balance_Sheet!D4 -> 7008 | F58: =Balance_Sheet!E4 -> 8588 | G58: =Balance_Sheet!F4 -> 8442 | I58: =Ind_bala!B4 -> 69864 | J58: =Ind_bala!C4 -> 93017 | K58: =Ind_bala!D4 -> 120397 | L58: =Ind_bala!E4 -> 146313 | M58: =Ind_bala!F4 -> 178016
A59: Investments | C59: =Balance_Sheet!B6 -> 483 | D59: =Balance_Sheet!C6 -> 473 | E59: =Balance_Sheet!D6 -> 400 | F59: =Balance_Sheet!E6 -> 1845 | G59: =Balance_Sheet!F6 -> 1874 | I59: =Ind_bala!B6 -> 30499 | J59: =Ind_bala!C6 -> 15353 | K59: =Ind_bala!D6 -> 9476 | L59: =Ind_bala!E6 -> 12801 | M59: =Ind_bala!F6 -> 12833
A60: MVA or Enterprise Value | C60: =C51+C56-C58 -> 433419 | D60: =D51+D56-D58 -> 431320 | E60: =E51+E56-E58 -> 423255 | F60: =F51+F56-F58 -> 413013 | G60: =G51+G56-G58 -> 407534 | I60: =I51+I56-I58 -> 19660787 | J60: =J51+J56-J58 -> 27034171 | K60: =K51+K56-K58 -> 32599973 | L60: =L51+L56-L58 -> 35584310 | M60: =M51+M56-M58 -> 41420829
A61: EV/EBIDTA | C61: =C60/'Profit Loss'!B25 -> 50.042605 | D61: =D60/'Profit Loss'!C25 -> 39.907476 | E61: =E60/'Profit Loss'!D25 -> 32.523052 | F61: =F60/'Profit Loss'!E25 -> 27.893091 | G61: =G60/'Profit Loss'!F25 -> 24.730505 | I61: =I60/Ind_bala!B22 -> 1169.6583 | J61: =J60/Ind_bala!C22 -> 1465.9818 | K61: =K60/Ind_bala!D22 -> 1728.6162 | L61: =L60/Ind_bala!E22 -> 1770.8923 | M61: =M60/Ind_bala!F22 -> 1802.2377
A62: EV/EBIT | C62: =C60/'Profit Loss'!B11 -> 53.634327 | D62: =D60/'Profit Loss'!C11 -> 42.781194 | E62: =E60/'Profit Loss'!D11 -> 34.511986 | F62: =F60/'Profit Loss'!E11 -> 29.484081 | G62: =G60/'Profit Loss'!F11 -> 26.154152 | I62: =I60/Ind_bala!B10 -> 117.63206 | J62: =J60/Ind_bala!C10 -> 174.43989 | K62: =K60/Ind_bala!D10 -> 218.72717 | L62: =L60/Ind_bala!E10 -> 203.16825 | M62: =M60/Ind_bala!F10 -> 236.17222
A63: Solvency Ratios/Capital Structure
A64: Total Debt/Equity(x) | B64: Total Debt / Total Equity | C64: =(Balance_Sheet!B28+Balance_Sheet!B25)/Balance_Sheet!B41 -> 1.9531443 | D64: =(Balance_Sheet!C28+Balance_Sheet!C25)/Balance_Sheet!C41 -> 1.882839 | E64: =(Balance_Sheet!D28+Balance_Sheet!D25)/Balance_Sheet!D41 -> 2.2062618 | F64: =(Balance_Sheet!E28+Balance_Sheet!E25)/Balance_Sheet!E41 -> 2.248172 | G64: =(Balance_Sheet!F28+Balance_Sheet!F25)/Balance_Sheet!F41 -> 2.7975441 | I64: =(Ind_bala!B24+Ind_bala!B21)/Ind_bala!B34 -> 0.64539171 | J64: =(Ind_bala!C24+Ind_bala!C21)/Ind_bala!C34 -> 0.63801093 | K64: =(Ind_bala!D24+Ind_bala!D21)/Ind_bala!D34 -> 0.65992984 | L64: =(Ind_bala!E24+Ind_bala!E21)/Ind_bala!E34 -> 0.63083252 | M64: =(Ind_bala!F24+Ind_bala!F21)/Ind_bala!F34 -> 0.67499034
A65: Interest Cover(x) (Times Interest Earned) | B65: EBIT/Interest | C65: ='Profit Loss'!B11/ABS('Profit Loss'!B15) -> 21.265789 | D65: ='Profit Loss'!C11/ABS('Profit Loss'!C15) -> 23.392111 | E65: ='Profit Loss'!D11/ABS('Profit Loss'!D15) -> 26.038217 | F65: ='Profit Loss'!E11/ABS('Profit Loss'!E15) -> 24.361739 | G65: ='Profit Loss'!F11/ABS('Profit Loss'!F15) -> 24.120743 | I65: ='Ind_P&L'!B10/ABS('Ind_P&L'!B14) -> 11.680441 | J65: ='Ind_P&L'!C10/ABS('Ind_P&L'!C14) -> 14.43313 | K65: ='Ind_P&L'!D10/ABS('Ind_P&L'!D14) -> 16.921022 | L65: ='Ind_P&L'!E10/ABS('Ind_P&L'!E14) -> 16.666175 | M65: ='Ind_P&L'!F10/ABS('Ind_P&L'!F14) -> 18.310529
A66: Total Debt Ratio | B66: Debt/(Debt+Equity) | C66: =(Balance_Sheet!B28+Balance_Sheet!B25)/((Balance_Sheet!B28+Balance_Sheet!B25)+Balance_Sheet!B41) -> 0.66137787 | D66: =(Balance_Sheet!C28+Balance_Sheet!C25)/((Balance_Sheet!C28+Balance_Sheet!C25)+Balance_Sheet!C41) -> 0.65311971 | E66: =(Balance_Sheet!D28+Balance_Sheet!D25)/((Balance_Sheet!D28+Balance_Sheet!D25)+Balance_Sheet!D41) -> 0.68811031 | F66: =(Balance_Sheet!E28+Balance_Sheet!E25)/((Balance_Sheet!E28+Balance_Sheet!E25)+Balance_Sheet!E41) -> 0.69213453 | G66: =(Balance_Sheet!F28+Balance_Sheet!F25)/((Balance_Sheet!F28+Balance_Sheet!F25)+Balance_Sheet!F41) -> 0.73667192 | I66: =(Ind_bala!B24+Ind_bala!B21)/((Ind_bala!B24+Ind_bala!B21)+Ind_bala!B34) -> 0.39224198 | J66: =(Ind_bala!C24+Ind_bala!C21)/((Ind_bala!C24+Ind_bala!C21)+Ind_bala!C34) -> 0.38950347 | K66: =(Ind_bala!D24+Ind_bala!D21)/((Ind_bala!D24+Ind_bala!D21)+Ind_bala!D34) -> 0.3975649 | L66: =(Ind_bala!E24+Ind_bala!E21)/((Ind_bala!E24+Ind_bala!E21)+Ind_bala!E34) -> 0.38681625 | M66: =(Ind_bala!F24+Ind_bala!F21)/((Ind_bala!F24+Ind_bala!F21)+Ind_bala!F34) -> 0.40298163
A67: Financial Leverage | B67: % Change in PAT/% Change in EBIT | C67: ='Profit Loss'!B20/'Profit Loss'!B11 -> 0.79334241 | D67: ='Profit Loss'!C20/'Profit Loss'!C11 -> 0.8616346 | E67: ='Profit Loss'!D20/'Profit Loss'!D11 -> 0.80968689 | F67: ='Profit Loss'!E20/'Profit Loss'!E11 -> 0.79918618 | G67: ='Profit Loss'!F20/'Profit Loss'!F11 -> 0.82620973 | I67: ='Ind_P&L'!B19/'Ind_P&L'!B10 -> 0.7846934 | J67: ='Ind_P&L'!C19/'Ind_P&L'!C10 -> 0.81388401 | K67: ='Ind_P&L'!D19/'Ind_P&L'!D10 -> 0.80540705 | L67: ='Ind_P&L'!E19/'Ind_P&L'!E10 -> 0.80098949 | M67: ='Ind_P&L'!F19/'Ind_P&L'!F10 -> 0.82447477
A69: Liquidity Ratios
A70: Current Ratio | B70: Current Assets/Current Liabilities | C70: =Balance_Sheet!B11/Balance_Sheet!B27 -> 1.6133198 | D70: =Balance_Sheet!C11/Balance_Sheet!C27 -> 1.2877222 | E70: =Balance_Sheet!D11/Balance_Sheet!D27 -> 1.1718298 | F70: =Balance_Sheet!E11/Balance_Sheet!E27 -> 1.1658264 | G70: =Balance_Sheet!F11/Balance_Sheet!F27 -> 1.0262227 | I70: =Ind_bala!B10/Ind_bala!B23 -> 2.2456032 | J70: =Ind_bala!C10/Ind_bala!C23 -> 1.8379843 | K70: =Ind_bala!D10/Ind_bala!D23 -> 1.6707845 | L70: =Ind_bala!E10/Ind_bala!E23 -> 1.7726891 | M70: =Ind_bala!F10/Ind_bala!F23 -> 1.6000438
A71: Quick Ratio (Acid Test) | B71: (CA-Inventory-Prepaid)/Current Liabilities | C71: =(Balance_Sheet!B11-Balance_Sheet!B10)/Balance_Sheet!B27 -> 1.4543766 | D71: =(Balance_Sheet!C11-Balance_Sheet!C10)/Balance_Sheet!C27 -> 1.1151801 | E71: =(Balance_Sheet!D11-Balance_Sheet!D10)/Balance_Sheet!D27 -> 1.0062804 | F71: =(Balance_Sheet!E11-Balance_Sheet!E10)/Balance_Sheet!E27 -> 1.0052878 | G71: =(Balance_Sheet!F11-Balance_Sheet!F10)/Balance_Sheet!F27 -> 0.87055151 | I71: =(Ind_bala!B10-Ind_bala!B9)/Ind_bala!B23 -> 2.0965081 | J71: =(Ind_bala!C10-Ind_bala!C9)/Ind_bala!C23 -> 1.6889313 | K71: =(Ind_bala!D10-Ind_bala!D9)/Ind_bala!D23 -> 1.5303119 | L71: =(Ind_bala!E10-Ind_bala!E9)/Ind_bala!E23 -> 1.6350617 | M71: =(Ind_bala!F10-Ind_bala!F9)/Ind_bala!F23 -> 1.4597307
A72: Cash Ratio | B72: Cash Ratio/Current Liabilities | C72: =Balance_Sheet!B4/Balance_Sheet!B27 -> 0.85363383 | D72: =Balance_Sheet!C4/Balance_Sheet!C27 -> 0.56382009 | E72: =Balance_Sheet!D4/Balance_Sheet!D27 -> 0.49453108 | F72: =Balance_Sheet!E4/Balance_Sheet!E27 -> 0.52803738 | G72: =Balance_Sheet!F4/Balance_Sheet!F27 -> 0.43922997 | I72: =Ind_bala!B4/Ind_bala!B23 -> 0.93866638 | J72: =Ind_bala!C4/Ind_bala!C23 -> 1.1031559 | K72: =Ind_bala!D4/Ind_bala!D23 -> 1.3496514 | L72: =Ind_bala!E4/Ind_bala!E23 -> 1.4808558 | M72: =Ind_bala!F4/Ind_bala!F23 -> 1.6240558
A73: Operating Cash Flow to Total Debt | B73: CFO/Total Debt | C73: ='Cash Flow'!B24/(Balance_Sheet!B28+Balance_Sheet!B25) -> 0.57007576 | D73: ='Cash Flow'!C24/(Balance_Sheet!C28+Balance_Sheet!C25) -> 0.68074239 | E73: ='Cash Flow'!D24/(Balance_Sheet!D28+Balance_Sheet!D25) -> 0.79833131 | F73: ='Cash Flow'!E24/(Balance_Sheet!E28+Balance_Sheet!E25) -> 0.76398189 | G73: ='Cash Flow'!F24/(Balance_Sheet!F28+Balance_Sheet!F25) -> 0.81092944 | I73: =Ind_Cashflow!B11/(Ind_bala!B24+Ind_bala!B21) -> 0.49547135 | J73: =Ind_Cashflow!C11/(Ind_bala!C24+Ind_bala!C21) -> 0.63454158 | K73: =Ind_Cashflow!D11/(Ind_bala!D24+Ind_bala!D21) -> 0.71596519 | L73: =Ind_Cashflow!E11/(Ind_bala!E24+Ind_bala!E21) -> 0.75539458 | M73: =Ind_Cashflow!F11/(Ind_bala!F24+Ind_bala!F21) -> 0.77645001
B78: PAT / Sales | C78: 2020 | D78: 2021 | E78: 2022 | F78: 2023 | G78: 2024
B79: Company | C79: =VLOOKUP($B$78,$A$3:$G$74,3,FALSE) -> 0.41899222 | D79: =VLOOKUP($B$78,$A$3:$G$74,4,FALSE) -> 0.46001906 | E79: =VLOOKUP($B$78,$A$3:$G$74,5,FALSE) -> 0.44655304 | F79: =VLOOKUP($B$78,$A$3:$G$74,6,FALSE) -> 0.44605148 | G79: =VLOOKUP($B$78,$A$3:$G$74,7,FALSE) -> 0.45705968
B80: Industry | C80: =VLOOKUP($B$78,$A$3:$M$74,9,FALSE) -> 0.25146247 | D80: =VLOOKUP($B$78,$A$3:$M$74,10,FALSE) -> 0.29643085 | E80: =VLOOKUP($B$78,$A$3:$M$74,11,FALSE) -> 0.31707916 | F80: =VLOOKUP($B$78,$A$3:$M$74,12,FALSE) -> 0.32242012 | G80: =VLOOKUP($B$78,$A$3:$M$74,13,FALSE) -> 0.34237249

Sheet Project Report
A1: Financial Modeling and Valuation of Mastercard Inc.
A3: 1. Introduction
A5: Financial modeling is a crucial tool used in corporate finance, investment banking, and equity research to evaluate a company's financial performance and estimate its intrinsic value. This project develops a comprehensive financial model for Mastercard Inc., a global payment technology company. The model forecasts financial performance, analyzes profitability and risk, and estimates the company's valuation using multiple methods.
A7: 2. Objectives of the Study
A9: To analyze the historical financial performance of Mastercard Inc.
A11: To build an integrated three‑statement financial model.
A13: To forecast future financial performance for the period 2025–2029.
A15: To estimate the intrinsic value of the company using DCF, DDM, and relative valuation.
A17: To compare Mastercard with industry competitors using financial ratios.
A19: 3. Company Overview
A21: Mastercard Inc. is a multinational financial services corporation that operates a global payments processing network. The company facilitates electronic payments between consumers, merchants, financial institutions, and governments worldwide.
A23: Key Business Segments:
... A211: Corporate Finance and Valuation Textbooks
